Workbook

Sheet About
L1: Created on: | M1: 12 Apr 25 09:09 UTC
L2: Jira Site: | M2: https://tataunistore.atlassian.net
L3: Jira Query: | M3: project = "UCW" AND "agency[dropdown]" = Netscribes ORDER BY created DESC

Sheet Your Jira Issues
A1: Key | B1: Summary | C1: Status | D1: Priority | E1: Assignee | F1: Reporter | G1: Created | H1: Updated | I1: Total SKU Count | J1: Listing Type - Sorted | K1: Listing Type | L1: L1 for UCW | M1: Closed SKU Count | N1: Listed Option Count | O1: Total Option Count | P1: Brand Name | Q1: Platform. | R1: Comment | S1: TAT (Days) | T1: Brand To resolve | U1: Comment2
A2: UCW-30466 | B2: Necklace category file for Listing in TATA CLIQ | C2: CLOSED | D2: Medium | E2: Sushma Ram | F2: Sushma Ram | G2: 46143.042 | H2: 46147.714 | I2: 4 | J2: E2E | K2: E2E | L2: Jewellery | M2: 4 | N2: 4 | O2: 4 | P2: Saraf RS Jewellery | Q2: Mall | R2: PFA the Summary & Post-Uploaded sheet[^UCW-30466 Post Upload Status_V.2 (1).xlsx] [^Summary.zip] ;[^UCW-30466_LID.xlsx] Hi [@Rajiv Saraf|mailto:hbtraders1973@gmail.com], Please find attached the sheet, where 0 options have been listed. Kindly update the price and inventory, and share the summary once completed. {adf:display=block} {"type":"table","attrs":{"isNumberColumnEnabled":false,"layout":"center","localId":"d5a19c3b-6809-4370-90ac-f019e899de0c"},"content":[{"type":"tableRow","content":[{"type":"tableCell","attrs":{"background":"#44b3e1"},"content":[{"type":"paragraph","content":[{"type":"text","text":"Ticket ID","marks":[{"type":"strong"}]}]}]},{"type":"tableCell","attrs":{"colspan":2,"background":"#44b3e1"},"content":[{"type":"paragraph","content":[{"type":"text","text":"UCW-30466","marks":[{"type":"strong"}]}]}]}]},{"type":"tableRow","content":[{"type":"tableCell","attrs":{"background":"#44b3e1"},"content":[{"type":"paragraph","content":[{"type":"text","text":"Brand Name","marks":[{"type":"strong"}]}]}]},{"type":"tableCell","attrs":{"colspan":2,"background":"#44b3e1"},"content":[{"type":"paragraph","content":[{"type":"text","text":"Saraf RS Jewellery","marks":[{"type":"strong"}]}]}]}]},{"type":"tableRow","content":[{"type":"tableCell","attrs":{"background":"#44b3e1"},"content":[{"type":"paragraph","content":[{"type":"text","text":"Platform","marks":[{"type":"strong"}]}]}]},{"type":"tableCell","attrs":{"colspan":2,"background":"#44b3e1"},"content":[{"type":"paragraph","content":[{"type":"text","text":"Mall","marks":[{"type":"strong"}]}]}]}]},{"type":"tableRow","content":[{"type":"tableCell","attrs":{"background":"#ace5fe"},"content":[{"type":"paragraph","content":[{"type":"text","text":"Particulars","marks":[{"type":"strong"}]}]}]},{"type":"tableCell","attrs":{"background":"#ace5fe"},"content":[{"type":"paragraph","content":[{"type":"text","text":"SKU Count","marks":[{"type":"strong"}]}]}]},{"type":"tableCell","attrs":{"background":"#ace5fe"},"content":[{"type":"paragraph","content":[{"type":"text","text":"Option Count","marks":[{"type":"strong"}]}]}]}]},{"type":"tableRow","content":[{"type":"tableCell","attrs":{"background":"white"},"content":[{"type":"paragraph","content":[{"type":"text","text":"Received"}]}]},{"type":"tableCell","attrs":{"background":"white"},"content":[{"type":"paragraph","content":[{"type":"text","text":"4"}]}]},{"type":"tableCell","attrs":{"background":"white"},"content":[{"type":"paragraph","content":[{"type":"text","text":"4"}]}]}]},{"type":"tableRow","content":[{"type":"tableCell","attrs":{"background":"white"},"content":[{"type":"paragraph","content":[{"type":"text","text":"Uploaded"}]}]},{"type":"tableCell","attrs":{"background":"white"},"content":[{"type":"paragraph","content":[{"type":"text","text":"4"}]}]},{"type":"tableCell","attrs":{"background":"white"},"content":[{"type":"paragraph","content":[{"type":"text","text":"0"}]}]}]},{"type":"tableRow","content":[{"type":"tableCell","attrs":{"background":"white"},"content":[{"type":"paragraph","content":[{"type":"text","text":"Not Uploaded"}]}]},{"type":"tableCell","attrs":{"background":"white"},"content":[{"type":"paragraph","content":[{"type":"text","text":"0"}]}]},{"type":"tableCell","attrs":{"background":"white"},"content":[{"type":"paragraph","content":[{"type":"text","text":"4"}]}]}]},{"type":"tableRow","content":[{"type":"tableCell","attrs":{"background":"white"},"content":[{"type":"paragraph","content":[{"type":"text","text":"LIDs Shared"}]}]},{"type":"tableCell","attrs":{"background":"white"},"content":[{"type":"paragraph","content":[{"type":"text","text":"4"}]}]},{"type":"tableCell","attrs":{"background":"white"},"content":[{"type":"paragraph","content":[{"type":"text","text":"0"}]}]}]},{"type":"tableRow","content":[{"type":"tableCell","attrs":{"background":"white"},"content":[{"type":"paragraph","content":[{"type":"text","text":"LIDs Stuck in the System"}]}]},{"type":"tableCell","attrs":{"background":"white"},"content":[{"type":"paragraph","content":[{"type":"text","text":"0"}]}]},{"type":"tableCell","attrs":{"background":"white"},"content":[{"type":"paragraph","content":[{"type":"text","text":"0"}]}]}]}]} {adf} Regards, Team Netscribes | S2: =IF(OR(G2="",H2=""),"",ROUND(H2-G2,2)) -> 4.67
A3: UCW-30472 | B3: ENRICH_Request for Product Image Update | C3: CLOSED Due to Inactive/Insufficient Information | D3: Medium | E3: netscribes | F3: Sushma Ram | G3: 46143.141 | H3: 46155.545 | I3: 1 | J3: Ad-hoc | K3: Retrigger Image | L3: Beauty & Grooming | M3: 0 | N3: 0 | O3: 1 | P3: Signaxo | Q3: Mall | R3: Duplicate worked on UCW-30480 | S3: =IF(OR(G3="",H3=""),"",ROUND(H3-G3,2)) -> 12.4
A4: UCW-30480 | B4: Enrich_Request for Product Image Update | C4: CLOSED | D4: Medium | E4: Chirag Dubal | F4: Simi Raichel Zachariah | G4: 46143.499 | H4: 46158.65 | I4: 1 | J4: Ad-hoc | K4: Retrigger Image | L4: Beauty & Grooming | M4: 1 | N4: 1 | O4: 1 | P4: signaxo | Q4: Mall | R4: The changes have been successfully updated and are now reflecting on both the Marketplace and Luxury platforms. Please find the attached screenshot for your reference. !image-20260516-100619.png|width=532,alt="image-20260516-100619.png"! !image-20260516-100628.png|width=517,alt="image-20260516-100628.png"! Regards, Team Netscribes | S4: =IF(OR(G4="",H4=""),"",ROUND(H4-G4,2)) -> 15.15
A5: UCW-30488 | B5: New Listings For Gold (21/04/2026) | C5: CLOSED | D5: Medium | E5: netscribes | F5: Sushma Ram | G5: 46143.585 | H5: 46155.713 | I5: 310 | J5: E2E | K5: E2E | L5: Jewellery | M5: 310 | N5: 310 | O5: 310 | P5: Joyalukkas | Q5: Mall | R5: PFA the Summary & Post-uploaded sheet[^UCW-30488 Post Upload Status_V.2 (1).xlsx] [^Summary.zip] ;[^UCW-30488_LID.xlsx] Hi [@Haripriya Nagaraj|mailto:haripriyanr@joyalukkas.com], Please find attached the sheet, where 310 options have been listed. Kindly update the price and inventory, and share the summary once completed. {adf:display=block} {"type":"table","attrs":{"isNumberColumnEnabled":false,"layout":"center","localId":"6a66edf7-d329-4239-87f3-34b68a6ec4a3"},"content":[{"type":"tableRow","content":[{"type":"tableCell","attrs":{"background":"#44b3e1"},"content":[{"type":"paragraph","content":[{"type":"text","text":"Ticket ID","marks":[{"type":"strong"}]}]}]},{"type":"tableCell","attrs":{"colspan":2,"background":"#44b3e1"},"content":[{"type":"paragraph","content":[{"type":"text","text":"UCW-30488","marks":[{"type":"strong"}]}]}]}]},{"type":"tableRow","content":[{"type":"tableCell","attrs":{"background":"#44b3e1"},"content":[{"type":"paragraph","content":[{"type":"text","text":"Brand Name","marks":[{"type":"strong"}]}]}]},{"type":"tableCell","attrs":{"colspan":2,"background":"#44b3e1"},"content":[{"type":"paragraph","content":[{"type":"text","text":"Joyalukkas","marks":[{"type":"strong"}]}]}]}]},{"type":"tableRow","content":[{"type":"tableCell","attrs":{"background":"#44b3e1"},"content":[{"type":"paragraph","content":[{"type":"text","text":"Platform","marks":[{"type":"strong"}]}]}]},{"type":"tableCell","attrs":{"colspan":2,"background":"#44b3e1"},"content":[{"type":"paragraph","content":[{"type":"text","text":"Mall","marks":[{"type":"strong"}]}]}]}]},{"type":"tableRow","content":[{"type":"tableCell","attrs":{"background":"#ace5fe"},"content":[{"type":"paragraph","content":[{"type":"text","text":"Particulars","marks":[{"type":"strong"}]}]}]},{"type":"tableCell","attrs":{"background":"#ace5fe"},"content":[{"type":"paragraph","content":[{"type":"text","text":"SKU Count","marks":[{"type":"strong"}]}]}]},{"type":"tableCell","attrs":{"background":"#ace5fe"},"content":[{"type":"paragraph","content":[{"type":"text","text":"Option Count","marks":[{"type":"strong"}]}]}]}]},{"type":"tableRow","content":[{"type":"tableCell","attrs":{"background":"white"},"content":[{"type":"paragraph","content":[{"type":"text","text":"Received"}]}]},{"type":"tableCell","attrs":{"background":"white"},"content":[{"type":"paragraph","content":[{"type":"text","text":"310"}]}]},{"type":"tableCell","attrs":{"background":"white"},"content":[{"type":"paragraph","content":[{"type":"text","text":"310"}]}]}]},{"type":"tableRow","content":[{"type":"tableCell","attrs":{"background":"white"},"content":[{"type":"paragraph","content":[{"type":"text","text":"Uploaded"}]}]},{"type":"tableCell","attrs":{"background":"white"},"content":[{"type":"paragraph","content":[{"type":"text","text":"310"}]}]},{"type":"tableCell","attrs":{"background":"white"},"content":[{"type":"paragraph","content":[{"type":"text","text":"310"}]}]}]},{"type":"tableRow","content":[{"type":"tableCell","attrs":{"background":"white"},"content":[{"type":"paragraph","content":[{"type":"text","text":"Not Uploaded"}]}]},{"type":"tableCell","attrs":{"background":"white"},"content":[{"type":"paragraph","content":[{"type":"text","text":"0"}]}]},{"type":"tableCell","attrs":{"background":"white"},"content":[{"type":"paragraph","content":[{"type":"text","text":"0"}]}]}]},{"type":"tableRow","content":[{"type":"tableCell","attrs":{"background":"white"},"content":[{"type":"paragraph","content":[{"type":"text","text":"LIDs Shared"}]}]},{"type":"tableCell","attrs":{"background":"white"},"content":[{"type":"paragraph","content":[{"type":"text","text":"310"}]}]},{"type":"tableCell","attrs":{"background":"white"},"content":[{"type":"paragraph","content":[{"type":"text","text":"310"}]}]}]},{"type":"tableRow","content":[{"type":"tableCell","attrs":{"background":"white"},"content":[{"type":"paragraph","content":[{"type":"text","text":"LIDs Stuck in the System"}]}]},{"type":"tableCell","attrs":{"background":"white"},"content":[{"type":"paragraph","content":[{"type":"text","text":"0"}]}]},{"type":"tableCell","attrs":{"background":"white"},"content":[{"type":"paragraph","content":[{"type":"text","text":"0"}]}]}]}]} {adf} Regards, Team Netscribes | S5: =IF(OR(G5="",H5=""),"",ROUND(H5-G5,2)) -> 12.13
A6: UCW-30497 | B6: Brand Name: SaintG, Category: Footwear, Seller Code: 128447/128537, Listing Type: New Listing, No of SKus:468 No of Options:78 Date:15.04.2026 | C6: CLOSED | D6: Medium | E6: netscribes | F6: Sushma Ram | G6: 46143.658 | H6: 46155.713 | I6: 468 | J6: E2E | K6: E2E+Dual Listing | L6: Footwear | M6: 36 | N6: 6 | O6: 78 | P6: Saint G | Q6: Mall;Luxury | R6: We have successfully uploaded this batch. Please find the attached summary sheet and summary report.[^Summary.zip] [^Post Upload Status_V.2 (1).xlsx] ;[^UCW-30497_LID.xlsx] Hi [@Sagar|mailto:sagar@saintgshoes.com], Please find attached the sheet, where 6 options on Mall and 6 options on Luxury have been listed. Kindly update the price and inventory, and share the summary once completed. {adf:display=block} {"type":"table","attrs":{"isNumberColumnEnabled":false,"layout":"center","localId":"23970458-106d-4aff-b4bf-ffaa8c29047f"},"content":[{"type":"tableRow","content":[{"type":"tableCell","attrs":{"background":"#4d93d9"},"content":[{"type":"paragraph","content":[{"type":"text","text":"Ticket ID","marks":[{"type":"strong"}]}]}]},{"type":"tableCell","attrs":{"colspan":4,"background":"#4d93d9"},"content":[{"type":"paragraph","content":[{"type":"text","text":"UCW-30497","marks":[{"type":"strong"}]}]}]}]},{"type":"tableRow","content":[{"type":"tableCell","attrs":{"background":"#4d93d9"},"content":[{"type":"paragraph","content":[{"type":"text","text":"Brand Name","marks":[{"type":"strong"}]}]}]},{"type":"tableCell","attrs":{"colspan":4,"background":"#4d93d9"},"content":[{"type":"paragraph","content":[{"type":"text","text":"Saint G","marks":[{"type":"strong"}]}]}]}]},{"type":"tableRow","content":[{"type":"tableCell","attrs":{"background":"#ace5fe"},"content":[{"type":"paragraph","content":[{"type":"text","text":"Platform","marks":[{"type":"strong"}]}]}]},{"type":"tableCell","attrs":{"colspan":2,"background":"#ace5fe"},"content":[{"type":"paragraph","content":[{"type":"text","text":"Mall","marks":[{"type":"strong"}]}]}]},{"type":"tableCell","attrs":{"colspan":2,"background":"#ace5fe"},"content":[{"type":"paragraph","content":[{"type":"text","text":"Luxury","marks":[{"type":"strong"}]}]}]}]},{"type":"tableRow","content":[{"type":"tableCell","attrs":{"background":"#ace5fe"},"content":[{"type":"paragraph","content":[{"type":"text","text":"Particulars","marks":[{"type":"strong"}]}]}]},{"type":"tableCell","attrs":{"background":"#ace5fe"},"content":[{"type":"paragraph","content":[{"type":"text","text":"SKU Count","marks":[{"type":"strong"}]}]}]},{"type":"tableCell","attrs":{"background":"#ace5fe"},"content":[{"type":"paragraph","content":[{"type":"text","text":"Option Count","marks":[{"type":"strong"}]}]}]},{"type":"tableCell","attrs":{"background":"#ace5fe"},"content":[{"type":"paragraph","content":[{"type":"text","text":"SKU Count","marks":[{"type":"strong"}]}]}]},{"type":"tableCell","attrs":{"background":"#ace5fe"},"content":[{"type":"paragraph","content":[{"type":"text","text":"Option Count","marks":[{"type":"strong"}]}]}]}]},{"type":"tableRow","content":[{"type":"tableCell","attrs":{"background":"white"},"content":[{"type":"paragraph","content":[{"type":"text","text":"Received"}]}]},{"type":"tableCell","attrs":{"background":"white"},"content":[{"type":"paragraph","content":[{"type":"text","text":"468"}]}]},{"type":"tableCell","attrs":{"background":"white"},"content":[{"type":"paragraph","content":[{"type":"text","text":"78"}]}]},{"type":"tableCell","attrs":{"background":"white"},"content":[{"type":"paragraph","content":[{"type":"text","text":"468"}]}]},{"type":"tableCell","attrs":{"background":"white"},"content":[{"type":"paragraph","content":[{"type":"text","text":"78"}]}]}]},{"type":"tableRow","content":[{"type":"tableCell","attrs":{"background":"white"},"content":[{"type":"paragraph","content":[{"type":"text","text":"Uploaded"}]}]},{"type":"tableCell","attrs":{"background":"white"},"content":[{"type":"paragraph","content":[{"type":"text","text":"36"}]}]},{"type":"tableCell","attrs":{"background":"white"},"content":[{"type":"paragraph","content":[{"type":"text","text":"6"}]}]},{"type":"tableCell","attrs":{"background":"white"},"content":[{"type":"paragraph","content":[{"type":"text","text":"36"}]}]},{"type":"tableCell","attrs":{"background":"white"},"content":[{"type":"paragraph","content":[{"type":"text","text":"6"}]}]}]},{"type":"tableRow","content":[{"type":"tableCell","attrs":{"background":"white"},"content":[{"type":"paragraph","content":[{"type":"text","text":"SKUs Not Uploaded"}]}]},{"type":"tableCell","attrs":{"background":"white"},"content":[{"type":"paragraph","content":[{"type":"text","text":"432"}]}]},{"type":"tableCell","attrs":{"background":"white"},"content":[{"type":"paragraph","content":[{"type":"text","text":"72"}]}]},{"type":"tableCell","attrs":{"background":"white"},"content":[{"type":"paragraph","content":[{"type":"text","text":"432"}]}]},{"type":"tableCell","attrs":{"background":"white"},"content":[{"type":"paragraph","content":[{"type":"text","text":"72"}]}]}]},{"type":"tableRow","content":[{"type":"tableCell","attrs":{"background":"white"},"content":[{"type":"paragraph","content":[{"type":"text","text":"LIDs Shared"}]}]},{"type":"tableCell","attrs":{"background":"white"},"content":[{"type":"paragraph","content":[{"type":"text","text":"36"}]}]},{"type":"tableCell","attrs":{"background":"white"},"content":[{"type":"paragraph","content":[{"type":"text","text":"6"}]}]},{"type":"tableCell","attrs":{"background":"white"},"content":[{"type":"paragraph","content":[{"type":"text","text":"36"}]}]},{"type":"tableCell","attrs":{"background":"white"},"content":[{"type":"paragraph","content":[{"type":"text","text":"6"}]}]}]},{"type":"tableRow","content":[{"type":"tableCell","attrs":{"background":"white"},"content":[{"type":"paragraph","content":[{"type":"text","text":"LIDs Stuck in the System"}]}]},{"type":"tableCell","attrs":{"background":"white"},"content":[{"type":"paragraph","content":[{"type":"text","text":"0"}]}]},{"type":"tableCell","attrs":{"background":"white"},"content":[{"type":"paragraph","content":[{"type":"text","text":"0"}]}]},{"type":"tableCell","attrs":{"background":"white"},"content":[{"type":"paragraph","content":[{"type":"text","text":"0"}]}]},{"type":"tableCell","attrs":{"background":"white"},"content":[{"type":"paragraph","content":[{"type":"text","text":"0"}]}]}]}]} {adf} Regards, Team Netscribes | S6: =IF(OR(G6="",H6=""),"",ROUND(H6-G6,2)) -> 12.06
A7: UCW-30523 | B7: TQ | Brand: Converse | Catalog Listing | SP26 Elevation Style. | C7: CLOSED | D7: Medium | E7: Chirag Dubal | F7: Shloka Chakre | G7: 46143.81 | H7: 46147.78 | I7: 59 | J7: E2E | K7: E2E+Dual Listing | L7: Footwear | M7: 59 | N7: 11 | O7: 11 | P7: Converse | Q7: Mall;Luxury | R7: We have successfully uploaded this batch. Please find the attached summary sheet and summary report.[^Post Upload Status_V.2 (1).xlsx] [^Summary.zip] ;[^UCW-30523_LID.xlsx] Hi [@Amit Kumar|mailto:amit@bhaane.com], Please find attached the sheet, where 9 options have been listed on Luxury and 11 options have been listed on Marketplace platform. Kindly update the price and inventory, and share the summary once completed. {adf:display=block} {"type":"table","attrs":{"isNumberColumnEnabled":false,"layout":"center","localId":"53f03b1a-a495-44eb-b6f6-c3f00175a829"},"content":[{"type":"tableRow","content":[{"type":"tableCell","attrs":{"background":"#4d93d9"},"content":[{"type":"paragraph","content":[{"type":"text","text":"Ticket ID","marks":[{"type":"strong"}]}]}]},{"type":"tableCell","attrs":{"colspan":4,"background":"#4d93d9"},"content":[{"type":"paragraph","content":[{"type":"text","text":"UCW-30523","marks":[{"type":"strong"}]}]}]}]},{"type":"tableRow","content":[{"type":"tableCell","attrs":{"background":"#4d93d9"},"content":[{"type":"paragraph","content":[{"type":"text","text":"Brand Name","marks":[{"type":"strong"}]}]}]},{"type":"tableCell","attrs":{"colspan":4,"background":"#4d93d9"},"content":[{"type":"paragraph","content":[{"type":"text","text":"Converse","marks":[{"type":"strong"}]}]}]}]},{"type":"tableRow","content":[{"type":"tableCell","attrs":{"background":"#ace5fe"},"content":[{"type":"paragraph","content":[{"type":"text","text":"Platform","marks":[{"type":"strong"}]}]}]},{"type":"tableCell","attrs":{"colspan":2,"background":"#ace5fe"},"content":[{"type":"paragraph","content":[{"type":"text","text":"Luxury","marks":[{"type":"strong"}]}]}]},{"type":"tableCell","attrs":{"colspan":2,"background":"#ace5fe"},"content":[{"type":"paragraph","content":[{"type":"text","text":"Marketplace","marks":[{"type":"strong"}]}]}]}]},{"type":"tableRow","content":[{"type":"tableCell","attrs":{"background":"#ace5fe"},"content":[{"type":"paragraph","content":[{"type":"text","text":"Particulars","marks":[{"type":"strong"}]}]}]},{"type":"tableCell","attrs":{"background":"#ace5fe"},"content":[{"type":"paragraph","content":[{"type":"text","text":"SKU Count","marks":[{"type":"strong"}]}]}]},{"type":"tableCell","attrs":{"background":"#ace5fe"},"content":[{"type":"paragraph","content":[{"type":"text","text":"Option Count","marks":[{"type":"strong"}]}]}]},{"type":"tableCell","attrs":{"background":"#ace5fe"},"content":[{"type":"paragraph","content":[{"type":"text","text":"SKU Count","marks":[{"type":"strong"}]}]}]},{"type":"tableCell","attrs":{"background":"#ace5fe"},"content":[{"type":"paragraph","content":[{"type":"text","text":"Option Count","marks":[{"type":"strong"}]}]}]}]},{"type":"tableRow","content":[{"type":"tableCell","attrs":{"background":"white"},"content":[{"type":"paragraph","content":[{"type":"text","text":"Received"}]}]},{"type":"tableCell","attrs":{"background":"white"},"content":[{"type":"paragraph","content":[{"type":"text","text":"59"}]}]},{"type":"tableCell","attrs":{"background":"white"},"content":[{"type":"paragraph","content":[{"type":"text","text":"11"}]}]},{"type":"tableCell","attrs":{"background":"white"},"content":[{"type":"paragraph","content":[{"type":"text","text":"59"}]}]},{"type":"tableCell","attrs":{"background":"white"},"content":[{"type":"paragraph","content":[{"type":"text","text":"11"}]}]}]},{"type":"tableRow","content":[{"type":"tableCell","attrs":{"background":"white"},"content":[{"type":"paragraph","content":[{"type":"text","text":"Uploaded"}]}]},{"type":"tableCell","attrs":{"background":"white"},"content":[{"type":"paragraph","content":[{"type":"text","text":"49"}]}]},{"type":"tableCell","attrs":{"background":"white"},"content":[{"type":"paragraph","content":[{"type":"text","text":"9"}]}]},{"type":"tableCell","attrs":{"background":"white"},"content":[{"type":"paragraph","content":[{"type":"text","text":"59"}]}]},{"type":"tableCell","attrs":{"background":"white"},"content":[{"type":"paragraph","content":[{"type":"text","text":"11"}]}]}]},{"type":"tableRow","content":[{"type":"tableCell","attrs":{"background":"white"},"content":[{"type":"paragraph","content":[{"type":"text","text":"SKUs Not Uploaded"}]}]},{"type":"tableCell","attrs":{"background":"white"},"content":[{"type":"paragraph","content":[{"type":"text","text":"10"}]}]},{"type":"tableCell","attrs":{"background":"white"},"content":[{"type":"paragraph","content":[{"type":"text","text":"2"}]}]},{"type":"tableCell","attrs":{"background":"white"},"content":[{"type":"paragraph","content":[{"type":"text","text":"0"}]}]},{"type":"tableCell","attrs":{"background":"white"},"content":[{"type":"paragraph","content":[{"type":"text","text":"0"}]}]}]},{"type":"tableRow","content":[{"type":"tableCell","attrs":{"background":"white"},"content":[{"type":"paragraph","content":[{"type":"text","text":"LIDs Shared"}]}]},{"type":"tableCell","attrs":{"background":"white"},"content":[{"type":"paragraph","content":[{"type":"text","text":"49"}]}]},{"type":"tableCell","attrs":{"background":"white"},"content":[{"type":"paragraph","content":[{"type":"text","text":"9"}]}]},{"type":"tableCell","attrs":{"background":"white"},"content":[{"type":"paragraph","content":[{"type":"text","text":"59"}]}]},{"type":"tableCell","attrs":{"background":"white"},"content":[{"type":"paragraph","content":[{"type":"text","text":"11"}]}]}]},{"type":"tableRow","content":[{"type":"tableCell","attrs":{"background":"white"},"content":[{"type":"paragraph","content":[{"type":"text","text":"LIDs Stuck in the System"}]}]},{"type":"tableCell","attrs":{"background":"white"},"content":[{"type":"paragraph","content":[{"type":"text","text":"0"}]}]},{"type":"tableCell","attrs":{"background":"white"},"content":[{"type":"paragraph","content":[{"type":"text","text":"0"}]}]},{"type":"tableCell","attrs":{"background":"white"},"content":[{"type":"paragraph","content":[{"type":"text","text":"0"}]}]},{"type":"tableCell","attrs":{"background":"white"},"content":[{"type":"paragraph","content":[{"type":"text","text":"0"}]}]}]}]} {adf} Regards, Team Netscribes | S7: =IF(OR(G7="",H7=""),"",ROUND(H7-G7,2)) -> 3.97
A8: UCW-30530 | B8: Inventory Report : Titan || Tata Cliq | C8: CLOSED | D8: Medium | E8: netscribes | F8: Shraddha Dighe | G8: 46143.865 | H8: 46155.738 | I8: 39 | J8: Ad-hoc | K8: E2E Relisting-SKU change | L8: HOME | M8: 39 | N8: 39 | O8: 39 | P8: Titan | Q8: Mall | S8: =IF(OR(G8="",H8=""),"",ROUND(H8-G8,2)) -> 11.87
A9: UCW-30531 | B9: Libas Apparel 127532 29-04-2026 (NEW CATALOGUE) | C9: CLOSED | D9: Medium | E9: Chirag Dubal | F9: Shraddha Dighe | G9: 46143.899 | H9: 46146.507 | I9: 228 | J9: E2E | K9: E2E | L9: Apparel | M9: 228 | N9: 228 | O9: 228 | P9: Libas | Q9: Mall | R9: PFA the Post Upload Sheet & Summary. [^Post Upload Status_UCW-30531.xlsx] [^Summary.zip] ;[^Post Upload Status_UCW-30531 (2cce4ea3-b227-4d35-a7f5-9c50af3dbd64).xlsx] Please find attached the sheet, where 228 options of Women's Apparel have been listed. Kindly update the price and inventory, and share the summary once completed. {color:#ffffff}__{color} {adf:display=block} {"type":"table","attrs":{"isNumberColumnEnabled":false,"layout":"center","localId":"87860848-2008-47fa-832b-193ecbcbe1e8"},"content":[{"type":"tableRow","content":[{"type":"tableCell","attrs":{"background":"#44b3e1"},"content":[{"type":"paragraph","content":[{"type":"text","text":"Ticket ID","marks":[{"type":"strong"}]}]}]},{"type":"tableCell","attrs":{"colspan":2,"background":"#44b3e1"},"content":[{"type":"paragraph","content":[{"type":"text","text":"UCW-30531","marks":[{"type":"strong"}]}]}]}]},{"type":"tableRow","content":[{"type":"tableCell","attrs":{"background":"#44b3e1"},"content":[{"type":"paragraph","content":[{"type":"text","text":"Brand Name","marks":[{"type":"strong"}]}]}]},{"type":"tableCell","attrs":{"colspan":2,"background":"#44b3e1"},"content":[{"type":"paragraph","content":[{"type":"text","text":"Libas","marks":[{"type":"strong"}]}]}]}]},{"type":"tableRow","content":[{"type":"tableCell","attrs":{"background":"#ace5fe"},"content":[{"type":"paragraph","content":[{"type":"text","text":"Platform","marks":[{"type":"strong"}]}]}]},{"type":"tableCell","attrs":{"colspan":2,"background":"#ace5fe"},"content":[{"type":"paragraph","content":[{"type":"text","text":"Mall","marks":[{"type":"strong"}]}]}]}]},{"type":"tableRow","content":[{"type":"tableCell","attrs":{"background":"#ace5fe"},"content":[{"type":"paragraph","content":[{"type":"text","text":"Particulars","marks":[{"type":"strong"}]}]}]},{"type":"tableCell","attrs":{"background":"#ace5fe"},"content":[{"type":"paragraph","content":[{"type":"text","text":"SKU Count","marks":[{"type":"strong"}]}]}]},{"type":"tableCell","attrs":{"background":"#ace5fe"},"content":[{"type":"paragraph","content":[{"type":"text","text":"Option Count","marks":[{"type":"strong"}]}]}]}]},{"type":"tableRow","content":[{"type":"tableCell","attrs":{"background":"white"},"content":[{"type":"paragraph","content":[{"type":"text","text":"Received"}]}]},{"type":"tableCell","attrs":{},"content":[{"type":"paragraph","content":[{"type":"text","text":"228"}]}]},{"type":"tableCell","attrs":{},"content":[{"type":"paragraph","content":[{"type":"text","text":"228"}]}]}]},{"type":"tableRow","content":[{"type":"tableCell","attrs":{"background":"white"},"content":[{"type":"paragraph","content":[{"type":"text","text":"Uploaded"}]}]},{"type":"tableCell","attrs":{},"content":[{"type":"paragraph","content":[{"type":"text","text":"228"}]}]},{"type":"tableCell","attrs":{},"content":[{"type":"paragraph","content":[{"type":"text","text":"228"}]}]}]},{"type":"tableRow","content":[{"type":"tableCell","attrs":{"background":"white"},"content":[{"type":"paragraph","content":[{"type":"text","text":"LIDs Shared"}]}]},{"type":"tableCell","attrs":{},"content":[{"type":"paragraph","content":[{"type":"text","text":"228"}]}]},{"type":"tableCell","attrs":{},"content":[{"type":"paragraph","content":[{"type":"text","text":"228"}]}]}]},{"type":"tableRow","content":[{"type":"tableCell","attrs":{"background":"white"},"content":[{"type":"paragraph","content":[{"type":"text","text":"LIDs Stuck in the System"}]}]},{"type":"tableCell","attrs":{},"content":[{"type":"paragraph","content":[{"type":"text","text":"0"}]}]},{"type":"tableCell","attrs":{},"content":[{"type":"paragraph","content":[{"type":"text","text":"0"}]}]}]}]} {adf} | S9: =IF(OR(G9="",H9=""),"",ROUND(H9-G9,2)) -> 2.61
A10: UCW-30533 | B10: 22 Pro Listing File ( SS26) | C10: CLOSED | D10: Medium | E10: Chirag Dubal | F10: Shraddha Dighe | G10: 46143.947 | H10: 46155.738 | I10: 107 | J10: E2E | K10: E2E | L10: Apparel | M10: 84 | N10: 17 | O10: 21 | P10: Juniper | Q10: Mall | R10: PFA the Post Upload Sheet & Summary. [^Post Upload Status_UCW-30533.xlsx] [^Summary.zip] ;[^UCW-30533_LID.xlsx] Hi [@chandramohan Juniper|mailto:chandramohan@juniperfashion.com], Please find attached the sheet, where 17 options have been listed. Kindly update the price and inventory, and share the summary once completed. {adf:display=block} {"type":"table","attrs":{"isNumberColumnEnabled":false,"layout":"center","localId":"bf77685b-d7d5-4317-a398-70d1e447105a"},"content":[{"type":"tableRow","content":[{"type":"tableCell","attrs":{"background":"#44b3e1"},"content":[{"type":"paragraph","content":[{"type":"text","text":"Ticket ID","marks":[{"type":"strong"}]}]}]},{"type":"tableCell","attrs":{"colspan":2,"background":"#44b3e1"},"content":[{"type":"paragraph","content":[{"type":"text","text":"UCW-30533","marks":[{"type":"strong"}]}]}]}]},{"type":"tableRow","content":[{"type":"tableCell","attrs":{"background":"#44b3e1"},"content":[{"type":"paragraph","content":[{"type":"text","text":"Brand Name","marks":[{"type":"strong"}]}]}]},{"type":"tableCell","attrs":{"colspan":2,"background":"#44b3e1"},"content":[{"type":"paragraph","content":[{"type":"text","text":"Juniper","marks":[{"type":"strong"}]}]}]}]},{"type":"tableRow","content":[{"type":"tableCell","attrs":{"background":"#44b3e1"},"content":[{"type":"paragraph","content":[{"type":"text","text":"Platform","marks":[{"type":"strong"}]}]}]},{"type":"tableCell","attrs":{"colspan":2,"background":"#44b3e1"},"content":[{"type":"paragraph","content":[{"type":"text","text":"Mall","marks":[{"type":"strong"}]}]}]}]},{"type":"tableRow","content":[{"type":"tableCell","attrs":{"background":"#ace5fe"},"content":[{"type":"paragraph","content":[{"type":"text","text":"Particulars","marks":[{"type":"strong"}]}]}]},{"type":"tableCell","attrs":{"background":"#ace5fe"},"content":[{"type":"paragraph","content":[{"type":"text","text":"SKU Count","marks":[{"type":"strong"}]}]}]},{"type":"tableCell","attrs":{"background":"#ace5fe"},"content":[{"type":"paragraph","content":[{"type":"text","text":"Option Count","marks":[{"type":"strong"}]}]}]}]},{"type":"tableRow","content":[{"type":"tableCell","attrs":{"background":"white"},"content":[{"type":"paragraph","content":[{"type":"text","text":"Received"}]}]},{"type":"tableCell","attrs":{"background":"white"},"content":[{"type":"paragraph","content":[{"type":"text","text":"107"}]}]},{"type":"tableCell","attrs":{"background":"white"},"content":[{"type":"paragraph","content":[{"type":"text","text":"21"}]}]}]},{"type":"tableRow","content":[{"type":"tableCell","attrs":{"background":"white"},"content":[{"type":"paragraph","content":[{"type":"text","text":"Uploaded"}]}]},{"type":"tableCell","attrs":{"background":"white"},"content":[{"type":"paragraph","content":[{"type":"text","text":"84"}]}]},{"type":"tableCell","attrs":{"background":"white"},"content":[{"type":"paragraph","content":[{"type":"text","text":"17"}]}]}]},{"type":"tableRow","content":[{"type":"tableCell","attrs":{"background":"white"},"content":[{"type":"paragraph","content":[{"type":"text","text":"Not Uploaded"}]}]},{"type":"tableCell","attrs":{"background":"white"},"content":[{"type":"paragraph","content":[{"type":"text","text":"23"}]}]},{"type":"tableCell","attrs":{"background":"white"},"content":[{"type":"paragraph","content":[{"type":"text","text":"4"}]}]}]},{"type":"tableRow","content":[{"type":"tableCell","attrs":{"background":"white"},"content":[{"type":"paragraph","content":[{"type":"text","text":"LIDs Shared"}]}]},{"type":"tableCell","attrs":{"background":"white"},"content":[{"type":"paragraph","content":[{"type":"text","text":"84"}]}]},{"type":"tableCell","attrs":{"background":"white"},"content":[{"type":"paragraph","content":[{"type":"text","text":"17"}]}]}]},{"type":"tableRow","content":[{"type":"tableCell","attrs":{"background":"white"},"content":[{"type":"paragraph","content":[{"type":"text","text":"LIDs Stuck in the System"}]}]},{"type":"tableCell","attrs":{"background":"white"},"content":[{"type":"paragraph","content":[{"type":"text","text":"0"}]}]},{"type":"tableCell","attrs":{"background":"white"},"content":[{"type":"paragraph","content":[{"type":"text","text":"0"}]}]}]}]} {adf} Regards, Team Netscribes | S10: =IF(OR(G10="",H10=""),"",ROUND(H10-G10,2)) -> 11.79
A11: UCW-30534 | B11: Support Required for Bulk Category-wise Listing Upload - Rajnandini | C11: CLOSED | D11: Medium | E11: Chirag Dubal | F11: Shraddha Dighe | G11: 46143.969 | H11: 46150.599 | I11: 342 | J11: E2E | K11: E2E | L11: Apparel | M11: 332 | N11: 55 | O11: 57 | P11: Rajnandini | Q11: Mall | R11: PFA the Post Upload Sheet & Summary. [^Post Upload Status_30534.xlsx] [^Summary.zip] ;[^UCW-30534_LID.xlsx] Hi [@Jainam Overseas Pvt Ltd|mailto:info@rajnandinifashion.com], Please find attached the sheet, where 55 options have been listed. Kindly update the price and inventory, and share the summary once completed. {adf:display=block} {"type":"table","attrs":{"isNumberColumnEnabled":false,"layout":"center","localId":"f362f5e3-cd32-4f18-8082-fed7cdad9924"},"content":[{"type":"tableRow","content":[{"type":"tableCell","attrs":{"background":"#44b3e1"},"content":[{"type":"paragraph","content":[{"type":"text","text":"Ticket ID","marks":[{"type":"strong"}]}]}]},{"type":"tableCell","attrs":{"colspan":2,"background":"#44b3e1"},"content":[{"type":"paragraph","content":[{"type":"text","text":"UCW-30534","marks":[{"type":"strong"}]}]}]}]},{"type":"tableRow","content":[{"type":"tableCell","attrs":{"background":"#44b3e1"},"content":[{"type":"paragraph","content":[{"type":"text","text":"Brand Name","marks":[{"type":"strong"}]}]}]},{"type":"tableCell","attrs":{"colspan":2,"background":"#44b3e1"},"content":[{"type":"paragraph","content":[{"type":"text","text":"Rajnandini","marks":[{"type":"strong"}]}]}]}]},{"type":"tableRow","content":[{"type":"tableCell","attrs":{"background":"#44b3e1"},"content":[{"type":"paragraph","content":[{"type":"text","text":"Platform","marks":[{"type":"strong"}]}]}]},{"type":"tableCell","attrs":{"colspan":2,"background":"#44b3e1"},"content":[{"type":"paragraph","content":[{"type":"text","text":"Mall","marks":[{"type":"strong"}]}]}]}]},{"type":"tableRow","content":[{"type":"tableCell","attrs":{"background":"#ace5fe"},"content":[{"type":"paragraph","content":[{"type":"text","text":"Particulars","marks":[{"type":"strong"}]}]}]},{"type":"tableCell","attrs":{"background":"#ace5fe"},"content":[{"type":"paragraph","content":[{"type":"text","text":"SKU Count","marks":[{"type":"strong"}]}]}]},{"type":"tableCell","attrs":{"background":"#ace5fe"},"content":[{"type":"paragraph","content":[{"type":"text","text":"Option Count","marks":[{"type":"strong"}]}]}]}]},{"type":"tableRow","content":[{"type":"tableCell","attrs":{"background":"white"},"content":[{"type":"paragraph","content":[{"type":"text","text":"Received"}]}]},{"type":"tableCell","attrs":{"background":"white"},"content":[{"type":"paragraph","content":[{"type":"text","text":"342"}]}]},{"type":"tableCell","attrs":{"background":"white"},"content":[{"type":"paragraph","content":[{"type":"text","text":"57"}]}]}]},{"type":"tableRow","content":[{"type":"tableCell","attrs":{"background":"white"},"content":[{"type":"paragraph","content":[{"type":"text","text":"Uploaded"}]}]},{"type":"tableCell","attrs":{"background":"white"},"content":[{"type":"paragraph","content":[{"type":"text","text":"332"}]}]},{"type":"tableCell","attrs":{"background":"white"},"content":[{"type":"paragraph","content":[{"type":"text","text":"55"}]}]}]},{"type":"tableRow","content":[{"type":"tableCell","attrs":{"background":"white"},"content":[{"type":"paragraph","content":[{"type":"text","text":"Not Uploaded"}]}]},{"type":"tableCell","attrs":{"background":"white"},"content":[{"type":"paragraph","content":[{"type":"text","text":"10"}]}]},{"type":"tableCell","attrs":{"background":"white"},"content":[{"type":"paragraph","content":[{"type":"text","text":"2"}]}]}]},{"type":"tableRow","content":[{"type":"tableCell","attrs":{"background":"white"},"content":[{"type":"paragraph","content":[{"type":"text","text":"LIDs Shared"}]}]},{"type":"tableCell","attrs":{"background":"white"},"content":[{"type":"paragraph","content":[{"type":"text","text":"332"}]}]},{"type":"tableCell","attrs":{"background":"white"},"content":[{"type":"paragraph","content":[{"type":"text","text":"55"}]}]}]},{"type":"tableRow","content":[{"type":"tableCell","attrs":{"background":"white"},"content":[{"type":"paragraph","content":[{"type":"text","text":"LIDs Stuck in the System"}]}]},{"type":"tableCell","attrs":{"background":"white"},"content":[{"type":"paragraph","content":[{"type":"text","text":"0"}]}]},{"type":"tableCell","attrs":{"background":"white"},"content":[{"type":"paragraph","content":[{"type":"text","text":"0"}]}]}]}]} {adf} Regards, Team Netscribes | S11: =IF(OR(G11="",H11=""),"",ROUND(H11-G11,2)) -> 6.63
A12: UCW-30535 | B12: Globus Women's Wear Apparels - 22 Styles - Batch 132 (Brand - Globus Stores Pvt Ltd) (Ethnic Wear) (27.04.2026) | C12: CLOSED | D12: Medium | E12: Chirag Dubal | F12: Shraddha Dighe | G12: 46143.973 | H12: 46155.738 | I12: 88 | J12: E2E | K12: E2E | L12: Apparel | M12: 88 | N12: 22 | O12: 22 | P12: Globus | Q12: Mall | R12: PFA the Post Upload Sheet & Summary. [^Summary.zip] [^Post Upload Status_UCW-30535.xlsx] ;[^UCW-30535_LID.xlsx] Hi [@Ganesh Rolekar|mailto:ganeshr@globusmail.com], Please find attached the sheet, where 22 options have been listed. Kindly update the price and inventory, and share the summary once completed. {adf:display=block} {"type":"table","attrs":{"isNumberColumnEnabled":false,"layout":"center","localId":"a34b7cf4-694c-4b22-8adc-831f4001456a"},"content":[{"type":"tableRow","content":[{"type":"tableCell","attrs":{"background":"#44b3e1"},"content":[{"type":"paragraph","content":[{"type":"text","text":"Ticket ID","marks":[{"type":"strong"}]}]}]},{"type":"tableCell","attrs":{"colspan":2,"background":"#44b3e1"},"content":[{"type":"paragraph","content":[{"type":"text","text":"UCW-30535","marks":[{"type":"strong"}]}]}]}]},{"type":"tableRow","content":[{"type":"tableCell","attrs":{"background":"#44b3e1"},"content":[{"type":"paragraph","content":[{"type":"text","text":"Brand Name","marks":[{"type":"strong"}]}]}]},{"type":"tableCell","attrs":{"colspan":2,"background":"#44b3e1"},"content":[{"type":"paragraph","content":[{"type":"text","text":"Globus ","marks":[{"type":"strong"}]}]}]}]},{"type":"tableRow","content":[{"type":"tableCell","attrs":{"background":"#44b3e1"},"content":[{"type":"paragraph","content":[{"type":"text","text":"Platform","marks":[{"type":"strong"}]}]}]},{"type":"tableCell","attrs":{"colspan":2,"background":"#44b3e1"},"content":[{"type":"paragraph","content":[{"type":"text","text":"Mall","marks":[{"type":"strong"}]}]}]}]},{"type":"tableRow","content":[{"type":"tableCell","attrs":{"background":"#ace5fe"},"content":[{"type":"paragraph","content":[{"type":"text","text":"Particulars","marks":[{"type":"strong"}]}]}]},{"type":"tableCell","attrs":{"background":"#ace5fe"},"content":[{"type":"paragraph","content":[{"type":"text","text":"SKU Count","marks":[{"type":"strong"}]}]}]},{"type":"tableCell","attrs":{"background":"#ace5fe"},"content":[{"type":"paragraph","content":[{"type":"text","text":"Option Count","marks":[{"type":"strong"}]}]}]}]},{"type":"tableRow","content":[{"type":"tableCell","attrs":{"background":"white"},"content":[{"type":"paragraph","content":[{"type":"text","text":"Received"}]}]},{"type":"tableCell","attrs":{"background":"white"},"content":[{"type":"paragraph","content":[{"type":"text","text":"88"}]}]},{"type":"tableCell","attrs":{"background":"white"},"content":[{"type":"paragraph","content":[{"type":"text","text":"22"}]}]}]},{"type":"tableRow","content":[{"type":"tableCell","attrs":{"background":"white"},"content":[{"type":"paragraph","content":[{"type":"text","text":"Uploaded"}]}]},{"type":"tableCell","attrs":{"background":"white"},"content":[{"type":"paragraph","content":[{"type":"text","text":"88"}]}]},{"type":"tableCell","attrs":{"background":"white"},"content":[{"type":"paragraph","content":[{"type":"text","text":"22"}]}]}]},{"type":"tableRow","content":[{"type":"tableCell","attrs":{"background":"white"},"content":[{"type":"paragraph","content":[{"type":"text","text":"Not Uploaded"}]}]},{"type":"tableCell","attrs":{"background":"white"},"content":[{"type":"paragraph","content":[{"type":"text","text":"0"}]}]},{"type":"tableCell","attrs":{"background":"white"},"content":[{"type":"paragraph","content":[{"type":"text","text":"0"}]}]}]},{"type":"tableRow","content":[{"type":"tableCell","attrs":{"background":"white"},"content":[{"type":"paragraph","content":[{"type":"text","text":"LIDs Shared"}]}]},{"type":"tableCell","attrs":{"background":"white"},"content":[{"type":"paragraph","content":[{"type":"text","text":"88"}]}]},{"type":"tableCell","attrs":{"background":"white"},"content":[{"type":"paragraph","content":[{"type":"text","text":"22"}]}]}]},{"type":"tableRow","content":[{"type":"tableCell","attrs":{"background":"white"},"content":[{"type":"paragraph","content":[{"type":"text","text":"LIDs Stuck in the System"}]}]},{"type":"tableCell","attrs":{"background":"white"},"content":[{"type":"paragraph","content":[{"type":"text","text":"0"}]}]},{"type":"tableCell","attrs":{"background":"white"},"content":[{"type":"paragraph","content":[{"type":"text","text":"0"}]}]}]}]} {adf} Regards, Team Netscribes | S12: =IF(OR(G12="",H12=""),"",ROUND(H12-G12,2)) -> 11.76
A13: UCW-30536 | B13: K18 Hair Oil 10ml New Listing | C13: CLOSED | D13: Medium | E13: Chirag Dubal | F13: Shraddha Dighe | G13: 46143.981 | H13: 46149.669 | I13: 1 | J13: E2E | K13: E2E | L13: Beauty & Grooming | M13: 1 | N13: 1 | O13: 1 | P13: K18 | Q13: Mall;Luxury | R13: [^UCW-30536 Post Upload Status_V.2 (1).xlsx] [^Summary.zip] ;[^UCW-30536_LID.xlsx] Hi [@Shobhakant|mailto:Shobhakant@mkexim.co.in], Please find attached the sheet, where 1 options have been listed. Kindly update the price and inventory, and share the summary once completed. {adf:display=block} {"type":"table","attrs":{"isNumberColumnEnabled":false,"layout":"center","localId":"fb22e979-1634-4ff0-8d9b-fe24054db616"},"content":[{"type":"tableRow","content":[{"type":"tableCell","attrs":{"background":"#44b3e1"},"content":[{"type":"paragraph","content":[{"type":"text","text":"Ticket ID","marks":[{"type":"strong"}]}]}]},{"type":"tableCell","attrs":{"colspan":2,"background":"#44b3e1"},"content":[{"type":"paragraph","content":[{"type":"text","text":"UCW-30536","marks":[{"type":"strong"}]}]}]}]},{"type":"tableRow","content":[{"type":"tableCell","attrs":{"background":"#44b3e1"},"content":[{"type":"paragraph","content":[{"type":"text","text":"Brand Name","marks":[{"type":"strong"}]}]}]},{"type":"tableCell","attrs":{"colspan":2,"background":"#44b3e1"},"content":[{"type":"paragraph","content":[{"type":"text","text":"K18","marks":[{"type":"strong"}]}]}]}]},{"type":"tableRow","content":[{"type":"tableCell","attrs":{"background":"#44b3e1"},"content":[{"type":"paragraph","content":[{"type":"text","text":"Platform","marks":[{"type":"strong"}]}]}]},{"type":"tableCell","attrs":{"colspan":2,"background":"#44b3e1"},"content":[{"type":"paragraph","content":[{"type":"text","text":"Mall, Luxury","marks":[{"type":"strong"}]}]}]}]},{"type":"tableRow","content":[{"type":"tableCell","attrs":{"background":"#ace5fe"},"content":[{"type":"paragraph","content":[{"type":"text","text":"Particulars","marks":[{"type":"strong"}]}]}]},{"type":"tableCell","attrs":{"background":"#ace5fe"},"content":[{"type":"paragraph","content":[{"type":"text","text":"SKU Count","marks":[{"type":"strong"}]}]}]},{"type":"tableCell","attrs":{"background":"#ace5fe"},"content":[{"type":"paragraph","content":[{"type":"text","text":"Option Count","marks":[{"type":"strong"}]}]}]}]},{"type":"tableRow","content":[{"type":"tableCell","attrs":{"background":"white"},"content":[{"type":"paragraph","content":[{"type":"text","text":"Received"}]}]},{"type":"tableCell","attrs":{"background":"white"},"content":[{"type":"paragraph","content":[{"type":"text","text":"1"}]}]},{"type":"tableCell","attrs":{"background":"white"},"content":[{"type":"paragraph","content":[{"type":"text","text":"1"}]}]}]},{"type":"tableRow","content":[{"type":"tableCell","attrs":{"background":"white"},"content":[{"type":"paragraph","content":[{"type":"text","text":"Uploaded"}]}]},{"type":"tableCell","attrs":{"background":"white"},"content":[{"type":"paragraph","content":[{"type":"text","text":"1"}]}]},{"type":"tableCell","attrs":{"background":"white"},"content":[{"type":"paragraph","content":[{"type":"text","text":"1"}]}]}]},{"type":"tableRow","content":[{"type":"tableCell","attrs":{"background":"white"},"content":[{"type":"paragraph","content":[{"type":"text","text":"Not Uploaded"}]}]},{"type":"tableCell","attrs":{"background":"white"},"content":[{"type":"paragraph","content":[{"type":"text","text":"0"}]}]},{"type":"tableCell","attrs":{"background":"white"},"content":[{"type":"paragraph","content":[{"type":"text","text":"0"}]}]}]},{"type":"tableRow","content":[{"type":"tableCell","attrs":{"background":"white"},"content":[{"type":"paragraph","content":[{"type":"text","text":"LIDs Shared"}]}]},{"type":"tableCell","attrs":{"background":"white"},"content":[{"type":"paragraph","content":[{"type":"text","text":"1"}]}]},{"type":"tableCell","attrs":{"background":"white"},"content":[{"type":"paragraph","content":[{"type":"text","text":"1"}]}]}]},{"type":"tableRow","content":[{"type":"tableCell","attrs":{"background":"white"},"content":[{"type":"paragraph","content":[{"type":"text","text":"LIDs Stuck in the System"}]}]},{"type":"tableCell","attrs":{"background":"white"},"content":[{"type":"paragraph","content":[{"type":"text","text":"0"}]}]},{"type":"tableCell","attrs":{"background":"white"},"content":[{"type":"paragraph","content":[{"type":"text","text":"0"}]}]}]}]} {adf} Regards, Team Netscribes | S13: =IF(OR(G13="",H13=""),"",ROUND(H13-G13,2)) -> 5.69
A14: UCW-30537 | B14: ENRICH_Image Update: Charcoal Peel Off Mask // Tatacliq | C14: CLOSED | D14: Medium | E14: Chirag Dubal | F14: Shraddha Dighe | G14: 46143.983 | H14: 46145.745 | I14: 1 | J14: Ad-hoc | K14: Retrigger Image | L14: Beauty & Grooming | M14: 1 | N14: 1 | O14: 1 | P14: Love Earth | Q14: Mall | S14: =IF(OR(G14="",H14=""),"",ROUND(H14-G14,2)) -> 1.76
A15: UCW-30543 | B15: Enrichment_Tata Cliq - Image Update - Banderas (29-04-2026) | C15: CLOSED | D15: Medium | E15: Chirag Dubal | F15: Reagan D’souza | G15: 46144.603 | H15: 46161.7 | I15: 2 | J15: Ad-hoc | K15: Retrigger Image | L15: Accessories | M15: 2 | N15: 2 | O15: 2 | P15: Banderas | Q15: Mall | R15: [^Status Of UCW-30543.xlsx] [^Summary.zip] We have updated the images and also attached the summary file. Once the images are successfully reflected we will let you know | S15: =IF(OR(G15="",H15=""),"",ROUND(H15-G15,2)) -> 17.1
A16: UCW-30544 | B16: Error_Hoversoul Batch -9_NC | C16: CLOSED | D16: Medium | E16: Chirag Dubal | F16: Reagan D’souza | G16: 46144.61 | H16: 46155.662 | I16: 10 | J16: Ad-hoc | K16: PDP/PLP QC | L16: Apparel | M16: 10 | N16: 10 | O16: 10 | P16: Hoversoul | Q16: Mall | S16: =IF(OR(G16="",H16=""),"",ROUND(H16-G16,2)) -> 11.05
A17: UCW-30550 | B17: Skechers Add now catalogue dated 15th April 2026 | C17: CLOSED | D17: Medium | E17: Chirag Dubal | F17: netscribes | G17: 46144.631 | H17: 46144.639 | I17: 0 | J17: E2E | K17: E2E | L17: Footwear | M17: 0 | N17: 0 | O17: 0 | P17: Sketchers | Q17: Mall | S17: =IF(OR(G17="",H17=""),"",ROUND(H17-G17,2)) -> 0.01 | U17: No task was assigned for this ticket
A18: UCW-30555 | B18: Error_Andon Cord | Thrice Wrong Product Delivered | Allen Cooper | C18: CLOSED | D18: Medium | E18: Chirag Dubal | F18: Reagan D’souza | G18: 46146.476 | H18: 46158.538 | I18: 5 | J18: Ad-hoc | K18: Detractor Cases | L18: Apparel | M18: 5 | N18: 5 | O18: 5 | P18: Allen Cooper | Q18: Mall | S18: =IF(OR(G18="",H18=""),"",ROUND(H18-G18,2)) -> 12.06
A19: UCW-30557 | B19: Tata Cliq Luxury - New listing - Fragrance MDP (GWP) 02-05-2026 | C19: CLOSED | D19: Medium | E19: Chirag Dubal | F19: Shraddha Dighe | G19: 46146.481 | H19: 46163.626 | I19: 21 | J19: E2E | K19: GWP | L19: Beauty & Grooming | M19: 18 | N19: 18 | O19: 21 | P19: Multiple | Q19: Luxury | R19: [^UCW-30557 Post Upload Status_V.2 (1).xlsx] [^Summary.zip] ; We are pleased to inform you that the listing IDs have been generated successfully. Please find the attached file for your reference, along with the summary table below. You may now proceed with price and inventory pushing from your end. {adf:display=block} {"type":"table","attrs":{"isNumberColumnEnabled":false,"layout":"center","localId":"8589c2e4-7522-4ef0-8968-f2343ea79e9d"},"content":[{"type":"tableRow","content":[{"type":"tableCell","attrs":{"background":"#44b3e1"},"content":[{"type":"paragraph","content":[{"type":"text","text":"Ticket ID","marks":[{"type":"strong"}]}]}]},{"type":"tableCell","attrs":{"colspan":2,"background":"#44b3e1"},"content":[{"type":"paragraph","content":[{"type":"text","text":"UCW-30557","marks":[{"type":"strong"}]}]}]}]},{"type":"tableRow","content":[{"type":"tableCell","attrs":{"background":"#44b3e1"},"content":[{"type":"paragraph","content":[{"type":"text","text":"Brand Name","marks":[{"type":"strong"}]}]}]},{"type":"tableCell","attrs":{"colspan":2,"background":"#44b3e1"},"content":[{"type":"paragraph","content":[{"type":"text","text":"Multiple","marks":[{"type":"strong"}]}]}]}]},{"type":"tableRow","content":[{"type":"tableCell","attrs":{"background":"#ace5fe"},"content":[{"type":"paragraph","content":[{"type":"text","text":"Platform","marks":[{"type":"strong"}]}]}]},{"type":"tableCell","attrs":{"colspan":2,"background":"#ace5fe"},"content":[{"type":"paragraph","content":[{"type":"text","text":"LUX","marks":[{"type":"strong"}]}]}]}]},{"type":"tableRow","content":[{"type":"tableCell","attrs":{"background":"#ace5fe"},"content":[{"type":"paragraph","content":[{"type":"text","text":"Particulars","marks":[{"type":"strong"}]}]}]},{"type":"tableCell","attrs":{"background":"#ace5fe"},"content":[{"type":"paragraph","content":[{"type":"text","text":"SKU Count","marks":[{"type":"strong"}]}]}]},{"type":"tableCell","attrs":{"background":"#ace5fe"},"content":[{"type":"paragraph","content":[{"type":"text","text":"Option Count","marks":[{"type":"strong"}]}]}]}]},{"type":"tableRow","content":[{"type":"tableCell","attrs":{"background":"white"},"content":[{"type":"paragraph","content":[{"type":"text","text":"Received"}]}]},{"type":"tableCell","attrs":{},"content":[{"type":"paragraph","content":[{"type":"text","text":"21"}]}]},{"type":"tableCell","attrs":{},"content":[{"type":"paragraph","content":[{"type":"text","text":"21"}]}]}]},{"type":"tableRow","content":[{"type":"tableCell","attrs":{"background":"white"},"content":[{"type":"paragraph","content":[{"type":"text","text":"Uploaded"}]}]},{"type":"tableCell","attrs":{},"content":[{"type":"paragraph","content":[{"type":"text","text":"18"}]}]},{"type":"tableCell","attrs":{},"content":[{"type":"paragraph","content":[{"type":"text","text":"18"}]}]}]},{"type":"tableRow","content":[{"type":"tableCell","attrs":{"background":"white"},"content":[{"type":"paragraph","content":[{"type":"text","text":"SKUs not uploaded"}]}]},{"type":"tableCell","attrs":{},"content":[{"type":"paragraph","content":[{"type":"text","text":"0"}]}]},{"type":"tableCell","attrs":{},"content":[{"type":"paragraph","content":[{"type":"text","text":"0"}]}]}]},{"type":"tableRow","content":[{"type":"tableCell","attrs":{"background":"white"},"content":[{"type":"paragraph","content":[{"type":"text","text":"Already Listed"}]}]},{"type":"tableCell","attrs":{},"content":[{"type":"paragraph","content":[{"type":"text","text":"3"}]}]},{"type":"tableCell","attrs":{},"content":[{"type":"paragraph","content":[{"type":"text","text":"3"}]}]}]},{"type":"tableRow","content":[{"type":"tableCell","attrs":{"background":"white"},"content":[{"type":"paragraph","content":[{"type":"text","text":"LIDs Shared"}]}]},{"type":"tableCell","attrs":{},"content":[{"type":"paragraph","content":[{"type":"text","text":"18"}]}]},{"type":"tableCell","attrs":{},"content":[{"type":"paragraph","content":[{"type":"text","text":"18"}]}]}]},{"type":"tableRow","content":[{"type":"tableCell","attrs":{"background":"white"},"content":[{"type":"paragraph","content":[{"type":"text","text":"LIDs Stuck in the System"}]}]},{"type":"tableCell","attrs":{},"content":[{"type":"paragraph","content":[{"type":"text","text":"0"}]}]},{"type":"tableCell","attrs":{},"content":[{"type":"paragraph","content":[{"type":"text","text":"0"}]}]}]}]} {adf} With this, we are closing this request from our end. Thank you for your patience, support, and cooperation throughout the process. Your brand is important to us, and we look forward to assisting you again.[^UCW-30557 Post Upload Status_V.2 (1) (54f2d411-e2be-450c-a74f-87f6357ee4dd).xlsx] | S19: =IF(OR(G19="",H19=""),"",ROUND(H19-G19,2)) -> 17.15 | U19: uploaded on 12th and closed on 15th after validating
A20: UCW-30574 | B20: New Listing | CareVeda x TataCliq | 15th April 2026 | C20: CLOSED | D20: Medium | E20: Chirag Dubal | F20: Shraddha Dighe | G20: 46146.534 | H20: 46163.626 | I20: 38 | J20: E2E | K20: E2E | L20: Beauty & Grooming | M20: 38 | N20: 38 | O20: 38 | P20: CareVeda | Q20: Mall | R20: [^UCW-30574 Post Upload Status_V.2 (1).xlsx] [^Summary.zip] ; We are pleased to inform you that the listing IDs have been generated successfully. Please find the attached file for your reference, along with the summary table below. You may now proceed with price and inventory pushing from your end. {adf:display=block} {"type":"table","attrs":{"isNumberColumnEnabled":false,"layout":"center","localId":"a1cb6d57-383a-495c-b682-c7905b8f2490"},"content":[{"type":"tableRow","content":[{"type":"tableCell","attrs":{"background":"#44b3e1"},"content":[{"type":"paragraph","content":[{"type":"text","text":"Ticket ID","marks":[{"type":"strong"}]}]}]},{"type":"tableCell","attrs":{"colspan":2,"background":"#44b3e1"},"content":[{"type":"paragraph","content":[{"type":"text","text":"UCW-30574","marks":[{"type":"strong"}]}]}]}]},{"type":"tableRow","content":[{"type":"tableCell","attrs":{"background":"#44b3e1"},"content":[{"type":"paragraph","content":[{"type":"text","text":"Brand Name","marks":[{"type":"strong"}]}]}]},{"type":"tableCell","attrs":{"colspan":2,"background":"#44b3e1"},"content":[{"type":"paragraph","content":[{"type":"text","text":"CareVeda","marks":[{"type":"strong"}]}]}]}]},{"type":"tableRow","content":[{"type":"tableCell","attrs":{"background":"#ace5fe"},"content":[{"type":"paragraph","content":[{"type":"text","text":"Platform","marks":[{"type":"strong"}]}]}]},{"type":"tableCell","attrs":{"colspan":2,"background":"#ace5fe"},"content":[{"type":"paragraph","content":[{"type":"text","text":"Mall","marks":[{"type":"strong"}]}]}]}]},{"type":"tableRow","content":[{"type":"tableCell","attrs":{"background":"#ace5fe"},"content":[{"type":"paragraph","content":[{"type":"text","text":"Particulars","marks":[{"type":"strong"}]}]}]},{"type":"tableCell","attrs":{"background":"#ace5fe"},"content":[{"type":"paragraph","content":[{"type":"text","text":"SKU Count","marks":[{"type":"strong"}]}]}]},{"type":"tableCell","attrs":{"background":"#ace5fe"},"content":[{"type":"paragraph","content":[{"type":"text","text":"Option Count","marks":[{"type":"strong"}]}]}]}]},{"type":"tableRow","content":[{"type":"tableCell","attrs":{"background":"white"},"content":[{"type":"paragraph","content":[{"type":"text","text":"Received"}]}]},{"type":"tableCell","attrs":{},"content":[{"type":"paragraph","content":[{"type":"text","text":"38"}]}]},{"type":"tableCell","attrs":{},"content":[{"type":"paragraph","content":[{"type":"text","text":"38"}]}]}]},{"type":"tableRow","content":[{"type":"tableCell","attrs":{"background":"white"},"content":[{"type":"paragraph","content":[{"type":"text","text":"Uploaded"}]}]},{"type":"tableCell","attrs":{},"content":[{"type":"paragraph","content":[{"type":"text","text":"38"}]}]},{"type":"tableCell","attrs":{},"content":[{"type":"paragraph","content":[{"type":"text","text":"38"}]}]}]},{"type":"tableRow","content":[{"type":"tableCell","attrs":{"background":"white"},"content":[{"type":"paragraph","content":[{"type":"text","text":"SKUs not uploaded"}]}]},{"type":"tableCell","attrs":{},"content":[{"type":"paragraph","content":[{"type":"text","text":"-"}]}]},{"type":"tableCell","attrs":{},"content":[{"type":"paragraph","content":[{"type":"text","text":"-"}]}]}]},{"type":"tableRow","content":[{"type":"tableCell","attrs":{"background":"white"},"content":[{"type":"paragraph","content":[{"type":"text","text":"Already Listed"}]}]},{"type":"tableCell","attrs":{},"content":[{"type":"paragraph","content":[{"type":"text","text":"-"}]}]},{"type":"tableCell","attrs":{},"content":[{"type":"paragraph","content":[{"type":"text","text":"-"}]}]}]},{"type":"tableRow","content":[{"type":"tableCell","attrs":{"background":"white"},"content":[{"type":"paragraph","content":[{"type":"text","text":"LIDs Shared"}]}]},{"type":"tableCell","attrs":{},"content":[{"type":"paragraph","content":[{"type":"text","text":"38"}]}]},{"type":"tableCell","attrs":{},"content":[{"type":"paragraph","content":[{"type":"text","text":"38"}]}]}]},{"type":"tableRow","content":[{"type":"tableCell","attrs":{"background":"white"},"content":[{"type":"paragraph","content":[{"type":"text","text":"LIDs Stuck in the System"}]}]},{"type":"tableCell","attrs":{},"content":[{"type":"paragraph","content":[{"type":"text","text":"-"}]}]},{"type":"tableCell","attrs":{},"content":[{"type":"paragraph","content":[{"type":"text","text":"-"}]}]}]}]} {adf} With this, we are closing this request from our end. Thank you for your patience, support, and cooperation throughout the process. Your brand is important to us, and we look forward to assisting you again.[^UCW-30574 Post Upload Status_V.2 (1) (110ee1c8-1f29-4577-99d2-5ddc1d8e37bb).xlsx] | S20: =IF(OR(G20="",H20=""),"",ROUND(H20-G20,2)) -> 17.09 | U20: uploaded on 12th and closed on 15th after validating
A21: UCW-30599 | B21: ERROR_PUMA Accessories_Footwear_Apparel 124130 & 125381 New Listing 12-02-2026_NC | C21: CLOSED | D21: Medium | E21: netscribes | F21: netscribes | G21: 46146.589 | H21: 46151.587 | I21: 1205 | J21: Ad-hoc | K21: PDP/PLP QC | L21: Multi Category | M21: 1205 | N21: 1205 | O21: 1205 | P21: PUMA | Q21: Mall;Luxury | R21: [^UCW-26534_Mall.xlsx] [^UCW-26534_Luxury.xlsx] As requested, please find all the LIDs and SKUs wise details in the attached files. Please refer the table below for the summary. Additionally, 1 SKU of MP an LUX each, are not uploaded as the image mismatched with content. So, we requested the brand to share the revised images, post that we will proceed with the listings. As all the actions are taken from our end, we are closing the ticket. Upon receiving the image details, we will create a clone and proceed. {adf:display=block} {"type":"table","attrs":{"isNumberColumnEnabled":false,"layout":"center","localId":"b0409f7f-f8d7-4319-8235-c129ebedbcfb"},"content":[{"type":"tableRow","content":[{"type":"tableCell","attrs":{"background":"#44b3e1"},"content":[{"type":"paragraph","content":[{"type":"text","text":"Ticket ID","marks":[{"type":"strong"}]}]}]},{"type":"tableCell","attrs":{"colspan":4,"background":"#44b3e1"},"content":[{"type":"paragraph","content":[{"type":"text","text":"UCW-28432 / UCW-30599","marks":[{"type":"strong"}]}]}]}]},{"type":"tableRow","content":[{"type":"tableCell","attrs":{"background":"#44b3e1"},"content":[{"type":"paragraph","content":[{"type":"text","text":"Brand Name","marks":[{"type":"strong"}]}]}]},{"type":"tableCell","attrs":{"colspan":4,"background":"#0f9ed5"},"content":[{"type":"paragraph","content":[{"type":"text","text":"PUMA","marks":[{"type":"strong"}]}]}]}]},{"type":"tableRow","content":[{"type":"tableCell","attrs":{"background":"#ace5fe"},"content":[{"type":"paragraph","content":[{"type":"text","text":"Platform","marks":[{"type":"strong"}]}]}]},{"type":"tableCell","attrs":{"colspan":2,"background":"#ace5fe"},"content":[{"type":"paragraph","content":[{"type":"text","text":"Mall","marks":[{"type":"strong"}]}]}]},{"type":"tableCell","attrs":{"colspan":2,"background":"#ace5fe"},"content":[{"type":"paragraph","content":[{"type":"text","text":"Luxury","marks":[{"type":"strong"}]}]}]}]},{"type":"tableRow","content":[{"type":"tableCell","attrs":{"background":"#ace5fe"},"content":[{"type":"paragraph","content":[{"type":"text","text":"Particulars","marks":[{"type":"strong"}]}]}]},{"type":"tableCell","attrs":{"background":"#ace5fe"},"content":[{"type":"paragraph","content":[{"type":"text","text":"SKU Count","marks":[{"type":"strong"}]}]}]},{"type":"tableCell","attrs":{"background":"#ace5fe"},"content":[{"type":"paragraph","content":[{"type":"text","text":"Option Count","marks":[{"type":"strong"}]}]}]},{"type":"tableCell","attrs":{"background":"#ace5fe"},"content":[{"type":"paragraph","content":[{"type":"text","text":"SKU Count","marks":[{"type":"strong"}]}]}]},{"type":"tableCell","attrs":{"background":"#ace5fe"},"content":[{"type":"paragraph","content":[{"type":"text","text":"Option Count","marks":[{"type":"strong"}]}]}]}]},{"type":"tableRow","content":[{"type":"tableCell","attrs":{"background":"white"},"content":[{"type":"paragraph","content":[{"type":"text","text":"Received"}]}]},{"type":"tableCell","attrs":{},"content":[{"type":"paragraph","content":[{"type":"text","text":"1205"}]}]},{"type":"tableCell","attrs":{},"content":[{"type":"paragraph","content":[{"type":"text","text":"664"}]}]},{"type":"tableCell","attrs":{},"content":[{"type":"paragraph","content":[{"type":"text","text":"1205"}]}]},{"type":"tableCell","attrs":{},"content":[{"type":"paragraph","content":[{"type":"text","text":"664"}]}]}]},{"type":"tableRow","content":[{"type":"tableCell","attrs":{"background":"white"},"content":[{"type":"paragraph","content":[{"type":"text","text":"Uploaded"}]}]},{"type":"tableCell","attrs":{},"content":[{"type":"paragraph","content":[{"type":"text","text":"1165"}]}]},{"type":"tableCell","attrs":{},"content":[{"type":"paragraph","content":[{"type":"text","text":"637"}]}]},{"type":"tableCell","attrs":{},"content":[{"type":"paragraph","content":[{"type":"text","text":"1136"}]}]},{"type":"tableCell","attrs":{},"content":[{"type":"paragraph","content":[{"type":"text","text":"595"}]}]}]},{"type":"tableRow","content":[{"type":"tableCell","attrs":{"background":"white"},"content":[{"type":"paragraph","content":[{"type":"text","text":"SKUs not uploaded-Image mismatched with content"}]}]},{"type":"tableCell","attrs":{},"content":[{"type":"paragraph","content":[{"type":"text","text":"1"}]}]},{"type":"tableCell","attrs":{},"content":[{"type":"paragraph","content":[{"type":"text","text":"1"}]}]},{"type":"tableCell","attrs":{},"content":[{"type":"paragraph","content":[{"type":"text","text":"1"}]}]},{"type":"tableCell","attrs":{},"content":[{"type":"paragraph","content":[{"type":"text","text":"1"}]}]}]},{"type":"tableRow","content":[{"type":"tableCell","attrs":{"background":"white"},"content":[{"type":"paragraph","content":[{"type":"text","text":"SKUs not uploaded- Drop down not available in this seller code"}]}]},{"type":"tableCell","attrs":{},"content":[{"type":"paragraph","content":[{"type":"text","text":"-"}]}]},{"type":"tableCell","attrs":{},"content":[{"type":"paragraph","content":[{"type":"text","text":"-"}]}]},{"type":"tableCell","attrs":{},"content":[{"type":"paragraph","content":[{"type":"text","text":"67"}]}]},{"type":"tableCell","attrs":{},"content":[{"type":"paragraph","content":[{"type":"text","text":"67"}]}]}]},{"type":"tableRow","content":[{"type":"tableCell","attrs":{"background":"white"},"content":[{"type":"paragraph","content":[{"type":"text","text":"Already Listed"}]}]},{"type":"tableCell","attrs":{},"content":[{"type":"paragraph","content":[{"type":"text","text":"39"}]}]},{"type":"tableCell","attrs":{},"content":[{"type":"paragraph","content":[{"type":"text","text":"26"}]}]},{"type":"tableCell","attrs":{},"content":[{"type":"paragraph","content":[{"type":"text","text":"1"}]}]},{"type":"tableCell","attrs":{},"content":[{"type":"paragraph","content":[{"type":"text","text":"1"}]}]}]},{"type":"tableRow","content":[{"type":"tableCell","attrs":{"background":"white"},"content":[{"type":"paragraph","content":[{"type":"text","text":"LIDs Shared"}]}]},{"type":"tableCell","attrs":{},"content":[{"type":"paragraph","content":[{"type":"text","text":"1165"}]}]},{"type":"tableCell","attrs":{},"content":[{"type":"paragraph","content":[{"type":"text","text":"637"}]}]},{"type":"tableCell","attrs":{},"content":[{"type":"paragraph","content":[{"type":"text","text":"1136"}]}]},{"type":"tableCell","attrs":{},"content":[{"type":"paragraph","content":[{"type":"text","text":"595"}]}]}]},{"type":"tableRow","content":[{"type":"tableCell","attrs":{"background":"white"},"content":[{"type":"paragraph","content":[{"type":"text","text":"LIDs Stuck in the System"}]}]},{"type":"tableCell","attrs":{},"content":[{"type":"paragraph","content":[{"type":"text","text":"0"}]}]},{"type":"tableCell","attrs":{},"content":[{"type":"paragraph","content":[{"type":"text","text":"0"}]}]},{"type":"tableCell","attrs":{},"content":[{"type":"paragraph","content":[{"type":"text","text":"0"}]}]},{"type":"tableCell","attrs":{},"content":[{"type":"paragraph","content":[{"type":"text","text":"0"}]}]}]}]} {adf} | S21: =IF(OR(G21="",H21=""),"",ROUND(H21-G21,2)) -> 5
A22: UCW-30602 | B22: Foxtale x Tatacliq Hula Hoop rollon Flora New Listings | C22: CLOSED | D22: Medium | E22: Chirag Dubal | F22: Shraddha Dighe | G22: 46146.617 | H22: 46164.769 | I22: 1 | J22: E2E | K22: E2E | L22: Beauty & Grooming | M22: 1 | N22: 1 | O22: 1 | P22: Foxtale | Q22: Mall | R22: [^UCW-30602 Post Upload Status_V.2 (1).xlsx] [^Summary.zip] ;[^128628_product_retrigger_BULK_UPLOAD_summary.csv] [^128628_SKUEDITRETRIGGER__Roll_Ons(MPH2211100105)_20260512_125547_216_summary.csv] Stuck in Rejected due to image aspect Ratio Invalid. we retriggered by correct the Image RATIO.;[^UCW-30602.xlsx] We are pleased to inform you that the listing IDs have been generated successfully. Please find the attached file for your reference, along with the summary table below. You may now proceed with price and inventory pushing from your end. {adf:display=block} {"type":"table","attrs":{"isNumberColumnEnabled":false,"layout":"center","localId":"a4a6f767-44de-4cc5-a837-8076e21e1650"},"content":[{"type":"tableRow","content":[{"type":"tableCell","attrs":{"background":"#44b3e1"},"content":[{"type":"paragraph","content":[{"type":"text","text":"Ticket ID","marks":[{"type":"strong"}]}]}]},{"type":"tableCell","attrs":{"colspan":2,"background":"#44b3e1"},"content":[{"type":"paragraph","content":[{"type":"text","text":"UCW-30602","marks":[{"type":"strong"}]}]}]}]},{"type":"tableRow","content":[{"type":"tableCell","attrs":{"background":"#44b3e1"},"content":[{"type":"paragraph","content":[{"type":"text","text":"Brand Name","marks":[{"type":"strong"}]}]}]},{"type":"tableCell","attrs":{"colspan":2,"background":"#44b3e1"},"content":[{"type":"paragraph","content":[{"type":"text","text":"Foxtale","marks":[{"type":"strong"}]}]}]}]},{"type":"tableRow","content":[{"type":"tableCell","attrs":{"background":"#ace5fe"},"content":[{"type":"paragraph","content":[{"type":"text","text":"Platform","marks":[{"type":"strong"}]}]}]},{"type":"tableCell","attrs":{"colspan":2,"background":"#ace5fe"},"content":[{"type":"paragraph","content":[{"type":"text","text":"Mall","marks":[{"type":"strong"}]}]}]}]},{"type":"tableRow","content":[{"type":"tableCell","attrs":{"background":"#ace5fe"},"content":[{"type":"paragraph","content":[{"type":"text","text":"Particulars","marks":[{"type":"strong"}]}]}]},{"type":"tableCell","attrs":{"background":"#ace5fe"},"content":[{"type":"paragraph","content":[{"type":"text","text":"SKU Count","marks":[{"type":"strong"}]}]}]},{"type":"tableCell","attrs":{"background":"#ace5fe"},"content":[{"type":"paragraph","content":[{"type":"text","text":"Option Count","marks":[{"type":"strong"}]}]}]}]},{"type":"tableRow","content":[{"type":"tableCell","attrs":{"background":"white"},"content":[{"type":"paragraph","content":[{"type":"text","text":"Received"}]}]},{"type":"tableCell","attrs":{},"content":[{"type":"paragraph","content":[{"type":"text","text":"1"}]}]},{"type":"tableCell","attrs":{},"content":[{"type":"paragraph","content":[{"type":"text","text":"1"}]}]}]},{"type":"tableRow","content":[{"type":"tableCell","attrs":{"background":"white"},"content":[{"type":"paragraph","content":[{"type":"text","text":"Uploaded"}]}]},{"type":"tableCell","attrs":{},"content":[{"type":"paragraph","content":[{"type":"text","text":"1"}]}]},{"type":"tableCell","attrs":{},"content":[{"type":"paragraph","content":[{"type":"text","text":"1"}]}]}]},{"type":"tableRow","content":[{"type":"tableCell","attrs":{"background":"white"},"content":[{"type":"paragraph","content":[{"type":"text","text":"LIDs Shared"}]}]},{"type":"tableCell","attrs":{},"content":[{"type":"paragraph","content":[{"type":"text","text":"1"}]}]},{"type":"tableCell","attrs":{},"content":[{"type":"paragraph","content":[{"type":"text","text":"1"}]}]}]},{"type":"tableRow","content":[{"type":"tableCell","attrs":{"background":"white"},"content":[{"type":"paragraph","content":[{"type":"text","text":"LIDs Stuck in the System"}]}]},{"type":"tableCell","attrs":{},"content":[{"type":"paragraph","content":[{"type":"text","text":"0"}]}]},{"type":"tableCell","attrs":{},"content":[{"type":"paragraph","content":[{"type":"text","text":"0"}]}]}]}]} {adf} With this, we are closing this request from our end. Thank you for your patience, support, and cooperation throughout the process. Your brand is important to us, and we look forward to assisting you again. | S22: =IF(OR(G22="",H22=""),"",ROUND(H22-G22,2)) -> 18.15 | U22: It was uploaded on 8th but ticket got closed on 22nd.
A23: UCW-30603 | B23: 3rd Batch for Cataloguing 45 products | C23: CLOSED | D23: Medium | E23: Chirag Dubal | F23: Shraddha Dighe | G23: 46146.619 | H23: 46163.625 | I23: 45 | J23: E2E | K23: E2E | L23: Beauty & Grooming | M23: 45 | N23: 45 | O23: 45 | P23: Lush | Q23: Mall;Luxury | R23: Assigned on - May 4 Started on - May 8 Pre processing query - May 8 |1|EAN Code|32| |2|Skin Type|2| |3|Fragrance Type|2| |4|Fragrance Family|2| |5|Occasion|2| |6|Longevity|2| |7|Ingredients|1| |8|Length,Width,Height|1| |9|Image Analysis|23| |10|Certificate|45| 1st follow up - 11th may 2nd follow up - {{2026-05-12}};[^UCW-30603_Post Upload Status_V.2 (1).xlsx] [^Summary.zip] ;We would like to inform you that SKU is in the Commission stage. [^UCW-30603_Post Upload Status_V.2 (1) (e3bddb10-0a53-42a3-ad49-4a57c3d59d30).xlsx] As the commission is not approved yet, we are closing the ticket. | S23: =IF(OR(G23="",H23=""),"",ROUND(H23-G23,2)) -> 17.01
A24: UCW-30605 | B24: ENRICH_The Sleep Company + Furniture (Home /Home / Furniture / Chairs)+127275 - 30th April 2026 | C24: CLOSED | D24: Medium | E24: Chirag Dubal | F24: Shraddha Dighe | G24: 46146.624 | H24: 46151.634 | I24: 3 | J24: Ad-hoc | K24: Retrigger Content & Image | L24: HOME | M24: 3 | N24: 3 | O24: 3 | P24: The Sleep Company | Q24: Mall | R24: We have updated the title and images. Once the changes are reflected, we will let you know. {adf:display=block} {"type":"table","attrs":{"isNumberColumnEnabled":false,"layout":"center","localId":"0d2989a4-58a9-40aa-90dc-9d8a18513723"},"content":[{"type":"tableRow","content":[{"type":"tableCell","attrs":{},"content":[{"type":"paragraph","content":[{"type":"text","text":"Ticket ID"}]}]},{"type":"tableCell","attrs":{"colspan":2},"content":[{"type":"paragraph","content":[{"type":"text","text":"UCW-30605"}]}]}]},{"type":"tableRow","content":[{"type":"tableCell","attrs":{},"content":[{"type":"paragraph","content":[{"type":"text","text":"Brand Name"}]}]},{"type":"tableCell","attrs":{"colspan":2},"content":[{"type":"paragraph","content":[{"type":"text","text":"The Sleep Company"}]}]}]},{"type":"tableRow","content":[{"type":"tableCell","attrs":{},"content":[{"type":"paragraph","content":[{"type":"text","text":"Platform"}]}]},{"type":"tableCell","attrs":{"colspan":2},"content":[{"type":"paragraph","content":[{"type":"text","text":"Marketplace"}]}]}]},{"type":"tableRow","content":[{"type":"tableCell","attrs":{},"content":[{"type":"paragraph","content":[{"type":"text","text":"Particulars"}]}]},{"type":"tableCell","attrs":{},"content":[{"type":"paragraph","content":[{"type":"text","text":"SKU Count"}]}]},{"type":"tableCell","attrs":{},"content":[{"type":"paragraph","content":[{"type":"text","text":"Option Count"}]}]}]},{"type":"tableRow","content":[{"type":"tableCell","attrs":{},"content":[{"type":"paragraph","content":[{"type":"text","text":"Received"}]}]},{"type":"tableCell","attrs":{},"content":[{"type":"paragraph","content":[{"type":"text","text":"3"}]}]},{"type":"tableCell","attrs":{},"content":[{"type":"paragraph","content":[{"type":"text","text":"3"}]}]}]},{"type":"tableRow","content":[{"type":"tableCell","attrs":{},"content":[{"type":"paragraph","content":[{"type":"text","text":"Uploaded"}]}]},{"type":"tableCell","attrs":{},"content":[{"type":"paragraph","content":[{"type":"text","text":"3"}]}]},{"type":"tableCell","attrs":{},"content":[{"type":"paragraph","content":[{"type":"text","text":"3"}]}]}]}]} {adf} [^Status of UCW-30605.xlsx] [^127275_SKUEDITRETRIGGER__Others_3(MPH2115102107)_20260507_035025_143_summary.csv] ;The images and title have been successfully reflected. Therefore, we are closing the ticket for now. If you require any further assistance, please feel free to connect with us at any time. |MP000000019621727| |MP000000019621717| |MP000000019621726| !image-20260509-094312.png|width=517,alt="image-20260509-094312.png"! !image-20260509-094321.png|width=502,alt="image-20260509-094321.png"! | S24: =IF(OR(G24="",H24=""),"",ROUND(H24-G24,2)) -> 5.01
A25: UCW-30607 | B25: ENRICH_The Sleep Company + Mattresses (/Home/Bed/Pillow & Mattresses/Mattresses)+ 127275+ 15th April 2026 | C25: CLOSED | D25: Medium | E25: Chirag Dubal | F25: Shraddha Dighe | G25: 46146.627 | H25: 46151.652 | I25: 25 | J25: Ad-hoc | K25: Retrigger Image | L25: HOME | M25: 25 | N25: 25 | O25: 25 | P25: The Sleep Company | Q25: Mall | R25: We have updated the images. Please find the attached summary sheet for your reference. Once the images are successfully reflected, we will let you know. {adf:display=block} {"type":"table","attrs":{"isNumberColumnEnabled":false,"layout":"center","localId":"8468dc17-827c-44e2-8b58-2d9ba796c53c"},"content":[{"type":"tableRow","content":[{"type":"tableCell","attrs":{},"content":[{"type":"paragraph","content":[{"type":"text","text":"Ticket ID"}]}]},{"type":"tableCell","attrs":{"colspan":2},"content":[{"type":"paragraph","content":[{"type":"text","text":"UCW-30607"}]}]}]},{"type":"tableRow","content":[{"type":"tableCell","attrs":{},"content":[{"type":"paragraph","content":[{"type":"text","text":"Brand Name"}]}]},{"type":"tableCell","attrs":{"colspan":2},"content":[{"type":"paragraph","content":[{"type":"text","text":"The Sleep Company"}]}]}]},{"type":"tableRow","content":[{"type":"tableCell","attrs":{},"content":[{"type":"paragraph","content":[{"type":"text","text":"Platform"}]}]},{"type":"tableCell","attrs":{"colspan":2},"content":[{"type":"paragraph","content":[{"type":"text","text":"Marketplace"}]}]}]},{"type":"tableRow","content":[{"type":"tableCell","attrs":{},"content":[{"type":"paragraph","content":[{"type":"text","text":"Particulars"}]}]},{"type":"tableCell","attrs":{},"content":[{"type":"paragraph","content":[{"type":"text","text":"SKU Count"}]}]},{"type":"tableCell","attrs":{},"content":[{"type":"paragraph","content":[{"type":"text","text":"Option Count"}]}]}]},{"type":"tableRow","content":[{"type":"tableCell","attrs":{},"content":[{"type":"paragraph","content":[{"type":"text","text":"Received"}]}]},{"type":"tableCell","attrs":{},"content":[{"type":"paragraph","content":[{"type":"text","text":"25"}]}]},{"type":"tableCell","attrs":{},"content":[{"type":"paragraph","content":[{"type":"text","text":"25"}]}]}]},{"type":"tableRow","content":[{"type":"tableCell","attrs":{},"content":[{"type":"paragraph","content":[{"type":"text","text":"Uploaded"}]}]},{"type":"tableCell","attrs":{},"content":[{"type":"paragraph","content":[{"type":"text","text":"25"}]}]},{"type":"tableCell","attrs":{},"content":[{"type":"paragraph","content":[{"type":"text","text":"25"}]}]}]}]} {adf} [^Status of UCW-30607.xlsx] [^Summery.zip] ;The images have been successfully reflected. Therefore, we are closing the ticket for now. If you require any further assistance, please feel free to connect with us at any time. |MP000000026499783| |MP000000026499930| |MP000000026499931| |MP000000026500151| |MP000000026500228| |MP000000019621717| |MP000000019621726| |MP000000019621727| |MP000000025366426| |MP000000025366427| |MP000000026283054| |MP000000026283057| |MP000000026283058| |MP000000026283060| |MP000000026283065| |MP000000026283067| |MP000000026283068| |MP000000026283602| |MP000000026283603| |MP000000026283606| |MP000000026283607| |MP000000026283612| |MP000000026283620| |MP000000026283623| |MP000000026283625| | S25: =IF(OR(G25="",H25=""),"",ROUND(H25-G25,2)) -> 5.03
A26: UCW-30609 | B26: Soulflower x TataCliq Connect | C26: CLOSED Due to Inactive/Insufficient Information | D26: Medium | E26: Chirag Dubal | F26: Shraddha Dighe | G26: 46146.633 | H26: 46163.47 | I26: 19 | J26: E2E | K26: E2E | L26: Beauty & Grooming | M26: 0 | N26: 0 | O26: 19 | P26: Soulflower | Q26: Mall | S26: =IF(OR(G26="",H26=""),"",ROUND(H26-G26,2)) -> 16.84 | U26: Ticket was closed since brand took high time to resolve the ticket.
A27: UCW-30610 | B27: ERROR_Image update Required 30.04.2026 | C27: CLOSED | D27: Medium | E27: Chirag Dubal | F27: catalogue_repo | G27: 46146.646 | H27: 46162.52 | I27: 55 | J27: Ad-hoc | K27: Retrigger Image | L27: Apparel | M27: 55 | N27: 55 | O27: 55 | P27: Andamen | Q27: Mall | R27: We have updated the images. Please find the attached summary sheet for your reference. Once the images are successfully reflected, we will let you know. {adf:display=block} {"type":"table","attrs":{"isNumberColumnEnabled":false,"layout":"center","localId":"d6b63170-bf9f-4d13-9b82-3d3154cb9e03"},"content":[{"type":"tableRow","content":[{"type":"tableCell","attrs":{},"content":[{"type":"paragraph","content":[{"type":"text","text":"Ticket ID"}]}]},{"type":"tableCell","attrs":{"colspan":2},"content":[{"type":"paragraph","content":[{"type":"text","text":"UCW-30610"}]}]}]},{"type":"tableRow","content":[{"type":"tableCell","attrs":{},"content":[{"type":"paragraph","content":[{"type":"text","text":"Brand Name"}]}]},{"type":"tableCell","attrs":{"colspan":2},"content":[{"type":"paragraph","content":[{"type":"text","text":"Andamen"}]}]}]},{"type":"tableRow","content":[{"type":"tableCell","attrs":{},"content":[{"type":"paragraph","content":[{"type":"text","text":"Platform"}]}]},{"type":"tableCell","attrs":{"colspan":2},"content":[{"type":"paragraph","content":[{"type":"text","text":"Marketplace"}]}]}]},{"type":"tableRow","content":[{"type":"tableCell","attrs":{},"content":[{"type":"paragraph","content":[{"type":"text","text":"Particulars"}]}]},{"type":"tableCell","attrs":{},"content":[{"type":"paragraph","content":[{"type":"text","text":"SKU Count"}]}]},{"type":"tableCell","attrs":{},"content":[{"type":"paragraph","content":[{"type":"text","text":"Option Count"}]}]}]},{"type":"tableRow","content":[{"type":"tableCell","attrs":{},"content":[{"type":"paragraph","content":[{"type":"text","text":"Received"}]}]},{"type":"tableCell","attrs":{},"content":[{"type":"paragraph","content":[{"type":"text","text":"55"}]}]},{"type":"tableCell","attrs":{},"content":[{"type":"paragraph","content":[{"type":"text","text":"11"}]}]}]},{"type":"tableRow","content":[{"type":"tableCell","attrs":{},"content":[{"type":"paragraph","content":[{"type":"text","text":"Uploaded"}]}]},{"type":"tableCell","attrs":{},"content":[{"type":"paragraph","content":[{"type":"text","text":"55"}]}]},{"type":"tableCell","attrs":{},"content":[{"type":"paragraph","content":[{"type":"text","text":"11"}]}]}]}]} {adf} [^Summery.zip] [^Status of UCW-30610.xlsx] ;The images have been successfully reflected. Please find the attached screenshot for your reference. We are closing this ticket for now. If any issues arise or if you require further assistance, please feel free to reach out to us. !image-20260520-065746.png|width=534,alt="image-20260520-065746.png"! !image-20260520-065753.png|width=519,alt="image-20260520-065753.png"! !image-20260520-065800.png|width=519,alt="image-20260520-065800.png"! !image-20260520-065808.png|width=519,alt="image-20260520-065808.png"! !image-20260520-065814.png|width=519,alt="image-20260520-065814.png"! !image-20260520-065820.png|width=519,alt="image-20260520-065820.png"! !image-20260520-065826.png|width=519,alt="image-20260520-065826.png"! !image-20260520-065833.png|width=519,alt="image-20260520-065833.png"! | S27: =IF(OR(G27="",H27=""),"",ROUND(H27-G27,2)) -> 15.87
A28: UCW-30612 | B28: CLONE - Vantier Shoes - 7th April 26 - 129308 - New collection - Luxury | C28: CLOSED Due to Inactive/Insufficient Information | D28: Medium | E28: netscribes | F28: netscribes | G28: 46146.648 | H28: 46158.767 | I28: 328 | J28: E2E | K28: E2E | L28: Footwear | M28: 0 | N28: 0 | O28: 41 | P28: Vantier Shoes | Q28: Luxury | S28: =IF(OR(G28="",H28=""),"",ROUND(H28-G28,2)) -> 12.12 | U28: Ticket was closed since brand took high time to resolve the ticket.
A29: UCW-30617 | B29: ENRICH_IMAGE UPDATE. | C29: CLOSED | D29: Medium | E29: Chirag Dubal | F29: Shraddha Dighe | G29: 46146.685 | H29: 46155.944 | I29: 162 | J29: Ad-hoc | K29: Retrigger Image | L29: Jewellery | M29: 162 | N29: 162 | O29: 162 | P29: Zaveri Pearls | Q29: Mall | S29: =IF(OR(G29="",H29=""),"",ROUND(H29-G29,2)) -> 9.26
A30: UCW-30619 | B30: Lancome Fragrance Duo Kit_TCL | C30: CLOSED Due to Inactive/Insufficient Information | D30: Medium | E30: Chirag Dubal | F30: Shraddha Dighe | G30: 46146.69 | H30: 46155.736 | I30: 1 | J30: E2E | K30: E2E | L30: Beauty & Grooming | M30: 0 | N30: 0 | O30: 1 | P30: Lancome | Q30: Luxury | S30: =IF(OR(G30="",H30=""),"",ROUND(H30-G30,2)) -> 9.05
A31: UCW-30622 | B31: CLONE - ENRICH_Arata 3.0 Catalogue Revision - 14 April | C31: CLOSED | D31: Medium | E31: Chirag Dubal | F31: Shraddha Dighe | G31: 46146.701 | H31: 46157.81 | I31: 34 | J31: Ad-hoc | K31: Retrigger Content | L31: Beauty & Grooming | M31: 32 | N31: 33 | O31: 34 | P31: Arata | Q31: Mall | S31: =IF(OR(G31="",H31=""),"",ROUND(H31-G31,2)) -> 11.11
A32: UCW-30629 | B32: New Chapter Series 10ML | C32: CLOSED | D32: Medium | E32: Chirag Dubal | F32: Shraddha Dighe | G32: 46146.74 | H32: 46155.701 | I32: 5 | J32: E2E | K32: E2E | L32: Beauty & Grooming | M32: 5 | N32: 5 | O32: 5 | P32: Ajmal | Q32: Mall | R32: [^UCW-30629_Post Upload Status_V.2.xlsx] [^Summary.zip] ;[^125790_product_retrigger_BULK_UPLOAD_summary.csv] [^125790_SKUEDITRETRIGGER__Perfumes(MPH2211100104)_20260512_025130_753_summary.csv] Stuck in Rejected due to Image Ratio: INVALID. we retriggered by correcting the image Ratio;[^UCW-30629_Post Upload Status_V.2 (c610e65c-bb9f-42a5-98c7-f100f4be9d94).xlsx] Please find attached the sheet, where 5 options have been listed. Kindly update the price and inventory, and share the summary once completed. {adf:display=block} {"type":"table","attrs":{"isNumberColumnEnabled":false,"layout":"center","localId":"cf604f7e-c0b7-4568-af9b-94a571993a9a"},"content":[{"type":"tableRow","content":[{"type":"tableCell","attrs":{"background":"#44b3e1"},"content":[{"type":"paragraph","content":[{"type":"text","text":"Ticket ID","marks":[{"type":"strong"}]}]}]},{"type":"tableCell","attrs":{"colspan":2,"background":"#44b3e1"},"content":[{"type":"paragraph","content":[{"type":"text","text":"UCW-30629","marks":[{"type":"strong"}]}]}]}]},{"type":"tableRow","content":[{"type":"tableCell","attrs":{"background":"#44b3e1"},"content":[{"type":"paragraph","content":[{"type":"text","text":"Brand Name","marks":[{"type":"strong"}]}]}]},{"type":"tableCell","attrs":{"colspan":2,"background":"#44b3e1"},"content":[{"type":"paragraph","content":[{"type":"text","text":"Ajmal","marks":[{"type":"strong"}]}]}]}]},{"type":"tableRow","content":[{"type":"tableCell","attrs":{"background":"#ace5fe"},"content":[{"type":"paragraph","content":[{"type":"text","text":"Platform","marks":[{"type":"strong"}]}]}]},{"type":"tableCell","attrs":{"colspan":2,"background":"#ace5fe"},"content":[{"type":"paragraph","content":[{"type":"text","text":"Mall","marks":[{"type":"strong"}]}]}]}]},{"type":"tableRow","content":[{"type":"tableCell","attrs":{"background":"#ace5fe"},"content":[{"type":"paragraph","content":[{"type":"text","text":"Particulars","marks":[{"type":"strong"}]}]}]},{"type":"tableCell","attrs":{"background":"#ace5fe"},"content":[{"type":"paragraph","content":[{"type":"text","text":"SKU Count","marks":[{"type":"strong"}]}]}]},{"type":"tableCell","attrs":{"background":"#ace5fe"},"content":[{"type":"paragraph","content":[{"type":"text","text":"Option Count","marks":[{"type":"strong"}]}]}]}]},{"type":"tableRow","content":[{"type":"tableCell","attrs":{"background":"white"},"content":[{"type":"paragraph","content":[{"type":"text","text":"Received"}]}]},{"type":"tableCell","attrs":{},"content":[{"type":"paragraph","content":[{"type":"text","text":"5"}]}]},{"type":"tableCell","attrs":{},"content":[{"type":"paragraph","content":[{"type":"text","text":"5"}]}]}]},{"type":"tableRow","content":[{"type":"tableCell","attrs":{"background":"white"},"content":[{"type":"paragraph","content":[{"type":"text","text":"Uploaded"}]}]},{"type":"tableCell","attrs":{},"content":[{"type":"paragraph","content":[{"type":"text","text":"5"}]}]},{"type":"tableCell","attrs":{},"content":[{"type":"paragraph","content":[{"type":"text","text":"5"}]}]}]},{"type":"tableRow","content":[{"type":"tableCell","attrs":{"background":"white"},"content":[{"type":"paragraph","content":[{"type":"text","text":"LIDs Shared"}]}]},{"type":"tableCell","attrs":{},"content":[{"type":"paragraph","content":[{"type":"text","text":"5"}]}]},{"type":"tableCell","attrs":{},"content":[{"type":"paragraph","content":[{"type":"text","text":"5"}]}]}]},{"type":"tableRow","content":[{"type":"tableCell","attrs":{"background":"white"},"content":[{"type":"paragraph","content":[{"type":"text","text":"LIDs Stuck in the System"}]}]},{"type":"tableCell","attrs":{},"content":[{"type":"paragraph","content":[{"type":"text","text":"0"}]}]},{"type":"tableCell","attrs":{},"content":[{"type":"paragraph","content":[{"type":"text","text":"0"}]}]}]}]} {adf} | S32: =IF(OR(G32="",H32=""),"",ROUND(H32-G32,2)) -> 8.96
A33: UCW-30630 | B33: Tata Cliq - April New Listings | C33: CLOSED | D33: Medium | E33: Chirag Dubal | F33: Shraddha Dighe | G33: 46146.745 | H33: 46154.515 | I33: 4 | J33: E2E | K33: E2E | L33: Beauty & Grooming | M33: 4 | N33: 4 | O33: 4 | P33: Brillare | Q33: Mall | R33: [^UCW-30630 Post Upload Status_V.2 (1).xlsx] [^Summary.zip] ;[^UCW-30630 Post Upload Status_V.2 (1) (5131fae7-250c-43db-9b68-98dbc29267f8).xlsx] Please find attached the sheet, where 4 options of Beauty & Grooming have been listed. Kindly update the price and inventory, and share the summary once completed. {adf:display=block} {"type":"table","attrs":{"isNumberColumnEnabled":false,"layout":"center","localId":"dc8eafab-281b-47b7-bdde-e2d25fc97f6a"},"content":[{"type":"tableRow","content":[{"type":"tableCell","attrs":{"background":"#44b3e1"},"content":[{"type":"paragraph","content":[{"type":"text","text":"Ticket ID","marks":[{"type":"strong"}]}]}]},{"type":"tableCell","attrs":{"colspan":2,"background":"#44b3e1"},"content":[{"type":"paragraph","content":[{"type":"text","text":"UCW-30630","marks":[{"type":"strong"}]}]}]}]},{"type":"tableRow","content":[{"type":"tableCell","attrs":{"background":"#44b3e1"},"content":[{"type":"paragraph","content":[{"type":"text","text":"Brand Name","marks":[{"type":"strong"}]}]}]},{"type":"tableCell","attrs":{"colspan":2,"background":"#44b3e1"},"content":[{"type":"paragraph","content":[{"type":"text","text":"Brillare","marks":[{"type":"strong"}]}]}]}]},{"type":"tableRow","content":[{"type":"tableCell","attrs":{"background":"#ace5fe"},"content":[{"type":"paragraph","content":[{"type":"text","text":"Platform","marks":[{"type":"strong"}]}]}]},{"type":"tableCell","attrs":{"colspan":2,"background":"#ace5fe"},"content":[{"type":"paragraph","content":[{"type":"text","text":"Mall","marks":[{"type":"strong"}]}]}]}]},{"type":"tableRow","content":[{"type":"tableCell","attrs":{"background":"#ace5fe"},"content":[{"type":"paragraph","content":[{"type":"text","text":"Particulars","marks":[{"type":"strong"}]}]}]},{"type":"tableCell","attrs":{"background":"#ace5fe"},"content":[{"type":"paragraph","content":[{"type":"text","text":"SKU Count","marks":[{"type":"strong"}]}]}]},{"type":"tableCell","attrs":{"background":"#ace5fe"},"content":[{"type":"paragraph","content":[{"type":"text","text":"Option Count","marks":[{"type":"strong"}]}]}]}]},{"type":"tableRow","content":[{"type":"tableCell","attrs":{"background":"white"},"content":[{"type":"paragraph","content":[{"type":"text","text":"Received"}]}]},{"type":"tableCell","attrs":{},"content":[{"type":"paragraph","content":[{"type":"text","text":"4"}]}]},{"type":"tableCell","attrs":{},"content":[{"type":"paragraph","content":[{"type":"text","text":"4"}]}]}]},{"type":"tableRow","content":[{"type":"tableCell","attrs":{"background":"white"},"content":[{"type":"paragraph","content":[{"type":"text","text":"Uploaded"}]}]},{"type":"tableCell","attrs":{},"content":[{"type":"paragraph","content":[{"type":"text","text":"4"}]}]},{"type":"tableCell","attrs":{},"content":[{"type":"paragraph","content":[{"type":"text","text":"4"}]}]}]},{"type":"tableRow","content":[{"type":"tableCell","attrs":{"background":"white"},"content":[{"type":"paragraph","content":[{"type":"text","text":"LIDs Shared"}]}]},{"type":"tableCell","attrs":{},"content":[{"type":"paragraph","content":[{"type":"text","text":"4"}]}]},{"type":"tableCell","attrs":{},"content":[{"type":"paragraph","content":[{"type":"text","text":"4"}]}]}]},{"type":"tableRow","content":[{"type":"tableCell","attrs":{"background":"white"},"content":[{"type":"paragraph","content":[{"type":"text","text":"LIDs Stuck in the System"}]}]},{"type":"tableCell","attrs":{},"content":[{"type":"paragraph","content":[{"type":"text","text":"0"}]}]},{"type":"tableCell","attrs":{},"content":[{"type":"paragraph","content":[{"type":"text","text":"0"}]}]}]}]} {adf} | S33: =IF(OR(G33="",H33=""),"",ROUND(H33-G33,2)) -> 7.77
A34: UCW-30631 | B34: Enrich_Updated Product Cards – Ultra Matte Dry Touch Sunscreen 20g | C34: CLOSED | D34: Medium | E34: Chirag Dubal | F34: Shraddha Dighe | G34: 46146.747 | H34: 46151.764 | I34: 1 | J34: Ad-hoc | K34: Retrigger Content & Image | L34: Beauty & Grooming | M34: 1 | N34: 1 | O34: 1 | P34: Reequil | Q34: Mall | S34: =IF(OR(G34="",H34=""),"",ROUND(H34-G34,2)) -> 5.02
A35: UCW-30634 | B35: FE x 22162 x GWP (Night Cream Gotu Kola) | C35: CLOSED | D35: Medium | E35: Chirag Dubal | F35: Simi Raichel Zachariah | G35: 46146.753 | H35: 46154.624 | I35: 1 | J35: E2E | K35: E2E | L35: Beauty & Grooming | M35: 1 | N35: 1 | O35: 1 | P35: Forest Essential | Q35: Mall;Luxury | R35: [^UCW-30634 Post Upload Status_V.2 (1).xlsx] [^Summary.zip] ;[^UCW-30634 Post Upload Status_V.2 (1) (f6545426-a34c-4b5f-b5b2-4436b92daf66).xlsx] Please find attached the sheet, where 1 option of Beauty & Grooming has been listed. Kindly update the price and inventory, and share the summary once completed. {adf:display=block} {"type":"table","attrs":{"isNumberColumnEnabled":false,"layout":"center","localId":"91caafd2-6bc7-41e5-966e-553634361325"},"content":[{"type":"tableRow","content":[{"type":"tableCell","attrs":{"background":"#44b3e1"},"content":[{"type":"paragraph","content":[{"type":"text","text":"Ticket ID","marks":[{"type":"strong"}]}]}]},{"type":"tableCell","attrs":{"colspan":2,"background":"#44b3e1"},"content":[{"type":"paragraph","content":[{"type":"text","text":"UCW-30634","marks":[{"type":"strong"}]}]}]}]},{"type":"tableRow","content":[{"type":"tableCell","attrs":{"background":"#44b3e1"},"content":[{"type":"paragraph","content":[{"type":"text","text":"Brand Name","marks":[{"type":"strong"}]}]}]},{"type":"tableCell","attrs":{"colspan":2,"background":"#44b3e1"},"content":[{"type":"paragraph","content":[{"type":"text","text":"Forest Essential","marks":[{"type":"strong"}]}]}]}]},{"type":"tableRow","content":[{"type":"tableCell","attrs":{"background":"#ace5fe"},"content":[{"type":"paragraph","content":[{"type":"text","text":"Platform","marks":[{"type":"strong"}]}]}]},{"type":"tableCell","attrs":{"colspan":2,"background":"#ace5fe"},"content":[{"type":"paragraph","content":[{"type":"text","text":"Mall, Luxury","marks":[{"type":"strong"}]}]}]}]},{"type":"tableRow","content":[{"type":"tableCell","attrs":{"background":"#ace5fe"},"content":[{"type":"paragraph","content":[{"type":"text","text":"Particulars","marks":[{"type":"strong"}]}]}]},{"type":"tableCell","attrs":{"background":"#ace5fe"},"content":[{"type":"paragraph","content":[{"type":"text","text":"SKU Count","marks":[{"type":"strong"}]}]}]},{"type":"tableCell","attrs":{"background":"#ace5fe"},"content":[{"type":"paragraph","content":[{"type":"text","text":"Option Count","marks":[{"type":"strong"}]}]}]}]},{"type":"tableRow","content":[{"type":"tableCell","attrs":{"background":"white"},"content":[{"type":"paragraph","content":[{"type":"text","text":"Received"}]}]},{"type":"tableCell","attrs":{},"content":[{"type":"paragraph","content":[{"type":"text","text":"1"}]}]},{"type":"tableCell","attrs":{},"content":[{"type":"paragraph","content":[{"type":"text","text":"1"}]}]}]},{"type":"tableRow","content":[{"type":"tableCell","attrs":{"background":"white"},"content":[{"type":"paragraph","content":[{"type":"text","text":"Uploaded"}]}]},{"type":"tableCell","attrs":{},"content":[{"type":"paragraph","content":[{"type":"text","text":"1"}]}]},{"type":"tableCell","attrs":{},"content":[{"type":"paragraph","content":[{"type":"text","text":"1"}]}]}]},{"type":"tableRow","content":[{"type":"tableCell","attrs":{"background":"white"},"content":[{"type":"paragraph","content":[{"type":"text","text":"LIDs Shared"}]}]},{"type":"tableCell","attrs":{},"content":[{"type":"paragraph","content":[{"type":"text","text":"1"}]}]},{"type":"tableCell","attrs":{},"content":[{"type":"paragraph","content":[{"type":"text","text":"1"}]}]}]},{"type":"tableRow","content":[{"type":"tableCell","attrs":{"background":"white"},"content":[{"type":"paragraph","content":[{"type":"text","text":"LIDs Stuck in the System"}]}]},{"type":"tableCell","attrs":{},"content":[{"type":"paragraph","content":[{"type":"text","text":"0"}]}]},{"type":"tableCell","attrs":{},"content":[{"type":"paragraph","content":[{"type":"text","text":"0"}]}]}]}]} {adf} | S35: =IF(OR(G35="",H35=""),"",ROUND(H35-G35,2)) -> 7.87
A36: UCW-30644 | B36: REGAL TATACLIQ TEMPLATE 21.03.2026 | C36: CLOSED | D36: Medium | E36: netscribes | F36: catalogue_repo | G36: 46146.798 | H36: 46149.769 | I36: 96 | J36: E2E | K36: E2E | L36: Footwear | M36: 96 | N36: 16 | O36: 16 | P36: Regal, Imperio | Q36: Mall | R36: We have successfully uploaded this batch. Please find the attached summary sheet and summary report.[^Summary.zip] [^Post Upload Status_V.2 (1).xlsx] ;[^UCW-30644_LID.xlsx] Hi [@Vijay Shettiyar|mailto:vijays@regalshoes.co.in], Please find attached the sheet, where 16 options have been listed. Kindly update the price and inventory, and share the summary once completed. {adf:display=block} {"type":"table","attrs":{"isNumberColumnEnabled":false,"layout":"center","localId":"c3e5ec96-a4fd-465b-922d-6cd70740ff94"},"content":[{"type":"tableRow","content":[{"type":"tableCell","attrs":{"background":"#44b3e1"},"content":[{"type":"paragraph","content":[{"type":"text","text":"Ticket ID","marks":[{"type":"strong"}]}]}]},{"type":"tableCell","attrs":{"colspan":2,"background":"#44b3e1"},"content":[{"type":"paragraph","content":[{"type":"text","text":"UCW-30644","marks":[{"type":"strong"}]}]}]}]},{"type":"tableRow","content":[{"type":"tableCell","attrs":{"background":"#44b3e1"},"content":[{"type":"paragraph","content":[{"type":"text","text":"Brand Name","marks":[{"type":"strong"}]}]}]},{"type":"tableCell","attrs":{"colspan":2,"background":"#44b3e1"},"content":[{"type":"paragraph","content":[{"type":"text","text":"Regal, Imperio","marks":[{"type":"strong"}]}]}]}]},{"type":"tableRow","content":[{"type":"tableCell","attrs":{"background":"#44b3e1"},"content":[{"type":"paragraph","content":[{"type":"text","text":"Platform","marks":[{"type":"strong"}]}]}]},{"type":"tableCell","attrs":{"colspan":2,"background":"#44b3e1"},"content":[{"type":"paragraph","content":[{"type":"text","text":"Mall","marks":[{"type":"strong"}]}]}]}]},{"type":"tableRow","content":[{"type":"tableCell","attrs":{"background":"#ace5fe"},"content":[{"type":"paragraph","content":[{"type":"text","text":"Particulars","marks":[{"type":"strong"}]}]}]},{"type":"tableCell","attrs":{"background":"#ace5fe"},"content":[{"type":"paragraph","content":[{"type":"text","text":"SKU Count","marks":[{"type":"strong"}]}]}]},{"type":"tableCell","attrs":{"background":"#ace5fe"},"content":[{"type":"paragraph","content":[{"type":"text","text":"Option Count","marks":[{"type":"strong"}]}]}]}]},{"type":"tableRow","content":[{"type":"tableCell","attrs":{"background":"white"},"content":[{"type":"paragraph","content":[{"type":"text","text":"Received"}]}]},{"type":"tableCell","attrs":{"background":"white"},"content":[{"type":"paragraph","content":[{"type":"text","text":"96"}]}]},{"type":"tableCell","attrs":{"background":"white"},"content":[{"type":"paragraph","content":[{"type":"text","text":"16"}]}]}]},{"type":"tableRow","content":[{"type":"tableCell","attrs":{"background":"white"},"content":[{"type":"paragraph","content":[{"type":"text","text":"Uploaded"}]}]},{"type":"tableCell","attrs":{"background":"white"},"content":[{"type":"paragraph","content":[{"type":"text","text":"96"}]}]},{"type":"tableCell","attrs":{"background":"white"},"content":[{"type":"paragraph","content":[{"type":"text","text":"16"}]}]}]},{"type":"tableRow","content":[{"type":"tableCell","attrs":{"background":"white"},"content":[{"type":"paragraph","content":[{"type":"text","text":"Not Uploaded"}]}]},{"type":"tableCell","attrs":{"background":"white"},"content":[{"type":"paragraph","content":[{"type":"text","text":"0"}]}]},{"type":"tableCell","attrs":{"background":"white"},"content":[{"type":"paragraph","content":[{"type":"text","text":"0"}]}]}]},{"type":"tableRow","content":[{"type":"tableCell","attrs":{"background":"white"},"content":[{"type":"paragraph","content":[{"type":"text","text":"LIDs Shared"}]}]},{"type":"tableCell","attrs":{"background":"white"},"content":[{"type":"paragraph","content":[{"type":"text","text":"96"}]}]},{"type":"tableCell","attrs":{"background":"white"},"content":[{"type":"paragraph","content":[{"type":"text","text":"16"}]}]}]},{"type":"tableRow","content":[{"type":"tableCell","attrs":{"background":"white"},"content":[{"type":"paragraph","content":[{"type":"text","text":"LIDs Stuck in the System"}]}]},{"type":"tableCell","attrs":{"background":"white"},"content":[{"type":"paragraph","content":[{"type":"text","text":"0"}]}]},{"type":"tableCell","attrs":{"background":"white"},"content":[{"type":"paragraph","content":[{"type":"text","text":"0"}]}]}]}]} {adf} Regards, Team Netscribes | S36: =IF(OR(G36="",H36=""),"",ROUND(H36-G36,2)) -> 2.97
A37: UCW-30646 | B37: Charles & Keith_Footwear_125610_30thApr'26 (Batch 12) | C37: CLOSED | D37: Medium | E37: Chirag Dubal | F37: Shloka Chakre | G37: 46146.8 | H37: 46155.736 | I37: 174 | J37: E2E | K37: E2E | L37: Footwear | M37: 174 | N37: 27 | O37: 27 | P37: Charles & Keith | Q37: Luxury | R37: We have successfully uploaded this batch. Please find the attached summary sheet and summary report.[^Summary.zip] [^Post Upload Status_V.2 (1).xlsx] ;[^UCW-30646.xlsx] Please find attached the sheet, where 27 options of Footwear have been listed. Kindly update the price and inventory, and share the summary once completed. {adf:display=block} {"type":"table","attrs":{"isNumberColumnEnabled":false,"layout":"center","localId":"972cfd73-d7e0-4d77-8b15-1a71401c2aac"},"content":[{"type":"tableRow","content":[{"type":"tableCell","attrs":{"background":"#44b3e1"},"content":[{"type":"paragraph","content":[{"type":"text","text":"Ticket ID","marks":[{"type":"strong"}]}]}]},{"type":"tableCell","attrs":{"colspan":2,"background":"#44b3e1"},"content":[{"type":"paragraph","content":[{"type":"text","text":"UCW-30646","marks":[{"type":"strong"}]}]}]}]},{"type":"tableRow","content":[{"type":"tableCell","attrs":{"background":"#44b3e1"},"content":[{"type":"paragraph","content":[{"type":"text","text":"Brand Name","marks":[{"type":"strong"}]}]}]},{"type":"tableCell","attrs":{"colspan":2,"background":"#44b3e1"},"content":[{"type":"paragraph","content":[{"type":"text","text":"Charles & Keith","marks":[{"type":"strong"}]}]}]}]},{"type":"tableRow","content":[{"type":"tableCell","attrs":{"background":"#ace5fe"},"content":[{"type":"paragraph","content":[{"type":"text","text":"Platform","marks":[{"type":"strong"}]}]}]},{"type":"tableCell","attrs":{"colspan":2,"background":"#ace5fe"},"content":[{"type":"paragraph","content":[{"type":"text","text":"Mall","marks":[{"type":"strong"}]}]}]}]},{"type":"tableRow","content":[{"type":"tableCell","attrs":{"background":"#ace5fe"},"content":[{"type":"paragraph","content":[{"type":"text","text":"Particulars","marks":[{"type":"strong"}]}]}]},{"type":"tableCell","attrs":{"background":"#ace5fe"},"content":[{"type":"paragraph","content":[{"type":"text","text":"SKU Count","marks":[{"type":"strong"}]}]}]},{"type":"tableCell","attrs":{"background":"#ace5fe"},"content":[{"type":"paragraph","content":[{"type":"text","text":"Option Count","marks":[{"type":"strong"}]}]}]}]},{"type":"tableRow","content":[{"type":"tableCell","attrs":{"background":"white"},"content":[{"type":"paragraph","content":[{"type":"text","text":"Received"}]}]},{"type":"tableCell","attrs":{},"content":[{"type":"paragraph","content":[{"type":"text","text":"174"}]}]},{"type":"tableCell","attrs":{},"content":[{"type":"paragraph","content":[{"type":"text","text":"27"}]}]}]},{"type":"tableRow","content":[{"type":"tableCell","attrs":{"background":"white"},"content":[{"type":"paragraph","content":[{"type":"text","text":"Uploaded"}]}]},{"type":"tableCell","attrs":{},"content":[{"type":"paragraph","content":[{"type":"text","text":"174"}]}]},{"type":"tableCell","attrs":{},"content":[{"type":"paragraph","content":[{"type":"text","text":"27"}]}]}]},{"type":"tableRow","content":[{"type":"tableCell","attrs":{"background":"white"},"content":[{"type":"paragraph","content":[{"type":"text","text":"LIDs Shared"}]}]},{"type":"tableCell","attrs":{},"content":[{"type":"paragraph","content":[{"type":"text","text":"174"}]}]},{"type":"tableCell","attrs":{},"content":[{"type":"paragraph","content":[{"type":"text","text":"27"}]}]}]},{"type":"tableRow","content":[{"type":"tableCell","attrs":{"background":"white"},"content":[{"type":"paragraph","content":[{"type":"text","text":"LIDs Stuck in the System"}]}]},{"type":"tableCell","attrs":{},"content":[{"type":"paragraph","content":[{"type":"text","text":"0"}]}]},{"type":"tableCell","attrs":{},"content":[{"type":"paragraph","content":[{"type":"text","text":"0"}]}]}]}]} {adf} | S37: =IF(OR(G37="",H37=""),"",ROUND(H37-G37,2)) -> 8.94
A38: UCW-30656 | B38: ENRICH_PDP Tata X SKP | C38: CLOSED | D38: Medium | E38: Chirag Dubal | F38: Shraddha Dighe | G38: 46147.459 | H38: 46151.769 | I38: 1 | J38: Ad-hoc | K38: Retrigger Image | L38: Beauty & Grooming | M38: 1 | N38: 1 | O38: 1 | P38: Schwarzkopf Professional | Q38: Mall;Luxury | S38: =IF(OR(G38="",H38=""),"",ROUND(H38-G38,2)) -> 4.31
A39: UCW-30657 | B39: Bobbi Brown - GWP April'26 | C39: CLOSED | D39: Medium | E39: Chirag Dubal | F39: Shraddha Dighe | G39: 46147.47 | H39: 46154.624 | I39: 1 | J39: E2E | K39: GWP | L39: Beauty & Grooming | M39: 1 | N39: 1 | O39: 1 | P39: Bobbi Brown | Q39: Mall;Luxury | R39: We have successfully uploaded this batch. Please find the attached summary sheet and summary report.[^ProductBulkUpload_125928_Beauty__Grooming(MPH22)_Makeup(MPH2214)_Face(MPH2214101)_Face_Primer(MPH2214101110)_33887_1778480782990_20260511_115623_213_summary.csv] [^Post Upload Status.xlsx] ;[^UCW-30657.xlsx] Please find attached the sheet, where 1 option has been listed. Kindly update the price and inventory, and share the summary once completed. {adf:display=block} {"type":"table","attrs":{"isNumberColumnEnabled":false,"layout":"center","localId":"caced251-8085-4ed1-8595-20787eea7f3d"},"content":[{"type":"tableRow","content":[{"type":"tableCell","attrs":{"background":"#44b3e1"},"content":[{"type":"paragraph","content":[{"type":"text","text":"Ticket ID","marks":[{"type":"strong"}]}]}]},{"type":"tableCell","attrs":{"colspan":2,"background":"#44b3e1"},"content":[{"type":"paragraph","content":[{"type":"text","text":"UCW-30657","marks":[{"type":"strong"}]}]}]}]},{"type":"tableRow","content":[{"type":"tableCell","attrs":{"background":"#44b3e1"},"content":[{"type":"paragraph","content":[{"type":"text","text":"Brand Name","marks":[{"type":"strong"}]}]}]},{"type":"tableCell","attrs":{"colspan":2,"background":"#44b3e1"},"content":[{"type":"paragraph","content":[{"type":"text","text":"Bobbi Brown","marks":[{"type":"strong"}]}]}]}]},{"type":"tableRow","content":[{"type":"tableCell","attrs":{"background":"#ace5fe"},"content":[{"type":"paragraph","content":[{"type":"text","text":"Platform","marks":[{"type":"strong"}]}]}]},{"type":"tableCell","attrs":{"colspan":2,"background":"#ace5fe"},"content":[{"type":"paragraph","content":[{"type":"text","text":"Mall + Luxury","marks":[{"type":"strong"}]}]}]}]},{"type":"tableRow","content":[{"type":"tableCell","attrs":{"background":"#ace5fe"},"content":[{"type":"paragraph","content":[{"type":"text","text":"Particulars","marks":[{"type":"strong"}]}]}]},{"type":"tableCell","attrs":{"background":"#ace5fe"},"content":[{"type":"paragraph","content":[{"type":"text","text":"SKU Count","marks":[{"type":"strong"}]}]}]},{"type":"tableCell","attrs":{"background":"#ace5fe"},"content":[{"type":"paragraph","content":[{"type":"text","text":"Option Count","marks":[{"type":"strong"}]}]}]}]},{"type":"tableRow","content":[{"type":"tableCell","attrs":{"background":"white"},"content":[{"type":"paragraph","content":[{"type":"text","text":"Received"}]}]},{"type":"tableCell","attrs":{},"content":[{"type":"paragraph","content":[{"type":"text","text":"1"}]}]},{"type":"tableCell","attrs":{},"content":[{"type":"paragraph","content":[{"type":"text","text":"1"}]}]}]},{"type":"tableRow","content":[{"type":"tableCell","attrs":{"background":"white"},"content":[{"type":"paragraph","content":[{"type":"text","text":"Uploaded"}]}]},{"type":"tableCell","attrs":{},"content":[{"type":"paragraph","content":[{"type":"text","text":"1"}]}]},{"type":"tableCell","attrs":{},"content":[{"type":"paragraph","content":[{"type":"text","text":"1"}]}]}]},{"type":"tableRow","content":[{"type":"tableCell","attrs":{"background":"white"},"content":[{"type":"paragraph","content":[{"type":"text","text":"LIDs Shared"}]}]},{"type":"tableCell","attrs":{},"content":[{"type":"paragraph","content":[{"type":"text","text":"1"}]}]},{"type":"tableCell","attrs":{},"content":[{"type":"paragraph","content":[{"type":"text","text":"1"}]}]}]},{"type":"tableRow","content":[{"type":"tableCell","attrs":{"background":"white"},"content":[{"type":"paragraph","content":[{"type":"text","text":"LIDs Stuck in the System"}]}]},{"type":"tableCell","attrs":{},"content":[{"type":"paragraph","content":[{"type":"text","text":"0"}]}]},{"type":"tableCell","attrs":{},"content":[{"type":"paragraph","content":[{"type":"text","text":"0"}]}]}]}]} {adf} | S39: =IF(OR(G39="",H39=""),"",ROUND(H39-G39,2)) -> 7.15
A40: UCW-30661 | B40: ENRICH_ Images Update | Kids Iron Strip | Tata Cliq | Miduty | C40: CLOSED | D40: Medium | E40: netscribes | F40: Mohd Tahir Shaikh | G40: 46147.477 | H40: 46151.772 | I40: 1 | J40: Ad-hoc | K40: Retrigger Image | L40: Health & Wellness | M40: 1 | N40: 1 | O40: 1 | P40: Miduty | Q40: Mall | S40: =IF(OR(G40="",H40=""),"",ROUND(H40-G40,2)) -> 4.29
A41: UCW-30669 | B41: ENRICH_ Update Catalog images of Nutrabay <> TataCliq | C41: CLOSED | D41: Medium | E41: netscribes | F41: Mohd Tahir Shaikh | G41: 46147.528 | H41: 46153.56 | I41: 57 | J41: Ad-hoc | K41: Retrigger Image | L41: Health & Wellness | M41: 57 | N41: 57 | O41: 57 | P41: Nutrabay | Q41: Mall | S41: =IF(OR(G41="",H41=""),"",ROUND(H41-G41,2)) -> 6.03
A42: UCW-30670 | B42: Plix - Skincare Pending - UCW-29413 | C42: CLOSED Due to Inactive/Insufficient Information | D42: Medium | E42: Chirag Dubal | F42: Shraddha Dighe | G42: 46147.529 | H42: 46156.813 | I42: 0 | J42: E2E | K42: E2E | L42: Beauty & Grooming | M42: 0 | N42: 0 | O42: 19 | P42: Plix | Q42: Mall | S42: =IF(OR(G42="",H42=""),"",ROUND(H42-G42,2)) -> 9.28
A43: UCW-30673 | B43: Colors Queen || Makeup || 129094 || 31-03-2026 | C43: CLOSED | D43: Medium | E43: Chirag Dubal | F43: Shraddha Dighe | G43: 46147.565 | H43: 46163.624 | I43: 7 | J43: E2E | K43: E2E | L43: Beauty & Grooming | M43: 7 | N43: 7 | O43: 7 | P43: Colors Queen | Q43: Mall | R43: [^UCW-30673_Post Upload Status_V.2 (1).xlsx] [^Summary.zip] ;[^UCW-30673_Post Upload Status_V.2 (1) (994131e9-ae52-4ced-b529-0650b9be1d4a).xlsx] We are pleased to inform you that the listing IDs have been generated successfully. Please find the attached file for your reference, along with the summary table below. You may now proceed with price and inventory pushing from your end. {adf:display=block} {"type":"table","attrs":{"isNumberColumnEnabled":false,"layout":"center","localId":"3e13ad43-2274-418c-81b6-eb7df691b142"},"content":[{"type":"tableRow","content":[{"type":"tableCell","attrs":{"background":"#44b3e1"},"content":[{"type":"paragraph","content":[{"type":"text","text":"Ticket ID","marks":[{"type":"strong"}]}]}]},{"type":"tableCell","attrs":{"colspan":2,"background":"#44b3e1"},"content":[{"type":"paragraph","content":[{"type":"text","text":"UCW-30673","marks":[{"type":"strong"}]}]}]}]},{"type":"tableRow","content":[{"type":"tableCell","attrs":{"background":"#44b3e1"},"content":[{"type":"paragraph","content":[{"type":"text","text":"Brand Name","marks":[{"type":"strong"}]}]}]},{"type":"tableCell","attrs":{"colspan":2,"background":"#44b3e1"},"content":[{"type":"paragraph","content":[{"type":"text","text":"Colors Queen ","marks":[{"type":"strong"}]}]}]}]},{"type":"tableRow","content":[{"type":"tableCell","attrs":{"background":"#ace5fe"},"content":[{"type":"paragraph","content":[{"type":"text","text":"Platform","marks":[{"type":"strong"}]}]}]},{"type":"tableCell","attrs":{"colspan":2,"background":"#ace5fe"},"content":[{"type":"paragraph","content":[{"type":"text","text":"Mall","marks":[{"type":"strong"}]}]}]}]},{"type":"tableRow","content":[{"type":"tableCell","attrs":{"background":"#ace5fe"},"content":[{"type":"paragraph","content":[{"type":"text","text":"Particulars","marks":[{"type":"strong"}]}]}]},{"type":"tableCell","attrs":{"background":"#ace5fe"},"content":[{"type":"paragraph","content":[{"type":"text","text":"SKU Count","marks":[{"type":"strong"}]}]}]},{"type":"tableCell","attrs":{"background":"#ace5fe"},"content":[{"type":"paragraph","content":[{"type":"text","text":"Option Count","marks":[{"type":"strong"}]}]}]}]},{"type":"tableRow","content":[{"type":"tableCell","attrs":{"background":"white"},"content":[{"type":"paragraph","content":[{"type":"text","text":"Received"}]}]},{"type":"tableCell","attrs":{},"content":[{"type":"paragraph","content":[{"type":"text","text":"7"}]}]},{"type":"tableCell","attrs":{},"content":[{"type":"paragraph","content":[{"type":"text","text":"7"}]}]}]},{"type":"tableRow","content":[{"type":"tableCell","attrs":{"background":"white"},"content":[{"type":"paragraph","content":[{"type":"text","text":"Uploaded"}]}]},{"type":"tableCell","attrs":{},"content":[{"type":"paragraph","content":[{"type":"text","text":"7"}]}]},{"type":"tableCell","attrs":{},"content":[{"type":"paragraph","content":[{"type":"text","text":"7"}]}]}]},{"type":"tableRow","content":[{"type":"tableCell","attrs":{"background":"white"},"content":[{"type":"paragraph","content":[{"type":"text","text":"SKUs not uploaded"}]}]},{"type":"tableCell","attrs":{},"content":[{"type":"paragraph","content":[{"type":"text","text":"-"}]}]},{"type":"tableCell","attrs":{},"content":[{"type":"paragraph","content":[{"type":"text","text":"-"}]}]}]},{"type":"tableRow","content":[{"type":"tableCell","attrs":{"background":"white"},"content":[{"type":"paragraph","content":[{"type":"text","text":"Already Listed"}]}]},{"type":"tableCell","attrs":{},"content":[{"type":"paragraph","content":[{"type":"text","text":"-"}]}]},{"type":"tableCell","attrs":{},"content":[{"type":"paragraph","content":[{"type":"text","text":"-"}]}]}]},{"type":"tableRow","content":[{"type":"tableCell","attrs":{"background":"white"},"content":[{"type":"paragraph","content":[{"type":"text","text":"LIDs Shared"}]}]},{"type":"tableCell","attrs":{},"content":[{"type":"paragraph","content":[{"type":"text","text":"7"}]}]},{"type":"tableCell","attrs":{},"content":[{"type":"paragraph","content":[{"type":"text","text":"7"}]}]}]},{"type":"tableRow","content":[{"type":"tableCell","attrs":{"background":"white"},"content":[{"type":"paragraph","content":[{"type":"text","text":"LIDs Stuck in the System"}]}]},{"type":"tableCell","attrs":{},"content":[{"type":"paragraph","content":[{"type":"text","text":"-"}]}]},{"type":"tableCell","attrs":{},"content":[{"type":"paragraph","content":[{"type":"text","text":"-"}]}]}]}]} {adf} With this, we are closing this request from our end. Thank you for your patience, support, and cooperation throughout the process. Your brand is important to us, and we look forward to assisting you again. | S43: =IF(OR(G43="",H43=""),"",ROUND(H43-G43,2)) -> 16.06
A44: UCW-30677 | B44: CLONE - New Listings @TataCliq_25.04.2026 | C44: CLOSED | D44: Medium | E44: netscribes | F44: netscribes | G44: 46147.595 | H44: 46157.624 | I44: 28 | J44: E2E | K44: E2E | L44: Footwear | M44: 28 | N44: 4 | O44: 4 | P44: Pellealbero | Q44: Mall | R44: We have successfully uploaded this batch. Please find the summary of this batch. and attach Summary zip and Post upload Sheet. [^UCW-30677 Summary New.zip] [^UCW-30677 Post Upload Status_V.2 (1) (1).xlsx] ;LIDs attached[^UCW-30677 Post Upload Status_V.2 (1) (1) (5fb3ac03-0ec8-4abe-b036-0aad2c0c9851).xlsx] | S44: =IF(OR(G44="",H44=""),"",ROUND(H44-G44,2)) -> 10.03
A45: UCW-30678 | B45: Sub task - Tatacliq Footwear MP-62_Arrow_USPA_14-04-2026 | C45: CLOSED | D45: Medium | E45: netscribes | F45: netscribes | G45: 46147.601 | H45: 46157.622 | I45: 80 | J45: E2E | K45: E2E | L45: Footwear | M45: 80 | N45: 16 | O45: 16 | P45: U.S. Polo Assn. | Q45: Mall | R45: We would like to inform you that your ticket has been successfully uploaded in our system. Please find the attached summary files and post-upload file for footwear for your reference. We will share a further update once the listing IDs are generated. [^UCW-30678 - Post Upload Status .xlsx] [^Summary.zip] ;[^UCW-30678 - Post Upload Status.xlsx] We are pleased to inform you that the listing IDs have been generated successfully. Please find the attached file for your reference, along with the summary table below. You may now proceed with price and inventory pushing from your end.{color:#ffffff}__{color} {adf:display=block} {"type":"table","attrs":{"isNumberColumnEnabled":false,"layout":"center","localId":"6695b0d3-8524-46b9-b91f-b298db9a5da1","width":509},"content":[{"type":"tableRow","content":[{"type":"tableCell","attrs":{"background":"#44b3e1"},"content":[{"type":"paragraph","content":[{"type":"text","text":"Ticket ID","marks":[{"type":"strong"}]}]}]},{"type":"tableCell","attrs":{"colspan":2,"background":"#44b3e1"},"content":[{"type":"paragraph","content":[{"type":"text","text":"UCW-30678","marks":[{"type":"strong"}]}]}]}]},{"type":"tableRow","content":[{"type":"tableCell","attrs":{"background":"#44b3e1"},"content":[{"type":"paragraph","content":[{"type":"text","text":"Brand Name","marks":[{"type":"strong"}]}]}]},{"type":"tableCell","attrs":{"colspan":2,"background":"#44b3e1"},"content":[{"type":"paragraph","content":[{"type":"text","text":"U.S.Polo Assn.","marks":[{"type":"strong"}]}]}]}]},{"type":"tableRow","content":[{"type":"tableCell","attrs":{"background":"#ace5fe"},"content":[{"type":"paragraph","content":[{"type":"text","text":"Platform","marks":[{"type":"strong"}]}]}]},{"type":"tableCell","attrs":{"colspan":2,"background":"#ace5fe"},"content":[{"type":"paragraph","content":[{"type":"text","text":"Mall","marks":[{"type":"strong"}]}]}]}]},{"type":"tableRow","content":[{"type":"tableCell","attrs":{"background":"#ace5fe"},"content":[{"type":"paragraph","content":[{"type":"text","text":"Particulars","marks":[{"type":"strong"}]}]}]},{"type":"tableCell","attrs":{"background":"#ace5fe"},"content":[{"type":"paragraph","content":[{"type":"text","text":"SKU Count","marks":[{"type":"strong"}]}]}]},{"type":"tableCell","attrs":{"background":"#ace5fe"},"content":[{"type":"paragraph","content":[{"type":"text","text":"Option Count","marks":[{"type":"strong"}]}]}]}]},{"type":"tableRow","content":[{"type":"tableCell","attrs":{"background":"white"},"content":[{"type":"paragraph","content":[{"type":"text","text":"Received"}]}]},{"type":"tableCell","attrs":{},"content":[{"type":"paragraph","content":[{"type":"text","text":"16"}]}]},{"type":"tableCell","attrs":{},"content":[{"type":"paragraph","content":[{"type":"text","text":"80"}]}]}]},{"type":"tableRow","content":[{"type":"tableCell","attrs":{"background":"white"},"content":[{"type":"paragraph","content":[{"type":"text","text":"Uploaded"}]}]},{"type":"tableCell","attrs":{},"content":[{"type":"paragraph","content":[{"type":"text","text":"16"}]}]},{"type":"tableCell","attrs":{},"content":[{"type":"paragraph","content":[{"type":"text","text":"80"}]}]}]},{"type":"tableRow","content":[{"type":"tableCell","attrs":{"background":"white"},"content":[{"type":"paragraph","content":[{"type":"text","text":"SKUs not uploaded"}]}]},{"type":"tableCell","attrs":{},"content":[{"type":"paragraph","content":[{"type":"text","text":"-"}]}]},{"type":"tableCell","attrs":{},"content":[{"type":"paragraph","content":[{"type":"text","text":"-"}]}]}]},{"type":"tableRow","content":[{"type":"tableCell","attrs":{"background":"white"},"content":[{"type":"paragraph","content":[{"type":"text","text":"Already Listed"}]}]},{"type":"tableCell","attrs":{},"content":[{"type":"paragraph","content":[{"type":"text","text":"-"}]}]},{"type":"tableCell","attrs":{},"content":[{"type":"paragraph","content":[{"type":"text","text":"-"}]}]}]},{"type":"tableRow","content":[{"type":"tableCell","attrs":{"background":"white"},"content":[{"type":"paragraph","content":[{"type":"text","text":"LIDs Shared"}]}]},{"type":"tableCell","attrs":{},"content":[{"type":"paragraph","content":[{"type":"text","text":"16"}]}]},{"type":"tableCell","attrs":{},"content":[{"type":"paragraph","content":[{"type":"text","text":"80"}]}]}]},{"type":"tableRow","content":[{"type":"tableCell","attrs":{"background":"white"},"content":[{"type":"paragraph","content":[{"type":"text","text":"LIDs Stuck in the System"}]}]},{"type":"tableCell","attrs":{},"content":[{"type":"paragraph","content":[{"type":"text","text":"-"}]}]},{"type":"tableCell","attrs":{},"content":[{"type":"paragraph","content":[{"type":"text","text":"-"}]}]}]}]} {adf} For the accessories we have created a clone and will proceed accordingly with uploads - [https://tataunistore.atlassian.net/browse/UCW-31328|https://tataunistore.atlassian.net/browse/UCW-31328|smart-link] | S45: =IF(OR(G45="",H45=""),"",ROUND(H45-G45,2)) -> 10.02
A46: UCW-30684 | B46: Limese x Tata CLiQ | MOM | C46: CLOSED | D46: Medium | E46: Chirag Dubal | F46: Shraddha Dighe | G46: 46147.665 | H46: 46163.62 | I46: 25 | J46: E2E | K46: E2E | L46: Beauty & Grooming | M46: 25 | N46: 25 | O46: 25 | P46: Torriden | Q46: Mall | R46: [^UCW-30684_Post Upload Status_V.2 (1).xlsx] [^Summary.zip] ;[^UCW-30684_Post Upload Status_V.2 (1) (8e7d5320-5fe0-4d8c-be2a-9e53f067d3b6).xlsx] We are pleased to inform you that the listing IDs have been generated successfully. Please find the attached file for your reference, along with the summary table below. You may now proceed with price and inventory pushing from your end. {adf:display=block} {"type":"table","attrs":{"isNumberColumnEnabled":false,"layout":"center","localId":"12d224dd-af27-4ef6-9f46-f138d21ed9ca"},"content":[{"type":"tableRow","content":[{"type":"tableCell","attrs":{"background":"#44b3e1"},"content":[{"type":"paragraph","content":[{"type":"text","text":"Ticket ID","marks":[{"type":"strong"}]}]}]},{"type":"tableCell","attrs":{"colspan":2,"background":"#44b3e1"},"content":[{"type":"paragraph","content":[{"type":"text","text":"UCW-30684","marks":[{"type":"strong"}]}]}]}]},{"type":"tableRow","content":[{"type":"tableCell","attrs":{"background":"#44b3e1"},"content":[{"type":"paragraph","content":[{"type":"text","text":"Brand Name","marks":[{"type":"strong"}]}]}]},{"type":"tableCell","attrs":{"colspan":2,"background":"#44b3e1"},"content":[{"type":"paragraph","content":[{"type":"text","text":"Torriden ","marks":[{"type":"strong"}]}]}]}]},{"type":"tableRow","content":[{"type":"tableCell","attrs":{"background":"#ace5fe"},"content":[{"type":"paragraph","content":[{"type":"text","text":"Platform","marks":[{"type":"strong"}]}]}]},{"type":"tableCell","attrs":{"colspan":2,"background":"#ace5fe"},"content":[{"type":"paragraph","content":[{"type":"text","text":"Mall","marks":[{"type":"strong"}]}]}]}]},{"type":"tableRow","content":[{"type":"tableCell","attrs":{"background":"#ace5fe"},"content":[{"type":"paragraph","content":[{"type":"text","text":"Particulars","marks":[{"type":"strong"}]}]}]},{"type":"tableCell","attrs":{"background":"#ace5fe"},"content":[{"type":"paragraph","content":[{"type":"text","text":"SKU Count","marks":[{"type":"strong"}]}]}]},{"type":"tableCell","attrs":{"background":"#ace5fe"},"content":[{"type":"paragraph","content":[{"type":"text","text":"Option Count","marks":[{"type":"strong"}]}]}]}]},{"type":"tableRow","content":[{"type":"tableCell","attrs":{"background":"white"},"content":[{"type":"paragraph","content":[{"type":"text","text":"Received"}]}]},{"type":"tableCell","attrs":{},"content":[{"type":"paragraph","content":[{"type":"text","text":"25"}]}]},{"type":"tableCell","attrs":{},"content":[{"type":"paragraph","content":[{"type":"text","text":"25"}]}]}]},{"type":"tableRow","content":[{"type":"tableCell","attrs":{"background":"white"},"content":[{"type":"paragraph","content":[{"type":"text","text":"Uploaded"}]}]},{"type":"tableCell","attrs":{},"content":[{"type":"paragraph","content":[{"type":"text","text":"25"}]}]},{"type":"tableCell","attrs":{},"content":[{"type":"paragraph","content":[{"type":"text","text":"25"}]}]}]},{"type":"tableRow","content":[{"type":"tableCell","attrs":{"background":"white"},"content":[{"type":"paragraph","content":[{"type":"text","text":"SKUs not uploaded"}]}]},{"type":"tableCell","attrs":{},"content":[{"type":"paragraph","content":[{"type":"text","text":"-"}]}]},{"type":"tableCell","attrs":{},"content":[{"type":"paragraph","content":[{"type":"text","text":"-"}]}]}]},{"type":"tableRow","content":[{"type":"tableCell","attrs":{"background":"white"},"content":[{"type":"paragraph","content":[{"type":"text","text":"Already Listed"}]}]},{"type":"tableCell","attrs":{},"content":[{"type":"paragraph","content":[{"type":"text","text":"-"}]}]},{"type":"tableCell","attrs":{},"content":[{"type":"paragraph","content":[{"type":"text","text":"-"}]}]}]},{"type":"tableRow","content":[{"type":"tableCell","attrs":{"background":"white"},"content":[{"type":"paragraph","content":[{"type":"text","text":"LIDs Shared"}]}]},{"type":"tableCell","attrs":{},"content":[{"type":"paragraph","content":[{"type":"text","text":"25"}]}]},{"type":"tableCell","attrs":{},"content":[{"type":"paragraph","content":[{"type":"text","text":"25"}]}]}]},{"type":"tableRow","content":[{"type":"tableCell","attrs":{"background":"white"},"content":[{"type":"paragraph","content":[{"type":"text","text":"LIDs Stuck in the System"}]}]},{"type":"tableCell","attrs":{},"content":[{"type":"paragraph","content":[{"type":"text","text":"-"}]}]},{"type":"tableCell","attrs":{},"content":[{"type":"paragraph","content":[{"type":"text","text":"-"}]}]}]}]} {adf} With this, we are closing this request from our end. Thank you for your patience, support, and cooperation throughout the process. Your brand is important to us, and we look forward to assisting you again. | S46: =IF(OR(G46="",H46=""),"",ROUND(H46-G46,2)) -> 15.96
A47: UCW-30685 | B47: Puma Add now catalogue dated 30th April 2026 | C47: CLOSED | D47: Medium | E47: netscribes | F47: Mohd Tahir Shaikh | G47: 46147.665 | H47: 46157.619 | I47: 286 | J47: E2E | K47: E2E + Sell Now | L47: Footwear | M47: 246 | N47: 53 | O47: 61 | P47: Puma | Q47: Mall | R47: We would like to inform you that your ticket has been successfully uploaded in our system. Please find the attached summary files and post-upload file for your reference. We will share a further update once the listing IDs are generated. Please note that some styles are pending due to insufficient images. Once we receive the correct images, we will proceed with uploading the remaining styles.[^Post Upload Status_V.2 (1).xlsx] [^Summary.zip] ;[^UCW-30685.xlsx] Please find attached the sheet, where 53 options of Footwear have been listed. Kindly update the price and inventory, and share the summary once completed. {adf:display=block} {"type":"table","attrs":{"isNumberColumnEnabled":false,"layout":"center","localId":"06e9782f-4168-40b5-9425-f3d9979ce595"},"content":[{"type":"tableRow","content":[{"type":"tableCell","attrs":{"background":"#44b3e1"},"content":[{"type":"paragraph","content":[{"type":"text","text":"Ticket ID","marks":[{"type":"strong"}]}]}]},{"type":"tableCell","attrs":{"colspan":2,"background":"#44b3e1"},"content":[{"type":"paragraph","content":[{"type":"text","text":"UCW-30685","marks":[{"type":"strong"}]}]}]}]},{"type":"tableRow","content":[{"type":"tableCell","attrs":{"background":"#44b3e1"},"content":[{"type":"paragraph","content":[{"type":"text","text":"Brand Name","marks":[{"type":"strong"}]}]}]},{"type":"tableCell","attrs":{"colspan":2,"background":"#44b3e1"},"content":[{"type":"paragraph","content":[{"type":"text","text":"Puma","marks":[{"type":"strong"}]}]}]}]},{"type":"tableRow","content":[{"type":"tableCell","attrs":{"background":"#ace5fe"},"content":[{"type":"paragraph","content":[{"type":"text","text":"Platform","marks":[{"type":"strong"}]}]}]},{"type":"tableCell","attrs":{"colspan":2,"background":"#ace5fe"},"content":[{"type":"paragraph","content":[{"type":"text","text":"Mall","marks":[{"type":"strong"}]}]}]}]},{"type":"tableRow","content":[{"type":"tableCell","attrs":{"background":"#ace5fe"},"content":[{"type":"paragraph","content":[{"type":"text","text":"Particulars","marks":[{"type":"strong"}]}]}]},{"type":"tableCell","attrs":{"background":"#ace5fe"},"content":[{"type":"paragraph","content":[{"type":"text","text":"SKU Count","marks":[{"type":"strong"}]}]}]},{"type":"tableCell","attrs":{"background":"#ace5fe"},"content":[{"type":"paragraph","content":[{"type":"text","text":"Option Count","marks":[{"type":"strong"}]}]}]}]},{"type":"tableRow","content":[{"type":"tableCell","attrs":{"background":"white"},"content":[{"type":"paragraph","content":[{"type":"text","text":"Received"}]}]},{"type":"tableCell","attrs":{},"content":[{"type":"paragraph","content":[{"type":"text","text":"286"}]}]},{"type":"tableCell","attrs":{},"content":[{"type":"paragraph","content":[{"type":"text","text":"61"}]}]}]},{"type":"tableRow","content":[{"type":"tableCell","attrs":{"background":"white"},"content":[{"type":"paragraph","content":[{"type":"text","text":"Uploaded"}]}]},{"type":"tableCell","attrs":{},"content":[{"type":"paragraph","content":[{"type":"text","text":"246"}]}]},{"type":"tableCell","attrs":{},"content":[{"type":"paragraph","content":[{"type":"text","text":"53"}]}]}]},{"type":"tableRow","content":[{"type":"tableCell","attrs":{"background":"white"},"content":[{"type":"paragraph","content":[{"type":"text","text":"Already Listed"}]}]},{"type":"tableCell","attrs":{},"content":[{"type":"paragraph","content":[{"type":"text","text":"1"}]}]},{"type":"tableCell","attrs":{},"content":[{"type":"paragraph","content":[{"type":"text","text":"1"}]}]}]},{"type":"tableRow","content":[{"type":"tableCell","attrs":{"background":"white"},"content":[{"type":"paragraph","content":[{"type":"text","text":"SKUs Not Uploaded"}]}]},{"type":"tableCell","attrs":{},"content":[{"type":"paragraph","content":[{"type":"text","text":"39"}]}]},{"type":"tableCell","attrs":{},"content":[{"type":"paragraph","content":[{"type":"text","text":"7"}]}]}]},{"type":"tableRow","content":[{"type":"tableCell","attrs":{"background":"white"},"content":[{"type":"paragraph","content":[{"type":"text","text":"LIDs Shared"}]}]},{"type":"tableCell","attrs":{},"content":[{"type":"paragraph","content":[{"type":"text","text":"246"}]}]},{"type":"tableCell","attrs":{},"content":[{"type":"paragraph","content":[{"type":"text","text":"53"}]}]}]},{"type":"tableRow","content":[{"type":"tableCell","attrs":{"background":"white"},"content":[{"type":"paragraph","content":[{"type":"text","text":"LIDs Stuck in the System"}]}]},{"type":"tableCell","attrs":{},"content":[{"type":"paragraph","content":[{"type":"text","text":"0"}]}]},{"type":"tableCell","attrs":{},"content":[{"type":"paragraph","content":[{"type":"text","text":"0"}]}]}]}]} {adf} | S47: =IF(OR(G47="",H47=""),"",ROUND(H47-G47,2)) -> 9.95
A48: UCW-30686 | B48: CLONE - New Brand Listing - Oteria | C48: CLOSED | D48: Medium | E48: netscribes | F48: Shraddha Dighe | G48: 46147.669 | H48: 46158.619 | I48: 38 | J48: E2E | K48: E2E | L48: Beauty & Grooming | M48: 26 | N48: 26 | O48: 38 | P48: Oteria | Q48: Mall | R48: [^UCW-30686 Post Upload Status_V.2 (1).xlsx] [^Summary.zip] ;[^UCW-30686.xlsx] Please find attached the sheet, where 26 options of Beauty & Grooming have been listed. Kindly update the price and inventory, and share the summary once completed. {adf:display=block} {"type":"table","attrs":{"isNumberColumnEnabled":false,"layout":"center","localId":"d2100fd8-3095-428e-b8ca-e1f851324232"},"content":[{"type":"tableRow","content":[{"type":"tableCell","attrs":{"background":"#44b3e1"},"content":[{"type":"paragraph","content":[{"type":"text","text":"Ticket ID","marks":[{"type":"strong"}]}]}]},{"type":"tableCell","attrs":{"colspan":2,"background":"#44b3e1"},"content":[{"type":"paragraph","content":[{"type":"text","text":"UCW-30686","marks":[{"type":"strong"}]}]}]}]},{"type":"tableRow","content":[{"type":"tableCell","attrs":{"background":"#44b3e1"},"content":[{"type":"paragraph","content":[{"type":"text","text":"Brand Name","marks":[{"type":"strong"}]}]}]},{"type":"tableCell","attrs":{"colspan":2,"background":"#44b3e1"},"content":[{"type":"paragraph","content":[{"type":"text","text":"Oteria","marks":[{"type":"strong"}]}]}]}]},{"type":"tableRow","content":[{"type":"tableCell","attrs":{"background":"#ace5fe"},"content":[{"type":"paragraph","content":[{"type":"text","text":"Platform","marks":[{"type":"strong"}]}]}]},{"type":"tableCell","attrs":{"colspan":2,"background":"#ace5fe"},"content":[{"type":"paragraph","content":[{"type":"text","text":"Mall","marks":[{"type":"strong"}]}]}]}]},{"type":"tableRow","content":[{"type":"tableCell","attrs":{"background":"#ace5fe"},"content":[{"type":"paragraph","content":[{"type":"text","text":"Particulars","marks":[{"type":"strong"}]}]}]},{"type":"tableCell","attrs":{"background":"#ace5fe"},"content":[{"type":"paragraph","content":[{"type":"text","text":"SKU Count","marks":[{"type":"strong"}]}]}]},{"type":"tableCell","attrs":{"background":"#ace5fe"},"content":[{"type":"paragraph","content":[{"type":"text","text":"Option Count","marks":[{"type":"strong"}]}]}]}]},{"type":"tableRow","content":[{"type":"tableCell","attrs":{"background":"white"},"content":[{"type":"paragraph","content":[{"type":"text","text":"Received"}]}]},{"type":"tableCell","attrs":{},"content":[{"type":"paragraph","content":[{"type":"text","text":"38"}]}]},{"type":"tableCell","attrs":{},"content":[{"type":"paragraph","content":[{"type":"text","text":"38"}]}]}]},{"type":"tableRow","content":[{"type":"tableCell","attrs":{"background":"white"},"content":[{"type":"paragraph","content":[{"type":"text","text":"Uploaded"}]}]},{"type":"tableCell","attrs":{},"content":[{"type":"paragraph","content":[{"type":"text","text":"26"}]}]},{"type":"tableCell","attrs":{},"content":[{"type":"paragraph","content":[{"type":"text","text":"26"}]}]}]},{"type":"tableRow","content":[{"type":"tableCell","attrs":{"background":"white"},"content":[{"type":"paragraph","content":[{"type":"text","text":"SKUs not uploaded"}]}]},{"type":"tableCell","attrs":{},"content":[{"type":"paragraph","content":[{"type":"text","text":"12"}]}]},{"type":"tableCell","attrs":{},"content":[{"type":"paragraph","content":[{"type":"text","text":"12"}]}]}]},{"type":"tableRow","content":[{"type":"tableCell","attrs":{"background":"white"},"content":[{"type":"paragraph","content":[{"type":"text","text":"LIDs Shared"}]}]},{"type":"tableCell","attrs":{},"content":[{"type":"paragraph","content":[{"type":"text","text":"26"}]}]},{"type":"tableCell","attrs":{},"content":[{"type":"paragraph","content":[{"type":"text","text":"26"}]}]}]},{"type":"tableRow","content":[{"type":"tableCell","attrs":{"background":"white"},"content":[{"type":"paragraph","content":[{"type":"text","text":"LIDs Stuck in the System"}]}]},{"type":"tableCell","attrs":{},"content":[{"type":"paragraph","content":[{"type":"text","text":"0"}]}]},{"type":"tableCell","attrs":{},"content":[{"type":"paragraph","content":[{"type":"text","text":"0"}]}]}]}]} {adf} *Call out-12 options were not uploaded due to various issues. We observed that the images are blurred and the size mentioned in the title does not match the size shown in the image. Therefore, we request you to kindly review the post-upload sheet and share the revised details accordingly.* | S48: =IF(OR(G48="",H48=""),"",ROUND(H48-G48,2)) -> 10.95
A49: UCW-30690 | B49: Cordwainers - FTW - 01/05/26 - 120 SKUs | C49: CLOSED | D49: Medium | E49: netscribes | F49: Mohd Tahir Shaikh | G49: 46147.681 | H49: 46150.617 | I49: 120 | J49: E2E | K49: E2E | L49: Footwear | M49: 120 | N49: 20 | O49: 20 | P49: Cordwainers | Q49: Luxury | R49: We have successfully uploaded this batch. Please find the attached summary sheet and summary report.[^Summary.zip] [^Post Upload Status_V.2 (1).xlsx] ;[^UCW-30690.xlsx] Please find attached the sheet, where 20 options have been listed. Kindly update the price and inventory, and share the summary once completed. {adf:display=block} {"type":"table","attrs":{"isNumberColumnEnabled":false,"layout":"center","localId":"69231b6d-5342-4f7b-80c5-f60b91736843"},"content":[{"type":"tableRow","content":[{"type":"tableCell","attrs":{"background":"#44b3e1"},"content":[{"type":"paragraph","content":[{"type":"text","text":"Ticket ID","marks":[{"type":"strong"}]}]}]},{"type":"tableCell","attrs":{"colspan":2,"background":"#44b3e1"},"content":[{"type":"paragraph","content":[{"type":"text","text":"UCW-30690","marks":[{"type":"strong"}]}]}]}]},{"type":"tableRow","content":[{"type":"tableCell","attrs":{"background":"#44b3e1"},"content":[{"type":"paragraph","content":[{"type":"text","text":"Brand Name","marks":[{"type":"strong"}]}]}]},{"type":"tableCell","attrs":{"colspan":2,"background":"#44b3e1"},"content":[{"type":"paragraph","content":[{"type":"text","text":"Cordwainers","marks":[{"type":"strong"}]}]}]}]},{"type":"tableRow","content":[{"type":"tableCell","attrs":{"background":"#ace5fe"},"content":[{"type":"paragraph","content":[{"type":"text","text":"Platform","marks":[{"type":"strong"}]}]}]},{"type":"tableCell","attrs":{"colspan":2,"background":"#ace5fe"},"content":[{"type":"paragraph","content":[{"type":"text","text":"Luxury","marks":[{"type":"strong"}]}]}]}]},{"type":"tableRow","content":[{"type":"tableCell","attrs":{"background":"#ace5fe"},"content":[{"type":"paragraph","content":[{"type":"text","text":"Particulars","marks":[{"type":"strong"}]}]}]},{"type":"tableCell","attrs":{"background":"#ace5fe"},"content":[{"type":"paragraph","content":[{"type":"text","text":"SKU Count","marks":[{"type":"strong"}]}]}]},{"type":"tableCell","attrs":{"background":"#ace5fe"},"content":[{"type":"paragraph","content":[{"type":"text","text":"Option Count","marks":[{"type":"strong"}]}]}]}]},{"type":"tableRow","content":[{"type":"tableCell","attrs":{"background":"white"},"content":[{"type":"paragraph","content":[{"type":"text","text":"Received"}]}]},{"type":"tableCell","attrs":{},"content":[{"type":"paragraph","content":[{"type":"text","text":"120"}]}]},{"type":"tableCell","attrs":{},"content":[{"type":"paragraph","content":[{"type":"text","text":"20"}]}]}]},{"type":"tableRow","content":[{"type":"tableCell","attrs":{"background":"white"},"content":[{"type":"paragraph","content":[{"type":"text","text":"Uploaded"}]}]},{"type":"tableCell","attrs":{},"content":[{"type":"paragraph","content":[{"type":"text","text":"120"}]}]},{"type":"tableCell","attrs":{},"content":[{"type":"paragraph","content":[{"type":"text","text":"20"}]}]}]},{"type":"tableRow","content":[{"type":"tableCell","attrs":{"background":"white"},"content":[{"type":"paragraph","content":[{"type":"text","text":"LIDs Shared"}]}]},{"type":"tableCell","attrs":{},"content":[{"type":"paragraph","content":[{"type":"text","text":"120"}]}]},{"type":"tableCell","attrs":{},"content":[{"type":"paragraph","content":[{"type":"text","text":"20"}]}]}]},{"type":"tableRow","content":[{"type":"tableCell","attrs":{"background":"white"},"content":[{"type":"paragraph","content":[{"type":"text","text":"LIDs Stuck in the System"}]}]},{"type":"tableCell","attrs":{},"content":[{"type":"paragraph","content":[{"type":"text","text":"0"}]}]},{"type":"tableCell","attrs":{},"content":[{"type":"paragraph","content":[{"type":"text","text":"0"}]}]}]}]} {adf} | S49: =IF(OR(G49="",H49=""),"",ROUND(H49-G49,2)) -> 2.94
A50: UCW-30696 | B50: Guess Footwear Men & Women (New) 31 Options 02-05-2026 | C50: CLOSED | D50: Medium | E50: Chirag Dubal | F50: Shloka Chakre | G50: 46147.688 | H50: 46155.735 | I50: 157 | J50: E2E | K50: E2E+Dual Listing | L50: Footwear | M50: 157 | N50: 31 | O50: 31 | P50: Guess | Q50: Mall;Luxury | R50: We have successfully uploaded this batch. Please find the attached summary sheet and summary report.[^Post Upload Status_V.2 (1).xlsx] [^Summary.zip] ;[^UCW-30696_LID.xlsx] Hi [@Malik Yogita|mailto:Yogita.Malik@guess.eu], Please find attached the sheet, where 31 options on Luxury 31 options on Mall have been listed. Kindly update the price and inventory, and share the summary once completed. {adf:display=block} {"type":"table","attrs":{"isNumberColumnEnabled":false,"layout":"center","localId":"285f9d84-6bf1-4a73-ac95-66aa53e757b1"},"content":[{"type":"tableRow","content":[{"type":"tableCell","attrs":{"background":"#4d93d9"},"content":[{"type":"paragraph","content":[{"type":"text","text":"Ticket ID","marks":[{"type":"strong"}]}]}]},{"type":"tableCell","attrs":{"colspan":4,"background":"#4d93d9"},"content":[{"type":"paragraph","content":[{"type":"text","text":"UCW-30696","marks":[{"type":"strong"}]}]}]}]},{"type":"tableRow","content":[{"type":"tableCell","attrs":{"background":"#4d93d9"},"content":[{"type":"paragraph","content":[{"type":"text","text":"Brand Name","marks":[{"type":"strong"}]}]}]},{"type":"tableCell","attrs":{"colspan":4,"background":"#4d93d9"},"content":[{"type":"paragraph","content":[{"type":"text","text":"Guess","marks":[{"type":"strong"}]}]}]}]},{"type":"tableRow","content":[{"type":"tableCell","attrs":{"background":"#ace5fe"},"content":[{"type":"paragraph","content":[{"type":"text","text":"Platform","marks":[{"type":"strong"}]}]}]},{"type":"tableCell","attrs":{"colspan":2,"background":"#ace5fe"},"content":[{"type":"paragraph","content":[{"type":"text","text":"Luxury","marks":[{"type":"strong"}]}]}]},{"type":"tableCell","attrs":{"colspan":2,"background":"#ace5fe"},"content":[{"type":"paragraph","content":[{"type":"text","text":"Mall","marks":[{"type":"strong"}]}]}]}]},{"type":"tableRow","content":[{"type":"tableCell","attrs":{"background":"#ace5fe"},"content":[{"type":"paragraph","content":[{"type":"text","text":"Particulars","marks":[{"type":"strong"}]}]}]},{"type":"tableCell","attrs":{"background":"#ace5fe"},"content":[{"type":"paragraph","content":[{"type":"text","text":"SKU Count","marks":[{"type":"strong"}]}]}]},{"type":"tableCell","attrs":{"background":"#ace5fe"},"content":[{"type":"paragraph","content":[{"type":"text","text":"Option Count","marks":[{"type":"strong"}]}]}]},{"type":"tableCell","attrs":{"background":"#ace5fe"},"content":[{"type":"paragraph","content":[{"type":"text","text":"SKU Count","marks":[{"type":"strong"}]}]}]},{"type":"tableCell","attrs":{"background":"#ace5fe"},"content":[{"type":"paragraph","content":[{"type":"text","text":"Option Count","marks":[{"type":"strong"}]}]}]}]},{"type":"tableRow","content":[{"type":"tableCell","attrs":{"background":"white"},"content":[{"type":"paragraph","content":[{"type":"text","text":"Received"}]}]},{"type":"tableCell","attrs":{"background":"white"},"content":[{"type":"paragraph","content":[{"type":"text","text":"157"}]}]},{"type":"tableCell","attrs":{"background":"white"},"content":[{"type":"paragraph","content":[{"type":"text","text":"31"}]}]},{"type":"tableCell","attrs":{"background":"white"},"content":[{"type":"paragraph","content":[{"type":"text","text":"157"}]}]},{"type":"tableCell","attrs":{"background":"white"},"content":[{"type":"paragraph","content":[{"type":"text","text":"31"}]}]}]},{"type":"tableRow","content":[{"type":"tableCell","attrs":{"background":"white"},"content":[{"type":"paragraph","content":[{"type":"text","text":"Uploaded"}]}]},{"type":"tableCell","attrs":{"background":"white"},"content":[{"type":"paragraph","content":[{"type":"text","text":"157"}]}]},{"type":"tableCell","attrs":{"background":"white"},"content":[{"type":"paragraph","content":[{"type":"text","text":"31"}]}]},{"type":"tableCell","attrs":{"background":"white"},"content":[{"type":"paragraph","content":[{"type":"text","text":"157"}]}]},{"type":"tableCell","attrs":{"background":"white"},"content":[{"type":"paragraph","content":[{"type":"text","text":"31"}]}]}]},{"type":"tableRow","content":[{"type":"tableCell","attrs":{"background":"white"},"content":[{"type":"paragraph","content":[{"type":"text","text":"SKUs Not Uploaded"}]}]},{"type":"tableCell","attrs":{"background":"white"},"content":[{"type":"paragraph","content":[{"type":"text","text":"0"}]}]},{"type":"tableCell","attrs":{"background":"white"},"content":[{"type":"paragraph","content":[{"type":"text","text":"0"}]}]},{"type":"tableCell","attrs":{"background":"white"},"content":[{"type":"paragraph","content":[{"type":"text","text":"0"}]}]},{"type":"tableCell","attrs":{"background":"white"},"content":[{"type":"paragraph","content":[{"type":"text","text":"0"}]}]}]},{"type":"tableRow","content":[{"type":"tableCell","attrs":{"background":"white"},"content":[{"type":"paragraph","content":[{"type":"text","text":"LIDs Shared"}]}]},{"type":"tableCell","attrs":{"background":"white"},"content":[{"type":"paragraph","content":[{"type":"text","text":"157"}]}]},{"type":"tableCell","attrs":{"background":"white"},"content":[{"type":"paragraph","content":[{"type":"text","text":"31"}]}]},{"type":"tableCell","attrs":{"background":"white"},"content":[{"type":"paragraph","content":[{"type":"text","text":"157"}]}]},{"type":"tableCell","attrs":{"background":"white"},"content":[{"type":"paragraph","content":[{"type":"text","text":"31"}]}]}]},{"type":"tableRow","content":[{"type":"tableCell","attrs":{"background":"white"},"content":[{"type":"paragraph","content":[{"type":"text","text":"LIDs Stuck in the System"}]}]},{"type":"tableCell","attrs":{"background":"white"},"content":[{"type":"paragraph","content":[{"type":"text","text":"0"}]}]},{"type":"tableCell","attrs":{"background":"white"},"content":[{"type":"paragraph","content":[{"type":"text","text":"0"}]}]},{"type":"tableCell","attrs":{"background":"white"},"content":[{"type":"paragraph","content":[{"type":"text","text":"0"}]}]},{"type":"tableCell","attrs":{"background":"white"},"content":[{"type":"paragraph","content":[{"type":"text","text":"0"}]}]}]}]} {adf} Regards, Team Netscribes | S50: =IF(OR(G50="",H50=""),"",ROUND(H50-G50,2)) -> 8.05
A51: UCW-30698 | B51: Rosso Brunello - FTW - 1/05/26 - 77 SKUs | C51: CLOSED | D51: Medium | E51: netscribes | F51: Mohd Tahir Shaikh | G51: 46147.69 | H51: 46149.702 | I51: 76 | J51: E2E | K51: E2E | L51: Footwear | M51: 76 | N51: 10 | O51: 10 | P51: Rosso Brunello | Q51: Luxury | R51: We have successfully uploaded this batch. Please find the attached summary sheet and summary report.[^Post Upload Status_V.2 (1).xlsx] [^Summary.zip] ;[^UCW-30698_LID.xlsx] Hi [@Sakshi@rossobrunello.com|mailto:ecommerce@rossobrunello.com], Please find attached the sheet, where 10 options have been listed. Kindly update the price and inventory, and share the summary once completed. {adf:display=block} {"type":"table","attrs":{"isNumberColumnEnabled":false,"layout":"center","localId":"c52b10eb-9a84-4542-bc86-9887a0539f5a"},"content":[{"type":"tableRow","content":[{"type":"tableCell","attrs":{"background":"#44b3e1"},"content":[{"type":"paragraph","content":[{"type":"text","text":"Ticket ID","marks":[{"type":"strong"}]}]}]},{"type":"tableCell","attrs":{"colspan":2,"background":"#44b3e1"},"content":[{"type":"paragraph","content":[{"type":"text","text":"UCW-30698","marks":[{"type":"strong"}]}]}]}]},{"type":"tableRow","content":[{"type":"tableCell","attrs":{"background":"#44b3e1"},"content":[{"type":"paragraph","content":[{"type":"text","text":"Brand Name","marks":[{"type":"strong"}]}]}]},{"type":"tableCell","attrs":{"colspan":2,"background":"#44b3e1"},"content":[{"type":"paragraph","content":[{"type":"text","text":"Rosso Brunello","marks":[{"type":"strong"}]}]}]}]},{"type":"tableRow","content":[{"type":"tableCell","attrs":{"background":"#44b3e1"},"content":[{"type":"paragraph","content":[{"type":"text","text":"Platform","marks":[{"type":"strong"}]}]}]},{"type":"tableCell","attrs":{"colspan":2,"background":"#44b3e1"},"content":[{"type":"paragraph","content":[{"type":"text","text":"Luxury","marks":[{"type":"strong"}]}]}]}]},{"type":"tableRow","content":[{"type":"tableCell","attrs":{"background":"#ace5fe"},"content":[{"type":"paragraph","content":[{"type":"text","text":"Particulars","marks":[{"type":"strong"}]}]}]},{"type":"tableCell","attrs":{"background":"#ace5fe"},"content":[{"type":"paragraph","content":[{"type":"text","text":"SKU Count","marks":[{"type":"strong"}]}]}]},{"type":"tableCell","attrs":{"background":"#ace5fe"},"content":[{"type":"paragraph","content":[{"type":"text","text":"Option Count","marks":[{"type":"strong"}]}]}]}]},{"type":"tableRow","content":[{"type":"tableCell","attrs":{"background":"white"},"content":[{"type":"paragraph","content":[{"type":"text","text":"Received"}]}]},{"type":"tableCell","attrs":{"background":"white"},"content":[{"type":"paragraph","content":[{"type":"text","text":"76"}]}]},{"type":"tableCell","attrs":{"background":"white"},"content":[{"type":"paragraph","content":[{"type":"text","text":"10"}]}]}]},{"type":"tableRow","content":[{"type":"tableCell","attrs":{"background":"white"},"content":[{"type":"paragraph","content":[{"type":"text","text":"Uploaded"}]}]},{"type":"tableCell","attrs":{"background":"white"},"content":[{"type":"paragraph","content":[{"type":"text","text":"76"}]}]},{"type":"tableCell","attrs":{"background":"white"},"content":[{"type":"paragraph","content":[{"type":"text","text":"10"}]}]}]},{"type":"tableRow","content":[{"type":"tableCell","attrs":{"background":"white"},"content":[{"type":"paragraph","content":[{"type":"text","text":"Not Uploaded"}]}]},{"type":"tableCell","attrs":{"background":"white"},"content":[{"type":"paragraph","content":[{"type":"text","text":"0"}]}]},{"type":"tableCell","attrs":{"background":"white"},"content":[{"type":"paragraph","content":[{"type":"text","text":"0"}]}]}]},{"type":"tableRow","content":[{"type":"tableCell","attrs":{"background":"white"},"content":[{"type":"paragraph","content":[{"type":"text","text":"LIDs Shared"}]}]},{"type":"tableCell","attrs":{"background":"white"},"content":[{"type":"paragraph","content":[{"type":"text","text":"76"}]}]},{"type":"tableCell","attrs":{"background":"white"},"content":[{"type":"paragraph","content":[{"type":"text","text":"10"}]}]}]},{"type":"tableRow","content":[{"type":"tableCell","attrs":{"background":"white"},"content":[{"type":"paragraph","content":[{"type":"text","text":"LIDs Stuck in the System"}]}]},{"type":"tableCell","attrs":{"background":"white"},"content":[{"type":"paragraph","content":[{"type":"text","text":"0"}]}]},{"type":"tableCell","attrs":{"background":"white"},"content":[{"type":"paragraph","content":[{"type":"text","text":"0"}]}]}]}]} {adf} Regards, Team Netscribes | S51: =IF(OR(G51="",H51=""),"",ROUND(H51-G51,2)) -> 2.01
A52: UCW-30719 | B52: New Listings_Khadlaj | C52: CLOSED | D52: Medium | E52: Chirag Dubal | F52: Simi Raichel Zachariah | G52: 46147.747 | H52: 46163.588 | I52: 33 | J52: E2E | K52: E2E | L52: Beauty & Grooming | M52: 33 | N52: 33 | O52: 33 | P52: Khadlaj | Q52: Mall | R52: [^Summary.zip] [^UCW-30719 Post Upload Status_V.2 (1).xlsx] ;[^UCW-30719.xlsx] We are pleased to inform you that the listing IDs have been generated successfully. Please find the attached file for your reference, along with the summary table below. You may now proceed with price and inventory pushing from your end. {adf:display=block} {"type":"table","attrs":{"isNumberColumnEnabled":false,"layout":"center","localId":"ea9c59c3-6a72-4c13-b386-49d0cdc39ade"},"content":[{"type":"tableRow","content":[{"type":"tableCell","attrs":{"background":"#44b3e1"},"content":[{"type":"paragraph","content":[{"type":"text","text":"Ticket ID","marks":[{"type":"strong"}]}]}]},{"type":"tableCell","attrs":{"colspan":2,"background":"#44b3e1"},"content":[{"type":"paragraph","content":[{"type":"text","text":"UCW-30719","marks":[{"type":"strong"}]}]}]}]},{"type":"tableRow","content":[{"type":"tableCell","attrs":{"background":"#44b3e1"},"content":[{"type":"paragraph","content":[{"type":"text","text":"Brand Name","marks":[{"type":"strong"}]}]}]},{"type":"tableCell","attrs":{"colspan":2,"background":"#44b3e1"},"content":[{"type":"paragraph","content":[{"type":"text","text":"Khadlaj","marks":[{"type":"strong"}]}]}]}]},{"type":"tableRow","content":[{"type":"tableCell","attrs":{"background":"#ace5fe"},"content":[{"type":"paragraph","content":[{"type":"text","text":"Platform","marks":[{"type":"strong"}]}]}]},{"type":"tableCell","attrs":{"colspan":2,"background":"#ace5fe"},"content":[{"type":"paragraph","content":[{"type":"text","text":"Mall","marks":[{"type":"strong"}]}]}]}]},{"type":"tableRow","content":[{"type":"tableCell","attrs":{"background":"#ace5fe"},"content":[{"type":"paragraph","content":[{"type":"text","text":"Particulars","marks":[{"type":"strong"}]}]}]},{"type":"tableCell","attrs":{"background":"#ace5fe"},"content":[{"type":"paragraph","content":[{"type":"text","text":"SKU Count","marks":[{"type":"strong"}]}]}]},{"type":"tableCell","attrs":{"background":"#ace5fe"},"content":[{"type":"paragraph","content":[{"type":"text","text":"Option Count","marks":[{"type":"strong"}]}]}]}]},{"type":"tableRow","content":[{"type":"tableCell","attrs":{"background":"white"},"content":[{"type":"paragraph","content":[{"type":"text","text":"Received"}]}]},{"type":"tableCell","attrs":{},"content":[{"type":"paragraph","content":[{"type":"text","text":"33"}]}]},{"type":"tableCell","attrs":{},"content":[{"type":"paragraph","content":[{"type":"text","text":"33"}]}]}]},{"type":"tableRow","content":[{"type":"tableCell","attrs":{"background":"white"},"content":[{"type":"paragraph","content":[{"type":"text","text":"Uploaded"}]}]},{"type":"tableCell","attrs":{},"content":[{"type":"paragraph","content":[{"type":"text","text":"33"}]}]},{"type":"tableCell","attrs":{},"content":[{"type":"paragraph","content":[{"type":"text","text":"33"}]}]}]},{"type":"tableRow","content":[{"type":"tableCell","attrs":{"background":"white"},"content":[{"type":"paragraph","content":[{"type":"text","text":"SKUs not uploaded"}]}]},{"type":"tableCell","attrs":{},"content":[{"type":"paragraph","content":[{"type":"text","text":"0"}]}]},{"type":"tableCell","attrs":{},"content":[{"type":"paragraph","content":[{"type":"text","text":"0"}]}]}]},{"type":"tableRow","content":[{"type":"tableCell","attrs":{"background":"white"},"content":[{"type":"paragraph","content":[{"type":"text","text":"LIDs Shared"}]}]},{"type":"tableCell","attrs":{},"content":[{"type":"paragraph","content":[{"type":"text","text":"33"}]}]},{"type":"tableCell","attrs":{},"content":[{"type":"paragraph","content":[{"type":"text","text":"33"}]}]}]},{"type":"tableRow","content":[{"type":"tableCell","attrs":{"background":"white"},"content":[{"type":"paragraph","content":[{"type":"text","text":"LIDs Stuck in the System"}]}]},{"type":"tableCell","attrs":{},"content":[{"type":"paragraph","content":[{"type":"text","text":"0"}]}]},{"type":"tableCell","attrs":{},"content":[{"type":"paragraph","content":[{"type":"text","text":"0"}]}]}]}]} {adf} With this, we are closing this request from our end. Thank you for your patience, support, and cooperation throughout the process. Your brand is important to us, and we look forward to assisting you again. | S52: =IF(OR(G52="",H52=""),"",ROUND(H52-G52,2)) -> 15.84
A53: UCW-30723 | B53: YSL Fragrance Listing | C53: CLOSED | D53: Medium | E53: Chirag Dubal | F53: Simi Raichel Zachariah | G53: 46147.76 | H53: 46163.464 | I53: 14 | J53: E2E | K53: E2E | L53: Beauty & Grooming | M53: 6 | N53: 6 | O53: 14 | P53: Yves Saint Laurent | Q53: Luxury | R53: [^Summary.zip] [^UCW-30723_Post Upload Status_V.2 (1).xlsx] ;*Please ignore the previous mail.* We would like to inform you that your ticket has been successfully uploaded in our system. Please find the attached summary files and post-upload file for your reference. We will share a further update once the listing IDs are generated. Your request is important to us, and we will continue to keep you updated throughout the ticket journey. [^UCW-30723_Post Upload Status_V.2 (1) (f02d3a1b-d4f3-414c-b212-a6c1b447215a).xlsx] [^Summary (95540ff1-65a6-49ba-aa86-0db5c786467d).zip] ;[^UCW-30723.xlsx] We are pleased to inform you that the listing IDs have been generated successfully. Please find the attached file for your reference, along with the summary table below. You may now proceed with price and inventory pushing from your end. {adf:display=block} {"type":"table","attrs":{"isNumberColumnEnabled":false,"layout":"center","localId":"39bdb1c6-ae3c-4a08-a7dc-748030555d91"},"content":[{"type":"tableRow","content":[{"type":"tableCell","attrs":{"background":"#44b3e1"},"content":[{"type":"paragraph","content":[{"type":"text","text":"Ticket ID","marks":[{"type":"strong"}]}]}]},{"type":"tableCell","attrs":{"colspan":2,"background":"#44b3e1"},"content":[{"type":"paragraph","content":[{"type":"text","text":"UCW-30723","marks":[{"type":"strong"}]}]}]}]},{"type":"tableRow","content":[{"type":"tableCell","attrs":{"background":"#44b3e1"},"content":[{"type":"paragraph","content":[{"type":"text","text":"Brand Name","marks":[{"type":"strong"}]}]}]},{"type":"tableCell","attrs":{"colspan":2,"background":"#44b3e1"},"content":[{"type":"paragraph","content":[{"type":"text","text":"Yves Saint Laurent","marks":[{"type":"strong"}]}]}]}]},{"type":"tableRow","content":[{"type":"tableCell","attrs":{"background":"#ace5fe"},"content":[{"type":"paragraph","content":[{"type":"text","text":"Platform","marks":[{"type":"strong"}]}]}]},{"type":"tableCell","attrs":{"colspan":2,"background":"#ace5fe"},"content":[{"type":"paragraph","content":[{"type":"text","text":"Luxury","marks":[{"type":"strong"}]}]}]}]},{"type":"tableRow","content":[{"type":"tableCell","attrs":{"background":"#ace5fe"},"content":[{"type":"paragraph","content":[{"type":"text","text":"Particulars","marks":[{"type":"strong"}]}]}]},{"type":"tableCell","attrs":{"background":"#ace5fe"},"content":[{"type":"paragraph","content":[{"type":"text","text":"SKU Count","marks":[{"type":"strong"}]}]}]},{"type":"tableCell","attrs":{"background":"#ace5fe"},"content":[{"type":"paragraph","content":[{"type":"text","text":"Option Count","marks":[{"type":"strong"}]}]}]}]},{"type":"tableRow","content":[{"type":"tableCell","attrs":{"background":"white"},"content":[{"type":"paragraph","content":[{"type":"text","text":"Received"}]}]},{"type":"tableCell","attrs":{},"content":[{"type":"paragraph","content":[{"type":"text","text":"14"}]}]},{"type":"tableCell","attrs":{},"content":[{"type":"paragraph","content":[{"type":"text","text":"14"}]}]}]},{"type":"tableRow","content":[{"type":"tableCell","attrs":{"background":"white"},"content":[{"type":"paragraph","content":[{"type":"text","text":"Uploaded"}]}]},{"type":"tableCell","attrs":{},"content":[{"type":"paragraph","content":[{"type":"text","text":"6"}]}]},{"type":"tableCell","attrs":{},"content":[{"type":"paragraph","content":[{"type":"text","text":"6"}]}]}]},{"type":"tableRow","content":[{"type":"tableCell","attrs":{"background":"white"},"content":[{"type":"paragraph","content":[{"type":"text","text":"SKUs not uploaded"}]}]},{"type":"tableCell","attrs":{},"content":[{"type":"paragraph","content":[{"type":"text","text":"2"}]}]},{"type":"tableCell","attrs":{},"content":[{"type":"paragraph","content":[{"type":"text","text":"2"}]}]}]},{"type":"tableRow","content":[{"type":"tableCell","attrs":{"background":"white"},"content":[{"type":"paragraph","content":[{"type":"text","text":"Already Listed"}]}]},{"type":"tableCell","attrs":{},"content":[{"type":"paragraph","content":[{"type":"text","text":"6"}]}]},{"type":"tableCell","attrs":{},"content":[{"type":"paragraph","content":[{"type":"text","text":"6"}]}]}]},{"type":"tableRow","content":[{"type":"tableCell","attrs":{"background":"white"},"content":[{"type":"paragraph","content":[{"type":"text","text":"LIDs Shared"}]}]},{"type":"tableCell","attrs":{},"content":[{"type":"paragraph","content":[{"type":"text","text":"6"}]}]},{"type":"tableCell","attrs":{},"content":[{"type":"paragraph","content":[{"type":"text","text":"6"}]}]}]},{"type":"tableRow","content":[{"type":"tableCell","attrs":{"background":"white"},"content":[{"type":"paragraph","content":[{"type":"text","text":"LIDs Stuck in the System"}]}]},{"type":"tableCell","attrs":{},"content":[{"type":"paragraph","content":[{"type":"text","text":"0"}]}]},{"type":"tableCell","attrs":{},"content":[{"type":"paragraph","content":[{"type":"text","text":"0"}]}]}]}]} {adf} With this, we are closing this request from our end. Thank you for your patience, support, and cooperation throughout the process. Your brand is important to us, and we look forward to assisting you again | S53: =IF(OR(G53="",H53=""),"",ROUND(H53-G53,2)) -> 15.7
A54: UCW-30729 | B54: ENRICH_Kiddopanti Image Change Request 4th_May_2026 | C54: CLOSED | D54: Medium | E54: netscribes | F54: Mohd Tahir Shaikh | G54: 46147.785 | H54: 46153.428 | I54: 12 | J54: Ad-hoc | K54: Retrigger Image | L54: Kids | M54: 12 | N54: 2 | O54: 2 | P54: Kiddopanti | Q54: Mall | S54: =IF(OR(G54="",H54=""),"",ROUND(H54-G54,2)) -> 5.64
A55: UCW-30733 | B55: Tata Versace GWP Cataloguing 17th Apr | C55: CLOSED | D55: Medium | E55: Chirag Dubal | F55: Simi Raichel Zachariah | G55: 46147.794 | H55: 46154.679 | I55: 12 | J55: E2E | K55: E2E | L55: Beauty & Grooming | M55: 12 | N55: 12 | O55: 12 | P55: Versace | Q55: Mall;Luxury | R55: We have successfully uploaded this batch. Please find the attached summary sheet and summary report.[^Post Upload Status.xlsx] [^ProductBulkUpload_125928_Beauty__Grooming(MPH22)_Fragrances_and_Perfumes(MPH2211)_Fragrances(MPH2211100)_Perfumes(MPH2211100104)_33887_1778487431461_20260511_014711_669_summary.csv] ;[^UCW-30733.xlsx] Please find attached the sheet, where 12 options have been listed. Kindly update the price and inventory, and share the summary once completed. {adf:display=block} {"type":"table","attrs":{"isNumberColumnEnabled":false,"layout":"center","localId":"3d8c6fe0-19d3-4676-9bb8-d18914ae0e61"},"content":[{"type":"tableRow","content":[{"type":"tableCell","attrs":{"background":"#44b3e1"},"content":[{"type":"paragraph","content":[{"type":"text","text":"Ticket ID","marks":[{"type":"strong"}]}]}]},{"type":"tableCell","attrs":{"colspan":2,"background":"#44b3e1"},"content":[{"type":"paragraph","content":[{"type":"text","text":"UCW-30733","marks":[{"type":"strong"}]}]}]}]},{"type":"tableRow","content":[{"type":"tableCell","attrs":{"background":"#44b3e1"},"content":[{"type":"paragraph","content":[{"type":"text","text":"Brand Name","marks":[{"type":"strong"}]}]}]},{"type":"tableCell","attrs":{"colspan":2,"background":"#44b3e1"},"content":[{"type":"paragraph","content":[{"type":"text","text":"Versace ","marks":[{"type":"strong"}]}]}]}]},{"type":"tableRow","content":[{"type":"tableCell","attrs":{"background":"#ace5fe"},"content":[{"type":"paragraph","content":[{"type":"text","text":"Platform","marks":[{"type":"strong"}]}]}]},{"type":"tableCell","attrs":{"colspan":2,"background":"#ace5fe"},"content":[{"type":"paragraph","content":[{"type":"text","text":"Mall + Luxury","marks":[{"type":"strong"}]}]}]}]},{"type":"tableRow","content":[{"type":"tableCell","attrs":{"background":"#ace5fe"},"content":[{"type":"paragraph","content":[{"type":"text","text":"Particulars","marks":[{"type":"strong"}]}]}]},{"type":"tableCell","attrs":{"background":"#ace5fe"},"content":[{"type":"paragraph","content":[{"type":"text","text":"SKU Count","marks":[{"type":"strong"}]}]}]},{"type":"tableCell","attrs":{"background":"#ace5fe"},"content":[{"type":"paragraph","content":[{"type":"text","text":"Option Count","marks":[{"type":"strong"}]}]}]}]},{"type":"tableRow","content":[{"type":"tableCell","attrs":{"background":"white"},"content":[{"type":"paragraph","content":[{"type":"text","text":"Received"}]}]},{"type":"tableCell","attrs":{},"content":[{"type":"paragraph","content":[{"type":"text","text":"12"}]}]},{"type":"tableCell","attrs":{},"content":[{"type":"paragraph","content":[{"type":"text","text":"12"}]}]}]},{"type":"tableRow","content":[{"type":"tableCell","attrs":{"background":"white"},"content":[{"type":"paragraph","content":[{"type":"text","text":"Uploaded"}]}]},{"type":"tableCell","attrs":{},"content":[{"type":"paragraph","content":[{"type":"text","text":"12"}]}]},{"type":"tableCell","attrs":{},"content":[{"type":"paragraph","content":[{"type":"text","text":"12"}]}]}]},{"type":"tableRow","content":[{"type":"tableCell","attrs":{"background":"white"},"content":[{"type":"paragraph","content":[{"type":"text","text":"LIDs Shared"}]}]},{"type":"tableCell","attrs":{},"content":[{"type":"paragraph","content":[{"type":"text","text":"12"}]}]},{"type":"tableCell","attrs":{},"content":[{"type":"paragraph","content":[{"type":"text","text":"12"}]}]}]},{"type":"tableRow","content":[{"type":"tableCell","attrs":{"background":"white"},"content":[{"type":"paragraph","content":[{"type":"text","text":"LIDs Stuck in the System"}]}]},{"type":"tableCell","attrs":{},"content":[{"type":"paragraph","content":[{"type":"text","text":"0"}]}]},{"type":"tableCell","attrs":{},"content":[{"type":"paragraph","content":[{"type":"text","text":"0"}]}]}]}]} {adf} | S55: =IF(OR(G55="",H55=""),"",ROUND(H55-G55,2)) -> 6.88
A56: UCW-30744 | B56: NEEMANS+FOOTWEAR+ 125173+ 04-05-2026 | C56: CLOSED | D56: Medium | E56: netscribes | F56: Mohd Tahir Shaikh | G56: 46148.455 | H56: 46154.617 | I56: 104 | J56: E2E | K56: E2E | L56: Footwear | M56: 104 | N56: 15 | O56: 15 | P56: Neemans | Q56: Mall | R56: We have successfully uploaded this batch. Please find the attached summary sheet and summary report.[^Post Upload Status_V.2 (1).xlsx] [^Summary.zip] ;[^UCW-30744.xlsx] Please find attached the sheet, where 15 options have been listed. Kindly update the price and inventory, and share the summary once completed. {adf:display=block} {"type":"table","attrs":{"isNumberColumnEnabled":false,"layout":"center","localId":"d350b65f-cdf1-4d0a-8fd4-d49699209985"},"content":[{"type":"tableRow","content":[{"type":"tableCell","attrs":{"background":"#44b3e1"},"content":[{"type":"paragraph","content":[{"type":"text","text":"Ticket ID","marks":[{"type":"strong"}]}]}]},{"type":"tableCell","attrs":{"colspan":2,"background":"#44b3e1"},"content":[{"type":"paragraph","content":[{"type":"text","text":"UCW-30744","marks":[{"type":"strong"}]}]}]}]},{"type":"tableRow","content":[{"type":"tableCell","attrs":{"background":"#44b3e1"},"content":[{"type":"paragraph","content":[{"type":"text","text":"Brand Name","marks":[{"type":"strong"}]}]}]},{"type":"tableCell","attrs":{"colspan":2,"background":"#44b3e1"},"content":[{"type":"paragraph","content":[{"type":"text","text":"Neemans","marks":[{"type":"strong"}]}]}]}]},{"type":"tableRow","content":[{"type":"tableCell","attrs":{"background":"#ace5fe"},"content":[{"type":"paragraph","content":[{"type":"text","text":"Platform","marks":[{"type":"strong"}]}]}]},{"type":"tableCell","attrs":{"colspan":2,"background":"#ace5fe"},"content":[{"type":"paragraph","content":[{"type":"text","text":"Mall","marks":[{"type":"strong"}]}]}]}]},{"type":"tableRow","content":[{"type":"tableCell","attrs":{"background":"#ace5fe"},"content":[{"type":"paragraph","content":[{"type":"text","text":"Particulars","marks":[{"type":"strong"}]}]}]},{"type":"tableCell","attrs":{"background":"#ace5fe"},"content":[{"type":"paragraph","content":[{"type":"text","text":"SKU Count","marks":[{"type":"strong"}]}]}]},{"type":"tableCell","attrs":{"background":"#ace5fe"},"content":[{"type":"paragraph","content":[{"type":"text","text":"Option Count","marks":[{"type":"strong"}]}]}]}]},{"type":"tableRow","content":[{"type":"tableCell","attrs":{"background":"white"},"content":[{"type":"paragraph","content":[{"type":"text","text":"Received"}]}]},{"type":"tableCell","attrs":{},"content":[{"type":"paragraph","content":[{"type":"text","text":"104"}]}]},{"type":"tableCell","attrs":{},"content":[{"type":"paragraph","content":[{"type":"text","text":"15"}]}]}]},{"type":"tableRow","content":[{"type":"tableCell","attrs":{"background":"white"},"content":[{"type":"paragraph","content":[{"type":"text","text":"Uploaded"}]}]},{"type":"tableCell","attrs":{},"content":[{"type":"paragraph","content":[{"type":"text","text":"104"}]}]},{"type":"tableCell","attrs":{},"content":[{"type":"paragraph","content":[{"type":"text","text":"15"}]}]}]},{"type":"tableRow","content":[{"type":"tableCell","attrs":{"background":"white"},"content":[{"type":"paragraph","content":[{"type":"text","text":"LIDs Shared"}]}]},{"type":"tableCell","attrs":{},"content":[{"type":"paragraph","content":[{"type":"text","text":"104"}]}]},{"type":"tableCell","attrs":{},"content":[{"type":"paragraph","content":[{"type":"text","text":"15"}]}]}]},{"type":"tableRow","content":[{"type":"tableCell","attrs":{"background":"white"},"content":[{"type":"paragraph","content":[{"type":"text","text":"LIDs Stuck in the System"}]}]},{"type":"tableCell","attrs":{},"content":[{"type":"paragraph","content":[{"type":"text","text":"0"}]}]},{"type":"tableCell","attrs":{},"content":[{"type":"paragraph","content":[{"type":"text","text":"0"}]}]}]}]} {adf} | S56: =IF(OR(G56="",H56=""),"",ROUND(H56-G56,2)) -> 6.16
A57: UCW-30745 | B57: CLONE - NOYRA - 6 Mar 26 - 126542 - New collection - Luxury | C57: CLOSED | D57: Medium | E57: netscribes | F57: netscribes | G57: 46148.456 | H57: 46149.729 | I57: 5 | J57: E2E | K57: E2E | L57: Jewellery | M57: 5 | N57: 5 | O57: 5 | P57: NOYRA | Q57: Luxury | R57: PFA the Summary & Post-uploaded sheet[^Summary Remanning (2).zip] [^UCW-28713 Post Upload Status_V.2 (1).xlsx] ;[^UCW-30745_LID.xlsx] Hi [@Noyra India|mailto:noyra.co.in@gmail.com], 5 options have been listed. Kindly update the price and inventory details and share the summary once the updates are completed. Please find the consolidated report attached below. {adf:display=block} {"type":"table","attrs":{"isNumberColumnEnabled":false,"layout":"center","localId":"2bd3dfc2-f877-4d4e-8a08-aaefb65bdd70"},"content":[{"type":"tableRow","content":[{"type":"tableCell","attrs":{"background":"#44b3e1"},"content":[{"type":"paragraph","content":[{"type":"text","text":"Ticket ID","marks":[{"type":"strong"}]}]}]},{"type":"tableCell","attrs":{"colspan":2,"background":"#44b3e1"},"content":[{"type":"paragraph","content":[{"type":"text","text":"UCW-30745","marks":[{"type":"strong"}]}]}]}]},{"type":"tableRow","content":[{"type":"tableCell","attrs":{"background":"#44b3e1"},"content":[{"type":"paragraph","content":[{"type":"text","text":"Brand Name","marks":[{"type":"strong"}]}]}]},{"type":"tableCell","attrs":{"colspan":2,"background":"#44b3e1"},"content":[{"type":"paragraph","content":[{"type":"text","text":"NOYRA","marks":[{"type":"strong"}]}]}]}]},{"type":"tableRow","content":[{"type":"tableCell","attrs":{"background":"#44b3e1"},"content":[{"type":"paragraph","content":[{"type":"text","text":"Platform","marks":[{"type":"strong"}]}]}]},{"type":"tableCell","attrs":{"colspan":2,"background":"#44b3e1"},"content":[{"type":"paragraph","content":[{"type":"text","text":"Luxury","marks":[{"type":"strong"}]}]}]}]},{"type":"tableRow","content":[{"type":"tableCell","attrs":{"background":"#ace5fe"},"content":[{"type":"paragraph","content":[{"type":"text","text":"Particulars","marks":[{"type":"strong"}]}]}]},{"type":"tableCell","attrs":{"background":"#ace5fe"},"content":[{"type":"paragraph","content":[{"type":"text","text":"SKU Count","marks":[{"type":"strong"}]}]}]},{"type":"tableCell","attrs":{"background":"#ace5fe"},"content":[{"type":"paragraph","content":[{"type":"text","text":"Option Count","marks":[{"type":"strong"}]}]}]}]},{"type":"tableRow","content":[{"type":"tableCell","attrs":{"background":"white"},"content":[{"type":"paragraph","content":[{"type":"text","text":"Received"}]}]},{"type":"tableCell","attrs":{"background":"white"},"content":[{"type":"paragraph","content":[{"type":"text","text":"111"}]}]},{"type":"tableCell","attrs":{"background":"white"},"content":[{"type":"paragraph","content":[{"type":"text","text":"111"}]}]}]},{"type":"tableRow","content":[{"type":"tableCell","attrs":{"background":"white"},"content":[{"type":"paragraph","content":[{"type":"text","text":"Uploaded"}]}]},{"type":"tableCell","attrs":{"background":"white"},"content":[{"type":"paragraph","content":[{"type":"text","text":"44"}]}]},{"type":"tableCell","attrs":{"background":"white"},"content":[{"type":"paragraph","content":[{"type":"text","text":"44"}]}]}]},{"type":"tableRow","content":[{"type":"tableCell","attrs":{"background":"white"},"content":[{"type":"paragraph","content":[{"type":"text","text":"Not Uploaded"}]}]},{"type":"tableCell","attrs":{"background":"white"},"content":[{"type":"paragraph","content":[{"type":"text","text":"67"}]}]},{"type":"tableCell","attrs":{"background":"white"},"content":[{"type":"paragraph","content":[{"type":"text","text":"67"}]}]}]},{"type":"tableRow","content":[{"type":"tableCell","attrs":{"background":"white"},"content":[{"type":"paragraph","content":[{"type":"text","text":"LIDs Shared"}]}]},{"type":"tableCell","attrs":{"background":"white"},"content":[{"type":"paragraph","content":[{"type":"text","text":"44"}]}]},{"type":"tableCell","attrs":{"background":"white"},"content":[{"type":"paragraph","content":[{"type":"text","text":"44"}]}]}]},{"type":"tableRow","content":[{"type":"tableCell","attrs":{"background":"white"},"content":[{"type":"paragraph","content":[{"type":"text","text":"LIDs Stuck in the System"}]}]},{"type":"tableCell","attrs":{"background":"white"},"content":[{"type":"paragraph","content":[{"type":"text","text":"0"}]}]},{"type":"tableCell","attrs":{"background":"white"},"content":[{"type":"paragraph","content":[{"type":"text","text":"0"}]}]}]}]} {adf} Regards, Team Netscribes | S57: =IF(OR(G57="",H57=""),"",ROUND(H57-G57,2)) -> 1.27
A58: UCW-30746 | B58: Miarcus -15 Styles-SS 26- 05 May | C58: CLOSED | D58: Medium | E58: netscribes | F58: Mohd Tahir Shaikh | G58: 46148.463 | H58: 46154.503 | I58: 15 | J58: E2E | K58: E2E | L58: Kids | M58: 15 | N58: 15 | O58: 15 | P58: Miarcus | Q58: Mall | R58: We would like to inform you that your ticket has been successfully uploaded in our system. Please find the attached summary files and post-processing file for your reference. We will share a further update once the listing IDs are generated.[^Summary.zip] [^UCW-30746 - Post Upload Status .xlsx] ;[^UCW-30746.xlsx] Please find attached the sheet, where 15 options have been listed. Kindly update the price and inventory, and share the summary once completed. {adf:display=block} {"type":"table","attrs":{"isNumberColumnEnabled":false,"layout":"center","localId":"5a12a480-4099-41d0-9d58-b42de96b65d2"},"content":[{"type":"tableRow","content":[{"type":"tableCell","attrs":{"background":"#44b3e1"},"content":[{"type":"paragraph","content":[{"type":"text","text":"Ticket ID","marks":[{"type":"strong"}]}]}]},{"type":"tableCell","attrs":{"colspan":2,"background":"#44b3e1"},"content":[{"type":"paragraph","content":[{"type":"text","text":"UCW-30746","marks":[{"type":"strong"}]}]}]}]},{"type":"tableRow","content":[{"type":"tableCell","attrs":{"background":"#44b3e1"},"content":[{"type":"paragraph","content":[{"type":"text","text":"Brand Name","marks":[{"type":"strong"}]}]}]},{"type":"tableCell","attrs":{"colspan":2,"background":"#44b3e1"},"content":[{"type":"paragraph","content":[{"type":"text","text":"Miarcus","marks":[{"type":"strong"}]}]}]}]},{"type":"tableRow","content":[{"type":"tableCell","attrs":{"background":"#ace5fe"},"content":[{"type":"paragraph","content":[{"type":"text","text":"Platform","marks":[{"type":"strong"}]}]}]},{"type":"tableCell","attrs":{"colspan":2,"background":"#ace5fe"},"content":[{"type":"paragraph","content":[{"type":"text","text":"Mall","marks":[{"type":"strong"}]}]}]}]},{"type":"tableRow","content":[{"type":"tableCell","attrs":{"background":"#ace5fe"},"content":[{"type":"paragraph","content":[{"type":"text","text":"Particulars","marks":[{"type":"strong"}]}]}]},{"type":"tableCell","attrs":{"background":"#ace5fe"},"content":[{"type":"paragraph","content":[{"type":"text","text":"SKU Count","marks":[{"type":"strong"}]}]}]},{"type":"tableCell","attrs":{"background":"#ace5fe"},"content":[{"type":"paragraph","content":[{"type":"text","text":"Option Count","marks":[{"type":"strong"}]}]}]}]},{"type":"tableRow","content":[{"type":"tableCell","attrs":{"background":"white"},"content":[{"type":"paragraph","content":[{"type":"text","text":"Received"}]}]},{"type":"tableCell","attrs":{},"content":[{"type":"paragraph","content":[{"type":"text","text":"15"}]}]},{"type":"tableCell","attrs":{},"content":[{"type":"paragraph","content":[{"type":"text","text":"15"}]}]}]},{"type":"tableRow","content":[{"type":"tableCell","attrs":{"background":"white"},"content":[{"type":"paragraph","content":[{"type":"text","text":"Uploaded"}]}]},{"type":"tableCell","attrs":{},"content":[{"type":"paragraph","content":[{"type":"text","text":"15"}]}]},{"type":"tableCell","attrs":{},"content":[{"type":"paragraph","content":[{"type":"text","text":"15"}]}]}]},{"type":"tableRow","content":[{"type":"tableCell","attrs":{"background":"white"},"content":[{"type":"paragraph","content":[{"type":"text","text":"LIDs Shared"}]}]},{"type":"tableCell","attrs":{},"content":[{"type":"paragraph","content":[{"type":"text","text":"15"}]}]},{"type":"tableCell","attrs":{},"content":[{"type":"paragraph","content":[{"type":"text","text":"15"}]}]}]},{"type":"tableRow","content":[{"type":"tableCell","attrs":{"background":"white"},"content":[{"type":"paragraph","content":[{"type":"text","text":"LIDs Stuck in the System"}]}]},{"type":"tableCell","attrs":{},"content":[{"type":"paragraph","content":[{"type":"text","text":"0"}]}]},{"type":"tableCell","attrs":{},"content":[{"type":"paragraph","content":[{"type":"text","text":"0"}]}]}]}]} {adf} | S58: =IF(OR(G58="",H58=""),"",ROUND(H58-G58,2)) -> 6.04
A59: UCW-30748 | B59: Miarcus -17 Styles-SS 26- 05 May | C59: CLOSED | D59: Medium | E59: netscribes | F59: Mohd Tahir Shaikh | G59: 46148.467 | H59: 46154.528 | I59: 17 | J59: E2E | K59: E2E | L59: Kids | M59: 17 | N59: 17 | O59: 17 | P59: Miarcus | Q59: Mall | R59: We would like to inform you that your ticket has been successfully uploaded in our system. Please find the attached summary files and post-upload file for your reference. We will share a further update once the listing IDs are generated.[^Summary.zip] [^UCW-30748 - Post Upload Status .xlsx] ;[^UCW-30748.xlsx] Please find attached the sheet, where 17 options have been listed. Kindly update the price and inventory, and share the summary once completed. {adf:display=block} {"type":"table","attrs":{"isNumberColumnEnabled":false,"layout":"center","localId":"19a12a0f-f25f-4149-9bc8-3073138ab5e4"},"content":[{"type":"tableRow","content":[{"type":"tableCell","attrs":{"background":"#44b3e1"},"content":[{"type":"paragraph","content":[{"type":"text","text":"Ticket ID","marks":[{"type":"strong"}]}]}]},{"type":"tableCell","attrs":{"colspan":2,"background":"#44b3e1"},"content":[{"type":"paragraph","content":[{"type":"text","text":"UCW-30748","marks":[{"type":"strong"}]}]}]}]},{"type":"tableRow","content":[{"type":"tableCell","attrs":{"background":"#44b3e1"},"content":[{"type":"paragraph","content":[{"type":"text","text":"Brand Name","marks":[{"type":"strong"}]}]}]},{"type":"tableCell","attrs":{"colspan":2,"background":"#44b3e1"},"content":[{"type":"paragraph","content":[{"type":"text","text":"Miarcus","marks":[{"type":"strong"}]}]}]}]},{"type":"tableRow","content":[{"type":"tableCell","attrs":{"background":"#ace5fe"},"content":[{"type":"paragraph","content":[{"type":"text","text":"Platform","marks":[{"type":"strong"}]}]}]},{"type":"tableCell","attrs":{"colspan":2,"background":"#ace5fe"},"content":[{"type":"paragraph","content":[{"type":"text","text":"Mall","marks":[{"type":"strong"}]}]}]}]},{"type":"tableRow","content":[{"type":"tableCell","attrs":{"background":"#ace5fe"},"content":[{"type":"paragraph","content":[{"type":"text","text":"Particulars","marks":[{"type":"strong"}]}]}]},{"type":"tableCell","attrs":{"background":"#ace5fe"},"content":[{"type":"paragraph","content":[{"type":"text","text":"SKU Count","marks":[{"type":"strong"}]}]}]},{"type":"tableCell","attrs":{"background":"#ace5fe"},"content":[{"type":"paragraph","content":[{"type":"text","text":"Option Count","marks":[{"type":"strong"}]}]}]}]},{"type":"tableRow","content":[{"type":"tableCell","attrs":{"background":"white"},"content":[{"type":"paragraph","content":[{"type":"text","text":"Received"}]}]},{"type":"tableCell","attrs":{},"content":[{"type":"paragraph","content":[{"type":"text","text":"17"}]}]},{"type":"tableCell","attrs":{},"content":[{"type":"paragraph","content":[{"type":"text","text":"17"}]}]}]},{"type":"tableRow","content":[{"type":"tableCell","attrs":{"background":"white"},"content":[{"type":"paragraph","content":[{"type":"text","text":"Uploaded"}]}]},{"type":"tableCell","attrs":{},"content":[{"type":"paragraph","content":[{"type":"text","text":"17"}]}]},{"type":"tableCell","attrs":{},"content":[{"type":"paragraph","content":[{"type":"text","text":"17"}]}]}]},{"type":"tableRow","content":[{"type":"tableCell","attrs":{"background":"white"},"content":[{"type":"paragraph","content":[{"type":"text","text":"LIDs Shared"}]}]},{"type":"tableCell","attrs":{},"content":[{"type":"paragraph","content":[{"type":"text","text":"17"}]}]},{"type":"tableCell","attrs":{},"content":[{"type":"paragraph","content":[{"type":"text","text":"17"}]}]}]},{"type":"tableRow","content":[{"type":"tableCell","attrs":{"background":"white"},"content":[{"type":"paragraph","content":[{"type":"text","text":"LIDs Stuck in the System"}]}]},{"type":"tableCell","attrs":{},"content":[{"type":"paragraph","content":[{"type":"text","text":"0"}]}]},{"type":"tableCell","attrs":{},"content":[{"type":"paragraph","content":[{"type":"text","text":"0"}]}]}]}]} {adf} | S59: =IF(OR(G59="",H59=""),"",ROUND(H59-G59,2)) -> 6.06
A60: UCW-30751 | B60: Miarcus -20 Styles-SS 26- 04 May | C60: CLOSED | D60: Medium | E60: netscribes | F60: Mohd Tahir Shaikh | G60: 46148.471 | H60: 46154.617 | I60: 20 | J60: E2E | K60: E2E | L60: Kids | M60: 19 | N60: 19 | O60: 20 | P60: Miarcus | Q60: Mall | R60: We would like to inform you that your ticket has been successfully uploaded in our system. Please find the attached summary files and post-upload file for your reference. We will share a further update once the listing IDs are generated.[^Summary.zip] [^UCW-30751 - Post Upload Status .xlsx] ;[^UCW-30751.xlsx] Please find attached the sheet, where 19 options of Accessories have been listed. Kindly update the price and inventory, and share the summary once completed. {adf:display=block} {"type":"table","attrs":{"isNumberColumnEnabled":false,"layout":"center","localId":"96500313-1f1f-49e9-9678-0ff2a55907fa"},"content":[{"type":"tableRow","content":[{"type":"tableCell","attrs":{"background":"#44b3e1"},"content":[{"type":"paragraph","content":[{"type":"text","text":"Ticket ID","marks":[{"type":"strong"}]}]}]},{"type":"tableCell","attrs":{"colspan":2,"background":"#44b3e1"},"content":[{"type":"paragraph","content":[{"type":"text","text":"UCW-30751","marks":[{"type":"strong"}]}]}]}]},{"type":"tableRow","content":[{"type":"tableCell","attrs":{"background":"#44b3e1"},"content":[{"type":"paragraph","content":[{"type":"text","text":"Brand Name","marks":[{"type":"strong"}]}]}]},{"type":"tableCell","attrs":{"colspan":2,"background":"#44b3e1"},"content":[{"type":"paragraph","content":[{"type":"text","text":"Mi Arcus","marks":[{"type":"strong"}]}]}]}]},{"type":"tableRow","content":[{"type":"tableCell","attrs":{"background":"#ace5fe"},"content":[{"type":"paragraph","content":[{"type":"text","text":"Platform","marks":[{"type":"strong"}]}]}]},{"type":"tableCell","attrs":{"colspan":2,"background":"#ace5fe"},"content":[{"type":"paragraph","content":[{"type":"text","text":"Mall","marks":[{"type":"strong"}]}]}]}]},{"type":"tableRow","content":[{"type":"tableCell","attrs":{"background":"#ace5fe"},"content":[{"type":"paragraph","content":[{"type":"text","text":"Particulars","marks":[{"type":"strong"}]}]}]},{"type":"tableCell","attrs":{"background":"#ace5fe"},"content":[{"type":"paragraph","content":[{"type":"text","text":"SKU Count","marks":[{"type":"strong"}]}]}]},{"type":"tableCell","attrs":{"background":"#ace5fe"},"content":[{"type":"paragraph","content":[{"type":"text","text":"Option Count","marks":[{"type":"strong"}]}]}]}]},{"type":"tableRow","content":[{"type":"tableCell","attrs":{"background":"white"},"content":[{"type":"paragraph","content":[{"type":"text","text":"Received"}]}]},{"type":"tableCell","attrs":{},"content":[{"type":"paragraph","content":[{"type":"text","text":"20"}]}]},{"type":"tableCell","attrs":{},"content":[{"type":"paragraph","content":[{"type":"text","text":"20"}]}]}]},{"type":"tableRow","content":[{"type":"tableCell","attrs":{"background":"white"},"content":[{"type":"paragraph","content":[{"type":"text","text":"Uploaded"}]}]},{"type":"tableCell","attrs":{},"content":[{"type":"paragraph","content":[{"type":"text","text":"19"}]}]},{"type":"tableCell","attrs":{},"content":[{"type":"paragraph","content":[{"type":"text","text":"19"}]}]}]},{"type":"tableRow","content":[{"type":"tableCell","attrs":{"background":"white"},"content":[{"type":"paragraph","content":[{"type":"text","text":"SKUs Not Uploaded- Image Issue"}]}]},{"type":"tableCell","attrs":{},"content":[{"type":"paragraph","content":[{"type":"text","text":"1"}]}]},{"type":"tableCell","attrs":{},"content":[{"type":"paragraph","content":[{"type":"text","text":"1"}]}]}]},{"type":"tableRow","content":[{"type":"tableCell","attrs":{"background":"white"},"content":[{"type":"paragraph","content":[{"type":"text","text":"LIDs Shared"}]}]},{"type":"tableCell","attrs":{},"content":[{"type":"paragraph","content":[{"type":"text","text":"19"}]}]},{"type":"tableCell","attrs":{},"content":[{"type":"paragraph","content":[{"type":"text","text":"19"}]}]}]},{"type":"tableRow","content":[{"type":"tableCell","attrs":{"background":"white"},"content":[{"type":"paragraph","content":[{"type":"text","text":"LIDs Stuck in the System"}]}]},{"type":"tableCell","attrs":{},"content":[{"type":"paragraph","content":[{"type":"text","text":"0"}]}]},{"type":"tableCell","attrs":{},"content":[{"type":"paragraph","content":[{"type":"text","text":"0"}]}]}]}]} {adf} | S60: =IF(OR(G60="",H60=""),"",ROUND(H60-G60,2)) -> 6.15
A61: UCW-30752 | B61: Clone-The Souled Store Footwear 123858 20-03-2026 | C61: CLOSED | D61: Medium | E61: netscribes | F61: netscribes | G61: 46148.472 | H61: 46155.735 | I61: 160 | J61: E2E | K61: E2E | L61: Footwear | M61: 160 | N61: 25 | O61: 25 | P61: The Souled Store | Q61: Mall | R61: We have successfully uploaded this batch. Please find the attached summary sheet and summary report.[^Post Upload Status_V.2 (1).xlsx] [^Summary.zip] ;[^UCW-30752_LID.xlsx] Hi [@Sahil Sonawane|mailto:sahil.sonawane@thesouledstore.com], Please find attached the sheet, where 25 options have been listed. Kindly update the price and inventory, and share the summary once completed. {adf:display=block} {"type":"table","attrs":{"isNumberColumnEnabled":false,"layout":"center","localId":"2f66b77e-d383-4cf6-9105-90a79560baa0"},"content":[{"type":"tableRow","content":[{"type":"tableCell","attrs":{"background":"#44b3e1"},"content":[{"type":"paragraph","content":[{"type":"text","text":"Ticket ID","marks":[{"type":"strong"}]}]}]},{"type":"tableCell","attrs":{"colspan":2,"background":"#44b3e1"},"content":[{"type":"paragraph","content":[{"type":"text","text":"UCW-30752","marks":[{"type":"strong"}]}]}]}]},{"type":"tableRow","content":[{"type":"tableCell","attrs":{"background":"#44b3e1"},"content":[{"type":"paragraph","content":[{"type":"text","text":"Brand Name","marks":[{"type":"strong"}]}]}]},{"type":"tableCell","attrs":{"colspan":2,"background":"#44b3e1"},"content":[{"type":"paragraph","content":[{"type":"text","text":"The Souled Store","marks":[{"type":"strong"}]}]}]}]},{"type":"tableRow","content":[{"type":"tableCell","attrs":{"background":"#44b3e1"},"content":[{"type":"paragraph","content":[{"type":"text","text":"Platform","marks":[{"type":"strong"}]}]}]},{"type":"tableCell","attrs":{"colspan":2,"background":"#44b3e1"},"content":[{"type":"paragraph","content":[{"type":"text","text":"Mall","marks":[{"type":"strong"}]}]}]}]},{"type":"tableRow","content":[{"type":"tableCell","attrs":{"background":"#ace5fe"},"content":[{"type":"paragraph","content":[{"type":"text","text":"Particulars","marks":[{"type":"strong"}]}]}]},{"type":"tableCell","attrs":{"background":"#ace5fe"},"content":[{"type":"paragraph","content":[{"type":"text","text":"SKU Count","marks":[{"type":"strong"}]}]}]},{"type":"tableCell","attrs":{"background":"#ace5fe"},"content":[{"type":"paragraph","content":[{"type":"text","text":"Option Count","marks":[{"type":"strong"}]}]}]}]},{"type":"tableRow","content":[{"type":"tableCell","attrs":{"background":"white"},"content":[{"type":"paragraph","content":[{"type":"text","text":"Received"}]}]},{"type":"tableCell","attrs":{"background":"white"},"content":[{"type":"paragraph","content":[{"type":"text","text":"160"}]}]},{"type":"tableCell","attrs":{"background":"white"},"content":[{"type":"paragraph","content":[{"type":"text","text":"25"}]}]}]},{"type":"tableRow","content":[{"type":"tableCell","attrs":{"background":"white"},"content":[{"type":"paragraph","content":[{"type":"text","text":"Uploaded"}]}]},{"type":"tableCell","attrs":{"background":"white"},"content":[{"type":"paragraph","content":[{"type":"text","text":"160"}]}]},{"type":"tableCell","attrs":{"background":"white"},"content":[{"type":"paragraph","content":[{"type":"text","text":"25"}]}]}]},{"type":"tableRow","content":[{"type":"tableCell","attrs":{"background":"white"},"content":[{"type":"paragraph","content":[{"type":"text","text":"Not Uploaded"}]}]},{"type":"tableCell","attrs":{"background":"white"},"content":[{"type":"paragraph","content":[{"type":"text","text":"0"}]}]},{"type":"tableCell","attrs":{"background":"white"},"content":[{"type":"paragraph","content":[{"type":"text","text":"0"}]}]}]},{"type":"tableRow","content":[{"type":"tableCell","attrs":{"background":"white"},"content":[{"type":"paragraph","content":[{"type":"text","text":"LIDs Shared"}]}]},{"type":"tableCell","attrs":{"background":"white"},"content":[{"type":"paragraph","content":[{"type":"text","text":"160"}]}]},{"type":"tableCell","attrs":{"background":"white"},"content":[{"type":"paragraph","content":[{"type":"text","text":"25"}]}]}]},{"type":"tableRow","content":[{"type":"tableCell","attrs":{"background":"white"},"content":[{"type":"paragraph","content":[{"type":"text","text":"LIDs Stuck in the System"}]}]},{"type":"tableCell","attrs":{"background":"white"},"content":[{"type":"paragraph","content":[{"type":"text","text":"0"}]}]},{"type":"tableCell","attrs":{"background":"white"},"content":[{"type":"paragraph","content":[{"type":"text","text":"0"}]}]}]}]} {adf} Regards, Team Netscribes | S61: =IF(OR(G61="",H61=""),"",ROUND(H61-G61,2)) -> 7.26
A62: UCW-30754 | B62: ENRICH_Tata Euroitala Hygiene check | C62: CLOSED | D62: Medium | E62: Chirag Dubal | F62: Shraddha Dighe | G62: 46148.476 | H62: 46167.678 | I62: 9 | J62: Ad-hoc | K62: Retrigger Content & Image | L62: Beauty & Grooming | M62: 9 | N62: 9 | O62: 9 | P62: Versace, Moschino | Q62: Luxury | R62: L1 ticket raised- [https://tatacliqhelpdesk.freshservice.com/support/tickets/213286|https://tatacliqhelpdesk.freshservice.com/support/tickets/213286];As discussed with shweta closing this | S62: =IF(OR(G62="",H62=""),"",ROUND(H62-G62,2)) -> 19.2 | U62: The TAT was high due to tech error
A63: UCW-30759 | B63: New listing seller 129577 | C63: CLOSED | D63: Medium | E63: Chirag Dubal | F63: Shraddha Dighe | G63: 46148.503 | H63: 46160.616 | I63: 9 | J63: Ad-hoc | K63: Sell Now - Bulk | L63: HOME | M63: 9 | N63: 6 | O63: 6 | P63: Apple | Q63: Mall | R63: [^Status Of UCW-30759.xlsx] ;sell now completed |SKU|MPID| |AP20WUSBC|MP000000008093500| |SAM65WOCAB|MP000000015391935| |APEARUSBCWIR|MP000000019481013| |AP1WOVENCAB60W|MP000000019481297| |AP1USBC2LIGHT|MP000000001403212| |SAM25WUSBCWOCAB|MP000000023274957| |SAM45WWOCAB|MP000000027095779| |GOG45W|MP000000027095778| |SAM45WUSBCWICAB|MP000000006870976| | S63: =IF(OR(G63="",H63=""),"",ROUND(H63-G63,2)) -> 12.11
A64: UCW-30762 | B64: Aurelia/W/Folksong/Elleven- 45 Style- Summer-2026- 16th April | C64: CLOSED | D64: Medium | E64: Chirag Dubal | F64: Shraddha Dighe | G64: 46148.519 | H64: 46158.571 | I64: 500 | J64: Ad-hoc | K64: Sell Now - Bulk | L64: Apparel | M64: 500 | N64: 84 | O64: 84 | P64: Aurelia, W, Folksong, Elleven | Q64: Mall | R64: [^Summary.zip] [^Status of UCW-30762.xlsx] We have done the sell now task, Here we attach the summery file for your reference. | S64: =IF(OR(G64="",H64=""),"",ROUND(H64-G64,2)) -> 10.05
A65: UCW-30763 | B65: Mapping listing lux to tata - 13 - Styles - Rockport | C65: CLOSED | D65: Medium | E65: netscribes | F65: Mohd Tahir Shaikh | G65: 46148.524 | H65: 46160.767 | I65: 70 | J65: E2E | K65: Dual Listing | L65: Footwear | M65: 59 | N65: 8 | O65: 11 | P65: Rockport | Q65: Mall | R65: We have uploaded those SKUs under seller code 126934. Please find the attached summary sheet for your reference. Once the LID is successfully generated, we will keep you updated. {adf:display=block} {"type":"table","attrs":{"isNumberColumnEnabled":false,"layout":"center","localId":"0fa63323-7a67-44e0-ab2f-70e561f04208"},"content":[{"type":"tableRow","content":[{"type":"tableCell","attrs":{},"content":[{"type":"paragraph","content":[{"type":"text","text":"Ticket ID"}]}]},{"type":"tableCell","attrs":{"colspan":2},"content":[{"type":"paragraph","content":[{"type":"text","text":"UCW-30763"}]}]}]},{"type":"tableRow","content":[{"type":"tableCell","attrs":{},"content":[{"type":"paragraph","content":[{"type":"text","text":"Brand Name"}]}]},{"type":"tableCell","attrs":{"colspan":2},"content":[{"type":"paragraph","content":[{"type":"text","text":"Rockport"}]}]}]},{"type":"tableRow","content":[{"type":"tableCell","attrs":{},"content":[{"type":"paragraph","content":[{"type":"text","text":"Platform"}]}]},{"type":"tableCell","attrs":{"colspan":2},"content":[{"type":"paragraph","content":[{"type":"text","text":"Marketplace"}]}]}]},{"type":"tableRow","content":[{"type":"tableCell","attrs":{},"content":[{"type":"paragraph","content":[{"type":"text","text":"Particulars"}]}]},{"type":"tableCell","attrs":{},"content":[{"type":"paragraph","content":[{"type":"text","text":"SKU Count"}]}]},{"type":"tableCell","attrs":{},"content":[{"type":"paragraph","content":[{"type":"text","text":"Option Count"}]}]}]},{"type":"tableRow","content":[{"type":"tableCell","attrs":{},"content":[{"type":"paragraph","content":[{"type":"text","text":"Received"}]}]},{"type":"tableCell","attrs":{},"content":[{"type":"paragraph","content":[{"type":"text","text":"70"}]}]},{"type":"tableCell","attrs":{},"content":[{"type":"paragraph","content":[{"type":"text","text":"11"}]}]}]},{"type":"tableRow","content":[{"type":"tableCell","attrs":{},"content":[{"type":"paragraph","content":[{"type":"text","text":"Failed"}]}]},{"type":"tableCell","attrs":{},"content":[{"type":"paragraph","content":[{"type":"text","text":"3"}]}]},{"type":"tableCell","attrs":{},"content":[{"type":"paragraph","content":[{"type":"text","text":"3"}]}]}]},{"type":"tableRow","content":[{"type":"tableCell","attrs":{},"content":[{"type":"paragraph","content":[{"type":"text","text":"Uploaded"}]}]},{"type":"tableCell","attrs":{},"content":[{"type":"paragraph","content":[{"type":"text","text":"67"}]}]},{"type":"tableCell","attrs":{},"content":[{"type":"paragraph","content":[{"type":"text","text":"8"}]}]}]}]} {adf} [^Summery.zip] [^Status of UCW-30763.xlsx] ;[^LID of UCW-30763.xlsx] Hi [@Vicky BMR|mailto:vicky@brandmanretail.com], The LIDs have been generated. Please refer to the below table for the report. Please find attached the LID file for your reference. {adf:display=block} {"type":"table","attrs":{"isNumberColumnEnabled":false,"layout":"center","localId":"ba65f2ad-4559-4939-8ecc-c6f6885e4822"},"content":[{"type":"tableRow","content":[{"type":"tableCell","attrs":{"background":"#61cbf3"},"content":[{"type":"paragraph","content":[{"type":"text","text":"Ticket ID","marks":[{"type":"strong"}]}]}]},{"type":"tableCell","attrs":{"colspan":2,"background":"#61cbf3"},"content":[{"type":"paragraph","content":[{"type":"text","text":"UCW-30763","marks":[{"type":"strong"}]}]}]}]},{"type":"tableRow","content":[{"type":"tableCell","attrs":{"background":"#61cbf3"},"content":[{"type":"paragraph","content":[{"type":"text","text":"Brand Name","marks":[{"type":"strong"}]}]}]},{"type":"tableCell","attrs":{"colspan":2,"background":"#61cbf3"},"content":[{"type":"paragraph","content":[{"type":"text","text":"Rockport","marks":[{"type":"strong"}]}]}]}]},{"type":"tableRow","content":[{"type":"tableCell","attrs":{"background":"#61cbf3"},"content":[{"type":"paragraph","content":[{"type":"text","text":"Platform","marks":[{"type":"strong"}]}]}]},{"type":"tableCell","attrs":{"colspan":2,"background":"#61cbf3"},"content":[{"type":"paragraph","content":[{"type":"text","text":"Marketplace","marks":[{"type":"strong"}]}]}]}]},{"type":"tableRow","content":[{"type":"tableCell","attrs":{"background":"#61cbf3"},"content":[{"type":"paragraph","content":[{"type":"text","text":"Particulars","marks":[{"type":"strong"}]}]}]},{"type":"tableCell","attrs":{"background":"#61cbf3"},"content":[{"type":"paragraph","content":[{"type":"text","text":"SKU Count","marks":[{"type":"strong"}]}]}]},{"type":"tableCell","attrs":{"background":"#61cbf3"},"content":[{"type":"paragraph","content":[{"type":"text","text":"Option Count","marks":[{"type":"strong"}]}]}]}]},{"type":"tableRow","content":[{"type":"tableCell","attrs":{"background":"white"},"content":[{"type":"paragraph","content":[{"type":"text","text":"Received"}]}]},{"type":"tableCell","attrs":{"background":"white"},"content":[{"type":"paragraph","content":[{"type":"text","text":"70"}]}]},{"type":"tableCell","attrs":{"background":"white"},"content":[{"type":"paragraph","content":[{"type":"text","text":"11"}]}]}]},{"type":"tableRow","content":[{"type":"tableCell","attrs":{"background":"white"},"content":[{"type":"paragraph","content":[{"type":"text","text":"Failed"}]}]},{"type":"tableCell","attrs":{"background":"white"},"content":[{"type":"paragraph","content":[{"type":"text","text":"3"}]}]},{"type":"tableCell","attrs":{"background":"white"},"content":[{"type":"paragraph","content":[{"type":"text","text":"3"}]}]}]},{"type":"tableRow","content":[{"type":"tableCell","attrs":{"background":"white"},"content":[{"type":"paragraph","content":[{"type":"text","text":"Uploaded"}]}]},{"type":"tableCell","attrs":{"background":"white"},"content":[{"type":"paragraph","content":[{"type":"text","text":"67"}]}]},{"type":"tableCell","attrs":{"background":"white"},"content":[{"type":"paragraph","content":[{"type":"text","text":"8"}]}]}]},{"type":"tableRow","content":[{"type":"tableCell","attrs":{"background":"white"},"content":[{"type":"paragraph","content":[{"type":"text","text":"Stuck in Rejected"}]}]},{"type":"tableCell","attrs":{"background":"white"},"content":[{"type":"paragraph","content":[{"type":"text","text":"8"}]}]},{"type":"tableCell","attrs":{"background":"white"},"content":[{"type":"paragraph","content":[{"type":"text","text":"0"}]}]}]},{"type":"tableRow","content":[{"type":"tableCell","attrs":{"background":"white"},"content":[{"type":"paragraph","content":[{"type":"text","text":"LID Shared"}]}]},{"type":"tableCell","attrs":{"background":"white"},"content":[{"type":"paragraph","content":[{"type":"text","text":"59"}]}]},{"type":"tableCell","attrs":{"background":"white"},"content":[{"type":"paragraph","content":[{"type":"text","text":"8"}]}]}]}]} {adf} Regards, Team Netscribes | S65: =IF(OR(G65="",H65=""),"",ROUND(H65-G65,2)) -> 12.24
A66: UCW-30769 | B66: ENRICH_TataCliq: AVI013-JB & LDOF-01 Category Article Image Updation | C66: CLOSED | D66: Medium | E66: netscribes | F66: Mohd Tahir Shaikh | G66: 46148.561 | H66: 46155.955 | I66: 36 | J66: Ad-hoc | K66: Retrigger Image | L66: Footwear | M66: 36 | N66: 6 | O66: 6 | P66: Louis Stitch | Q66: Mall | S66: =IF(OR(G66="",H66=""),"",ROUND(H66-G66,2)) -> 7.39
